[{"cardId":"por-12","name":"Decidueye ex","number":"12","rarity":"Double Rare","artist":"aky CG Works","imageUrl":"https://tcgcompanion.fra1.digitaloceanspaces.com/images/megaevolution/por/12.webp","imageUrlHiRes":"https://tcgcompanion.fra1.digitaloceanspaces.com/images/megaevolution/por/12_hires.webp","setSlug":"perfect-order","setName":"Perfect Order","setReleaseDate":"2026-03-27T00:00:00.000Z"},{"cardId":"por-31","name":"Mega Clefable ex","number":"31","rarity":"Double Rare","artist":"aky CG Works","imageUrl":"https://tcgcompanion.fra1.digitaloceanspaces.com/images/megaevolution/por/31.webp","imageUrlHiRes":"https://tcgcompanion.fra1.digitaloceanspaces.com/images/megaevolution/por/31_hires.webp","setSlug":"perfect-order","setName":"Perfect Order","setReleaseDate":"2026-03-27T00:00:00.000Z"},{"cardId":"por-103","name":"Mega Clefable ex","number":"103","rarity":"Rare Secret","artist":"aky CG Works","imageUrl":"https://tcgcompanion.fra1.digitaloceanspaces.com/images/megaevolution/por/103.webp","imageUrlHiRes":"https://tcgcompanion.fra1.digitaloceanspaces.com/images/megaevolution/por/103_hires.webp","setSlug":"perfect-order","setName":"Perfect Order","setReleaseDate":"2026-03-27T00:00:00.000Z"},{"cardId":"asc-22","name":"Mega Charizard Y ex","number":"22","rarity":"Double Rare","artist":"aky CG Works","imageUrl":"https://tcgcompanion.fra1.digitaloceanspaces.com/images/megaevolution/asc/22.webp","imageUrlHiRes":"https://tcgcompanion.fra1.digitaloceanspaces.com/images/megaevolution/asc/22_hires.webp","setSlug":"ascended-heroes","setName":"Ascended Heroes","setReleaseDate":"2026-01-30T00:00:00.000Z"},{"cardId":"asc-26","name":"Ethan's Ho-Oh ex","number":"26","rarity":"Double Rare","artist":"aky CG Works","imageUrl":"https://tcgcompanion.fra1.digitaloceanspaces.com/images/megaevolution/asc/26.webp","imageUrlHiRes":"https://tcgcompanion.fra1.digitaloceanspaces.com/images/megaevolution/asc/26_hires.webp","setSlug":"ascended-heroes","setName":"Ascended Heroes","setReleaseDate":"2026-01-30T00:00:00.000Z"},{"cardId":"asc-57","name":"Pikachu ex","number":"57","rarity":"Double Rare","artist":"aky CG Works","imageUrl":"https://tcgcompanion.fra1.digitaloceanspaces.com/images/megaevolution/asc/57.webp","imageUrlHiRes":"https://tcgcompanion.fra1.digitaloceanspaces.com/images/megaevolution/asc/57_hires.webp","setSlug":"ascended-heroes","setName":"Ascended Heroes","setReleaseDate":"2026-01-30T00:00:00.000Z"},{"cardId":"asc-79","name":"Team Rocket's Mewtwo ex","number":"79","rarity":"Double Rare","artist":"aky CG Works","imageUrl":"https://tcgcompanion.fra1.digitaloceanspaces.com/images/megaevolution/asc/79.webp","imageUrlHiRes":"https://tcgcompanion.fra1.digitaloceanspaces.com/images/megaevolution/asc/79_hires.webp","setSlug":"ascended-heroes","setName":"Ascended Heroes","setReleaseDate":"2026-01-30T00:00:00.000Z"},{"cardId":"asc-121","name":"Koraidon ex","number":"121","rarity":"Double Rare","artist":"aky CG Works","imageUrl":"https://tcgcompanion.fra1.digitaloceanspaces.com/images/megaevolution/asc/121.webp","imageUrlHiRes":"https://tcgcompanion.fra1.digitaloceanspaces.com/images/megaevolution/asc/121_hires.webp","setSlug":"ascended-heroes","setName":"Ascended Heroes","setReleaseDate":"2026-01-30T00:00:00.000Z"},{"cardId":"asc-152","name":"Mega Dragonite ex","number":"152","rarity":"Double Rare","artist":"aky CG Works","imageUrl":"https://tcgcompanion.fra1.digitaloceanspaces.com/images/megaevolution/asc/152.webp","imageUrlHiRes":"https://tcgcompanion.fra1.digitaloceanspaces.com/images/megaevolution/asc/152_hires.webp","setSlug":"ascended-heroes","setName":"Ascended Heroes","setReleaseDate":"2026-01-30T00:00:00.000Z"},{"cardId":"asc-294","name":"Mega Charizard Y ex","number":"294","rarity":"Rare Secret","artist":"aky CG Works","imageUrl":"https://tcgcompanion.fra1.digitaloceanspaces.com/images/megaevolution/asc/294.webp","imageUrlHiRes":"https://tcgcompanion.fra1.digitaloceanspaces.com/images/megaevolution/asc/294_hires.webp","setSlug":"ascended-heroes","setName":"Ascended Heroes","setReleaseDate":"2026-01-30T00:00:00.000Z"},{"cardId":"asc-295","name":"Mega Dragonite ex","number":"295","rarity":"Rare Secret","artist":"aky CG Works","imageUrl":"https://tcgcompanion.fra1.digitaloceanspaces.com/images/megaevolution/asc/295.webp","imageUrlHiRes":"https://tcgcompanion.fra1.digitaloceanspaces.com/images/megaevolution/asc/295_hires.webp","setSlug":"ascended-heroes","setName":"Ascended Heroes","setReleaseDate":"2026-01-30T00:00:00.000Z"},{"cardId":"pfl-41","name":"Mega Diancie ex","number":"41","rarity":"Double Rare","artist":"aky CG Works","imageUrl":"https://tcgcompanion.fra1.digitaloceanspaces.com/images/megaevolution/pfl/41.webp","imageUrlHiRes":"https://tcgcompanion.fra1.digitaloceanspaces.com/images/megaevolution/pfl/41_hires.webp","setSlug":"phantasmal-flames","setName":"Phantasmal Flames","setReleaseDate":"2025-11-14T00:00:00.000Z"},{"cardId":"meg-86","name":"Mega Absol ex","number":"86","rarity":"Double Rare","artist":"aky CG Works","imageUrl":"https://tcgcompanion.fra1.digitaloceanspaces.com/images/megaevolution/meg/86.webp","imageUrlHiRes":"https://tcgcompanion.fra1.digitaloceanspaces.com/images/megaevolution/meg/86_hires.webp","setSlug":"mega-evolution","setName":"Mega Evolution","setReleaseDate":"2025-09-25T23:00:00.000Z"},{"cardId":"meg-94","name":"Mega Mawile ex","number":"94","rarity":"Double Rare","artist":"aky CG Works","imageUrl":"https://tcgcompanion.fra1.digitaloceanspaces.com/images/megaevolution/meg/94.webp","imageUrlHiRes":"https://tcgcompanion.fra1.digitaloceanspaces.com/images/megaevolution/meg/94_hires.webp","setSlug":"mega-evolution","setName":"Mega Evolution","setReleaseDate":"2025-09-25T23:00:00.000Z"},{"cardId":"meg-161","name":"Mega Absol ex","number":"161","rarity":"Rare Secret","artist":"aky CG Works","imageUrl":"https://tcgcompanion.fra1.digitaloceanspaces.com/images/megaevolution/meg/161.webp","imageUrlHiRes":"https://tcgcompanion.fra1.digitaloceanspaces.com/images/megaevolution/meg/161_hires.webp","setSlug":"mega-evolution","setName":"Mega Evolution","setReleaseDate":"2025-09-25T23:00:00.000Z"},{"cardId":"meg-162","name":"Mega Mawile ex","number":"162","rarity":"Rare Secret","artist":"aky CG Works","imageUrl":"https://tcgcompanion.fra1.digitaloceanspaces.com/images/megaevolution/meg/162.webp","imageUrlHiRes":"https://tcgcompanion.fra1.digitaloceanspaces.com/images/megaevolution/meg/162_hires.webp","setSlug":"mega-evolution","setName":"Mega Evolution","setReleaseDate":"2025-09-25T23:00:00.000Z"},{"cardId":"dri-39","name":"Ethan's Ho-Oh ex","number":"39","rarity":"Double Rare","artist":"aky CG Works","imageUrl":"https://tcgcompanion.fra1.digitaloceanspaces.com/images/scarlet%26violet/dri/39.webp","imageUrlHiRes":"https://tcgcompanion.fra1.digitaloceanspaces.com/images/scarlet%26violet/dri/39_hires.webp","setSlug":"destined-rivals","setName":"Destined Rivals","setReleaseDate":"2025-05-29T23:00:00.000Z"},{"cardId":"dri-81","name":"Team Rocket's Mewtwo ex","number":"81","rarity":"Double Rare","artist":"aky CG Works","imageUrl":"https://tcgcompanion.fra1.digitaloceanspaces.com/images/scarlet%26violet/dri/81.webp","imageUrlHiRes":"https://tcgcompanion.fra1.digitaloceanspaces.com/images/scarlet%26violet/dri/81_hires.webp","setSlug":"destined-rivals","setName":"Destined Rivals","setReleaseDate":"2025-05-29T23:00:00.000Z"},{"cardId":"dri-209","name":"Ethan's Ho-Oh ex","number":"209","rarity":"Rare Secret","artist":"aky CG Works","imageUrl":"https://tcgcompanion.fra1.digitaloceanspaces.com/images/scarlet%26violet/dri/209.webp","imageUrlHiRes":"https://tcgcompanion.fra1.digitaloceanspaces.com/images/scarlet%26violet/dri/209_hires.webp","setSlug":"destined-rivals","setName":"Destined Rivals","setReleaseDate":"2025-05-29T23:00:00.000Z"},{"cardId":"dri-213","name":"Team Rocket's Mewtwo ex","number":"213","rarity":"Rare Secret","artist":"aky CG Works","imageUrl":"https://tcgcompanion.fra1.digitaloceanspaces.com/images/scarlet%26violet/dri/213.webp","imageUrlHiRes":"https://tcgcompanion.fra1.digitaloceanspaces.com/images/scarlet%26violet/dri/213_hires.webp","setSlug":"destined-rivals","setName":"Destined Rivals","setReleaseDate":"2025-05-29T23:00:00.000Z"},{"cardId":"dri-239","name":"Ethan's Ho-Oh ex","number":"239","rarity":"Rare Secret","artist":"aky CG Works","imageUrl":"https://tcgcompanion.fra1.digitaloceanspaces.com/images/scarlet%26violet/dri/239.webp","imageUrlHiRes":"https://tcgcompanion.fra1.digitaloceanspaces.com/images/scarlet%26violet/dri/239_hires.webp","setSlug":"destined-rivals","setName":"Destined Rivals","setReleaseDate":"2025-05-29T23:00:00.000Z"},{"cardId":"dri-240","name":"Team Rocket's Mewtwo ex","number":"240","rarity":"Rare Secret","artist":"aky CG Works","imageUrl":"https://tcgcompanion.fra1.digitaloceanspaces.com/images/scarlet%26violet/dri/240.webp","imageUrlHiRes":"https://tcgcompanion.fra1.digitaloceanspaces.com/images/scarlet%26violet/dri/240_hires.webp","setSlug":"destined-rivals","setName":"Destined Rivals","setReleaseDate":"2025-05-29T23:00:00.000Z"},{"cardId":"jtg-111","name":"Hop's Zacian ex","number":"111","rarity":"Double Rare","artist":"aky CG Works","imageUrl":"https://tcgcompanion.fra1.digitaloceanspaces.com/images/scarlet%26violet/jtg/111.png","imageUrlHiRes":"https://tcgcompanion.fra1.digitaloceanspaces.com/images/scarlet%26violet/jtg/111_hires.png","setSlug":"journey-together","setName":"Journey Together","setReleaseDate":"2025-03-28T00:00:00.000Z"},{"cardId":"jtg-176","name":"Hop's Zacian ex","number":"176","rarity":"Ultra Rare","artist":"aky CG Works","imageUrl":"https://tcgcompanion.fra1.digitaloceanspaces.com/images/scarlet%26violet/jtg/176.png","imageUrlHiRes":"https://tcgcompanion.fra1.digitaloceanspaces.com/images/scarlet%26violet/jtg/176_hires.png","setSlug":"journey-together","setName":"Journey Together","setReleaseDate":"2025-03-28T00:00:00.000Z"},{"cardId":"pre-26","name":"Glaceon ex","number":"26","rarity":"EX","artist":"aky CG Works","imageUrl":"https://tcgcompanion.fra1.digitaloceanspaces.com/images/scarlet%26violet/pre/26.png","imageUrlHiRes":"https://tcgcompanion.fra1.digitaloceanspaces.com/images/scarlet%26violet/pre/26_hires.png","setSlug":"prismatic-evolutions","setName":"Prismatic Evolutions","setReleaseDate":"2025-01-17T00:00:00.000Z"},{"cardId":"pre-75","name":"Eevee ex","number":"75","rarity":"EX","artist":"aky CG Works","imageUrl":"https://tcgcompanion.fra1.digitaloceanspaces.com/images/scarlet%26violet/pre/75.png","imageUrlHiRes":"https://tcgcompanion.fra1.digitaloceanspaces.com/images/scarlet%26violet/pre/75_hires.png","setSlug":"prismatic-evolutions","setName":"Prismatic Evolutions","setReleaseDate":"2025-01-17T00:00:00.000Z"},{"cardId":"pre-179","name":"Pikachu ex","number":"179","rarity":"Rare Secret","artist":"aky CG Works","imageUrl":"https://tcgcompanion.fra1.digitaloceanspaces.com/images/scarlet%26violet/pre/179.png","imageUrlHiRes":"https://tcgcompanion.fra1.digitaloceanspaces.com/images/scarlet%26violet/pre/179_hires.png","setSlug":"prismatic-evolutions","setName":"Prismatic Evolutions","setReleaseDate":"2025-01-17T00:00:00.000Z"},{"cardId":"ssp-57","name":"Pikachu ex","number":"57","rarity":"EX","artist":"Aky CG Works","imageUrl":"https://tcgcompanion.fra1.digitaloceanspaces.com/images/scarlet%26violet/ssp/57.png","imageUrlHiRes":"https://tcgcompanion.fra1.digitaloceanspaces.com/images/scarlet%26violet/ssp/57_hires.png","setSlug":"surging-sparks","setName":"Surging Sparks","setReleaseDate":"2024-11-08T00:00:00.000Z"},{"cardId":"ssp-133","name":"Alolan Exeggutor ex","number":"133","rarity":"EX","artist":"Aky CG Works","imageUrl":"https://tcgcompanion.fra1.digitaloceanspaces.com/images/scarlet%26violet/ssp/133.png","imageUrlHiRes":"https://tcgcompanion.fra1.digitaloceanspaces.com/images/scarlet%26violet/ssp/133_hires.png","setSlug":"surging-sparks","setName":"Surging Sparks","setReleaseDate":"2024-11-08T00:00:00.000Z"},{"cardId":"ssp-219","name":"Pikachu ex","number":"219","rarity":"Rare Secret","artist":"Aky CG Works","imageUrl":"https://tcgcompanion.fra1.digitaloceanspaces.com/images/scarlet%26violet/ssp/219.png","imageUrlHiRes":"https://tcgcompanion.fra1.digitaloceanspaces.com/images/scarlet%26violet/ssp/219_hires.png","setSlug":"surging-sparks","setName":"Surging Sparks","setReleaseDate":"2024-11-08T00:00:00.000Z"},{"cardId":"ssp-225","name":"Alolan Exeggutor ex","number":"225","rarity":"Rare Secret","artist":"Aky CG Works","imageUrl":"https://tcgcompanion.fra1.digitaloceanspaces.com/images/scarlet%26violet/ssp/225.png","imageUrlHiRes":"https://tcgcompanion.fra1.digitaloceanspaces.com/images/scarlet%26violet/ssp/225_hires.png","setSlug":"surging-sparks","setName":"Surging Sparks","setReleaseDate":"2024-11-08T00:00:00.000Z"},{"cardId":"ssp-247","name":"Pikachu ex","number":"247","rarity":"Rare Secret","artist":"Aky CG Works","imageUrl":"https://tcgcompanion.fra1.digitaloceanspaces.com/images/scarlet%26violet/ssp/247.png","imageUrlHiRes":"https://tcgcompanion.fra1.digitaloceanspaces.com/images/scarlet%26violet/ssp/247_hires.png","setSlug":"surging-sparks","setName":"Surging Sparks","setReleaseDate":"2024-11-08T00:00:00.000Z"},{"cardId":"ssp-248","name":"Alolan Exeggutor ex","number":"248","rarity":"Rare Secret","artist":"Aky CG Works","imageUrl":"https://tcgcompanion.fra1.digitaloceanspaces.com/images/scarlet%26violet/ssp/248.png","imageUrlHiRes":"https://tcgcompanion.fra1.digitaloceanspaces.com/images/scarlet%26violet/ssp/248_hires.png","setSlug":"surging-sparks","setName":"Surging Sparks","setReleaseDate":"2024-11-08T00:00:00.000Z"},{"cardId":"sfa-39","name":"Pecharunt ex","number":"39","rarity":"EX","artist":"Aky CG Works","imageUrl":"https://tcgcompanion.fra1.digitaloceanspaces.com/images/scarlet%26violet/sfa/39.png","imageUrlHiRes":"https://tcgcompanion.fra1.digitaloceanspaces.com/images/scarlet%26violet/sfa/39_hires.png","setSlug":"shrouded-fable","setName":"Shrouded Fable","setReleaseDate":"2024-08-02T00:00:00.000Z"},{"cardId":"sfa-85","name":"Pecharunt ex","number":"85","rarity":"Rare Secret","artist":"Aky CG Works","imageUrl":"https://tcgcompanion.fra1.digitaloceanspaces.com/images/scarlet%26violet/sfa/85.png","imageUrlHiRes":"https://tcgcompanion.fra1.digitaloceanspaces.com/images/scarlet%26violet/sfa/85_hires.png","setSlug":"shrouded-fable","setName":"Shrouded Fable","setReleaseDate":"2024-08-02T00:00:00.000Z"},{"cardId":"sfa-95","name":"Pecharunt ex","number":"95","rarity":"Rare Secret","artist":"Aky CG Works","imageUrl":"https://tcgcompanion.fra1.digitaloceanspaces.com/images/scarlet%26violet/sfa/95.png","imageUrlHiRes":"https://tcgcompanion.fra1.digitaloceanspaces.com/images/scarlet%26violet/sfa/95_hires.png","setSlug":"shrouded-fable","setName":"Shrouded Fable","setReleaseDate":"2024-08-02T00:00:00.000Z"},{"cardId":"twm-23","name":"Sinistcha ex","number":"23","rarity":"EX","artist":"Aky CG Works","imageUrl":"https://tcgcompanion.fra1.digitaloceanspaces.com/images/scarlet%26violet/twm/23.png","imageUrlHiRes":"https://tcgcompanion.fra1.digitaloceanspaces.com/images/scarlet%26violet/twm/23_hires.png","setSlug":"twilight-masquerade","setName":"Twilight Masquerade","setReleaseDate":"2024-05-24T00:00:00.000Z"},{"cardId":"twm-141","name":"Bloodmoon Ursaluna ex","number":"141","rarity":"EX","artist":"Aky CG Works","imageUrl":"https://tcgcompanion.fra1.digitaloceanspaces.com/images/scarlet%26violet/twm/141.png","imageUrlHiRes":"https://tcgcompanion.fra1.digitaloceanspaces.com/images/scarlet%26violet/twm/141_hires.png","setSlug":"twilight-masquerade","setName":"Twilight Masquerade","setReleaseDate":"2024-05-24T00:00:00.000Z"},{"cardId":"twm-189","name":"Sinistcha ex","number":"189","rarity":"Rare Secret","artist":"Aky CG Works","imageUrl":"https://tcgcompanion.fra1.digitaloceanspaces.com/images/scarlet%26violet/twm/189.png","imageUrlHiRes":"https://tcgcompanion.fra1.digitaloceanspaces.com/images/scarlet%26violet/twm/189_hires.png","setSlug":"twilight-masquerade","setName":"Twilight Masquerade","setReleaseDate":"2024-05-24T00:00:00.000Z"},{"cardId":"twm-202","name":"Bloodmoon Ursaluna ex","number":"202","rarity":"Rare Secret","artist":"Aky CG Works","imageUrl":"https://tcgcompanion.fra1.digitaloceanspaces.com/images/scarlet%26violet/twm/202.png","imageUrlHiRes":"https://tcgcompanion.fra1.digitaloceanspaces.com/images/scarlet%26violet/twm/202_hires.png","setSlug":"twilight-masquerade","setName":"Twilight Masquerade","setReleaseDate":"2024-05-24T00:00:00.000Z"},{"cardId":"twm-222","name":"Bloodmoon Ursaluna ex","number":"222","rarity":"Rare Secret","artist":"Aky CG Works","imageUrl":"https://tcgcompanion.fra1.digitaloceanspaces.com/images/scarlet%26violet/twm/222.png","imageUrlHiRes":"https://tcgcompanion.fra1.digitaloceanspaces.com/images/scarlet%26violet/twm/222_hires.png","setSlug":"twilight-masquerade","setName":"Twilight Masquerade","setReleaseDate":"2024-05-24T00:00:00.000Z"},{"cardId":"tef-123","name":"Raging Bolt ex","number":"123","rarity":"EX","artist":"Aky CG Works","imageUrl":"https://tcgcompanion.fra1.digitaloceanspaces.com/images/scarlet%26violet/tef/123.png","imageUrlHiRes":"https://tcgcompanion.fra1.digitaloceanspaces.com/images/scarlet%26violet/tef/123_hires.png","setSlug":"temporal-forces","setName":"Temporal Forces","setReleaseDate":"2024-03-22T00:00:00.000Z"},{"cardId":"tef-196","name":"Raging Bolt ex","number":"196","rarity":"Rare Secret","artist":"Aky CG Works","imageUrl":"https://tcgcompanion.fra1.digitaloceanspaces.com/images/scarlet%26violet/tef/196.png","imageUrlHiRes":"https://tcgcompanion.fra1.digitaloceanspaces.com/images/scarlet%26violet/tef/196_hires.png","setSlug":"temporal-forces","setName":"Temporal Forces","setReleaseDate":"2024-03-22T00:00:00.000Z"},{"cardId":"tef-218","name":"Raging Bolt ex","number":"218","rarity":"Rare Secret","artist":"Aky CG Works","imageUrl":"https://tcgcompanion.fra1.digitaloceanspaces.com/images/scarlet%26violet/tef/218.png","imageUrlHiRes":"https://tcgcompanion.fra1.digitaloceanspaces.com/images/scarlet%26violet/tef/218_hires.png","setSlug":"temporal-forces","setName":"Temporal Forces","setReleaseDate":"2024-03-22T00:00:00.000Z"},{"cardId":"par-58","name":"Mewtwo ex","number":"58","rarity":"EX","artist":"Aky CG Works","imageUrl":"https://tcgcompanion.fra1.digitaloceanspaces.com/images/scarlet%26violet/par/58.png","imageUrlHiRes":"https://tcgcompanion.fra1.digitaloceanspaces.com/images/scarlet%26violet/par/58_hires.png","setSlug":"paradox-rift","setName":"Paradox Rift","setReleaseDate":"2023-11-02T00:00:00.000Z"},{"cardId":"par-89","name":"Iron Valiant ex","number":"89","rarity":"EX","artist":"Aky CG Works","imageUrl":"https://tcgcompanion.fra1.digitaloceanspaces.com/images/scarlet%26violet/par/89.png","imageUrlHiRes":"https://tcgcompanion.fra1.digitaloceanspaces.com/images/scarlet%26violet/par/89_hires.png","setSlug":"paradox-rift","setName":"Paradox Rift","setReleaseDate":"2023-11-02T00:00:00.000Z"},{"cardId":"par-225","name":"Iron Valiant ex","number":"225","rarity":"Rare Secret","artist":"Aky CG Works","imageUrl":"https://tcgcompanion.fra1.digitaloceanspaces.com/images/scarlet%26violet/par/225.png","imageUrlHiRes":"https://tcgcompanion.fra1.digitaloceanspaces.com/images/scarlet%26violet/par/225_hires.png","setSlug":"paradox-rift","setName":"Paradox Rift","setReleaseDate":"2023-11-02T00:00:00.000Z"},{"cardId":"par-261","name":"Iron Valiant ex","number":"261","rarity":"Rare Secret","artist":"Aky CG Works","imageUrl":"https://tcgcompanion.fra1.digitaloceanspaces.com/images/scarlet%26violet/par/261.png","imageUrlHiRes":"https://tcgcompanion.fra1.digitaloceanspaces.com/images/scarlet%26violet/par/261_hires.png","setSlug":"paradox-rift","setName":"Paradox Rift","setReleaseDate":"2023-11-02T00:00:00.000Z"},{"cardId":"obf-73","name":"Pawmot ex","number":"73","rarity":"EX","artist":"Aky CG Works","imageUrl":"https://tcgcompanion.fra1.digitaloceanspaces.com/images/scarlet%26violet/obf/73.png","imageUrlHiRes":"https://tcgcompanion.fra1.digitaloceanspaces.com/images/scarlet%26violet/obf/73_hires.png","setSlug":"obsidian-flames","setName":"Obsidian Flames","setReleaseDate":"2023-08-11T00:00:00.000Z"},{"cardId":"obf-120","name":"Klawf","number":"120","rarity":"EX","artist":"Aky CG Works","imageUrl":"https://tcgcompanion.fra1.digitaloceanspaces.com/images/scarlet%26violet/obf/120.png","imageUrlHiRes":"https://tcgcompanion.fra1.digitaloceanspaces.com/images/scarlet%26violet/obf/120_hires.png","setSlug":"obsidian-flames","setName":"Obsidian Flames","setReleaseDate":"2023-08-11T00:00:00.000Z"},{"cardId":"obf-124","name":"Koraidon ex","number":"124","rarity":"EX","artist":"Aky CG Works","imageUrl":"https://tcgcompanion.fra1.digitaloceanspaces.com/images/scarlet%26violet/obf/124.png","imageUrlHiRes":"https://tcgcompanion.fra1.digitaloceanspaces.com/images/scarlet%26violet/obf/124_hires.png","setSlug":"obsidian-flames","setName":"Obsidian Flames","setReleaseDate":"2023-08-11T00:00:00.000Z"},{"cardId":"pal-61","name":"Chien-Pao ex","number":"61","rarity":"EX","artist":"Aky CG Works","imageUrl":"https://tcgcompanion.fra1.digitaloceanspaces.com/images/scarlet%26violet/pal/61.png","imageUrlHiRes":"https://tcgcompanion.fra1.digitaloceanspaces.com/images/scarlet%26violet/pal/61_hires.png","setSlug":"paldea-evolved","setName":"Paldea Evolved","setReleaseDate":"2023-06-09T00:00:00.000Z"},{"cardId":"pal-93","name":"Dedenne ex","number":"93","rarity":"EX","artist":"Aky CG Works","imageUrl":"https://tcgcompanion.fra1.digitaloceanspaces.com/images/scarlet%26violet/pal/93.png","imageUrlHiRes":"https://tcgcompanion.fra1.digitaloceanspaces.com/images/scarlet%26violet/pal/93_hires.png","setSlug":"paldea-evolved","setName":"Paldea Evolved","setReleaseDate":"2023-06-09T00:00:00.000Z"},{"cardId":"pal-236","name":"Chien-Pao ex","number":"236","rarity":"Rare Secret","artist":"Aky CG Works","imageUrl":"https://tcgcompanion.fra1.digitaloceanspaces.com/images/scarlet%26violet/pal/236.png","imageUrlHiRes":"https://tcgcompanion.fra1.digitaloceanspaces.com/images/scarlet%26violet/pal/236_hires.png","setSlug":"paldea-evolved","setName":"Paldea Evolved","setReleaseDate":"2023-06-09T00:00:00.000Z"},{"cardId":"pal-239","name":"Dedenne ex","number":"239","rarity":"Rare Secret","artist":"Aky CG Works","imageUrl":"https://tcgcompanion.fra1.digitaloceanspaces.com/images/scarlet%26violet/pal/239.png","imageUrlHiRes":"https://tcgcompanion.fra1.digitaloceanspaces.com/images/scarlet%26violet/pal/239_hires.png","setSlug":"paldea-evolved","setName":"Paldea Evolved","setReleaseDate":"2023-06-09T00:00:00.000Z"},{"cardId":"pal-274","name":"Chien-Pao ex","number":"274","rarity":"Rare Secret","artist":"Aky CG Works","imageUrl":"https://tcgcompanion.fra1.digitaloceanspaces.com/images/scarlet%26violet/pal/274.png","imageUrlHiRes":"https://tcgcompanion.fra1.digitaloceanspaces.com/images/scarlet%26violet/pal/274_hires.png","setSlug":"paldea-evolved","setName":"Paldea Evolved","setReleaseDate":"2023-06-09T00:00:00.000Z"},{"cardId":"svp-29","name":"Koraidon ex","number":"29","rarity":"Promo","artist":"aky CG Works","imageUrl":"https://tcgcompanion.fra1.digitaloceanspaces.com/images/scarlet%26violet/svp/29.png","imageUrlHiRes":"https://tcgcompanion.fra1.digitaloceanspaces.com/images/scarlet%26violet/svp/29_hires.png","setSlug":"sv-black-star-promos","setName":"SV Black Star Promos","setReleaseDate":"2023-03-30T00:00:00.000Z"},{"cardId":"svp-30","name":"Chien-Pao ex","number":"30","rarity":"Promo","artist":"aky CG Works","imageUrl":"https://tcgcompanion.fra1.digitaloceanspaces.com/images/scarlet%26violet/svp/30.png","imageUrlHiRes":"https://tcgcompanion.fra1.digitaloceanspaces.com/images/scarlet%26violet/svp/30_hires.png","setSlug":"sv-black-star-promos","setName":"SV Black Star Promos","setReleaseDate":"2023-03-30T00:00:00.000Z"},{"cardId":"svp-68","name":"Iron Valiant ex","number":"68","rarity":"Promo","artist":"aky CG Works","imageUrl":"https://tcgcompanion.fra1.digitaloceanspaces.com/images/scarlet%26violet/svp/68.png","imageUrlHiRes":"https://tcgcompanion.fra1.digitaloceanspaces.com/images/scarlet%26violet/svp/68_hires.png","setSlug":"sv-black-star-promos","setName":"SV Black Star Promos","setReleaseDate":"2023-03-30T00:00:00.000Z"},{"cardId":"svp-100","name":"Grafaiai ex","number":"100","rarity":"Promo","artist":"aky CG Works","imageUrl":"https://tcgcompanion.fra1.digitaloceanspaces.com/images/scarlet%26violet/svp/100.png","imageUrlHiRes":"https://tcgcompanion.fra1.digitaloceanspaces.com/images/scarlet%26violet/svp/100_hires.png","setSlug":"sv-black-star-promos","setName":"SV Black Star Promos","setReleaseDate":"2023-03-30T00:00:00.000Z"},{"cardId":"svp-177","name":"Bloodmoon Ursaluna ex","number":"177","rarity":"Promo","artist":"aky CG Works","imageUrl":"https://tcgcompanion.fra1.digitaloceanspaces.com/images/scarlet%26violet/svp/177.png","imageUrlHiRes":"https://tcgcompanion.fra1.digitaloceanspaces.com/images/scarlet%26violet/svp/177_hires.png","setSlug":"sv-black-star-promos","setName":"SV Black Star Promos","setReleaseDate":"2023-03-30T00:00:00.000Z"},{"cardId":"swsh14-55","name":"Zeraora VSTAR","number":"55","rarity":"VSTAR","artist":"Aky CG Works","imageUrl":"https://tcgcompanion.fra1.digitaloceanspaces.com/images/sword%26shield/swsh14/55.png","imageUrlHiRes":"https://tcgcompanion.fra1.digitaloceanspaces.com/images/sword%26shield/swsh14/55_hires.png","setSlug":"crown-zenith","setName":"Crown Zenith","setReleaseDate":"2023-01-20T00:00:00.000Z"},{"cardId":"swsh14-95","name":"Zacian V","number":"95","rarity":"V","artist":"Aky CG Works","imageUrl":"https://tcgcompanion.fra1.digitaloceanspaces.com/images/sword%26shield/swsh14/95.png","imageUrlHiRes":"https://tcgcompanion.fra1.digitaloceanspaces.com/images/sword%26shield/swsh14/95_hires.png","setSlug":"crown-zenith","setName":"Crown Zenith","setReleaseDate":"2023-01-20T00:00:00.000Z"},{"cardId":"swsh12-146","name":"Hisuian Zoroark V","number":"146","rarity":"V","artist":"Aky CG Works","imageUrl":"https://tcgcompanion.fra1.digitaloceanspaces.com/images/sword%26shield/swsh12/146.png","imageUrlHiRes":"https://tcgcompanion.fra1.digitaloceanspaces.com/images/sword%26shield/swsh12/146_hires.png","setSlug":"lost-origin","setName":"Lost Origin","setReleaseDate":"2022-09-09T00:00:00.000Z"},{"cardId":"swsh12-147","name":"Hisuian Zoroark VSTAR","number":"147","rarity":"VSTAR","artist":"Aky CG Works","imageUrl":"https://tcgcompanion.fra1.digitaloceanspaces.com/images/sword%26shield/swsh12/147.png","imageUrlHiRes":"https://tcgcompanion.fra1.digitaloceanspaces.com/images/sword%26shield/swsh12/147_hires.png","setSlug":"lost-origin","setName":"Lost Origin","setReleaseDate":"2022-09-09T00:00:00.000Z"},{"cardId":"swsh12-203","name":"Hisuian Zoroark VSTAR","number":"203","rarity":"Rare Secret","artist":"Aky CG Works","imageUrl":"https://tcgcompanion.fra1.digitaloceanspaces.com/images/sword%26shield/swsh12/203.png","imageUrlHiRes":"https://tcgcompanion.fra1.digitaloceanspaces.com/images/sword%26shield/swsh12/203_hires.png","setSlug":"lost-origin","setName":"Lost Origin","setReleaseDate":"2022-09-09T00:00:00.000Z"},{"cardId":"swsh12-213","name":"Hisuian Zoroark VSTAR","number":"213","rarity":"Rare Secret","artist":"Aky CG Works","imageUrl":"https://tcgcompanion.fra1.digitaloceanspaces.com/images/sword%26shield/swsh12/213.png","imageUrlHiRes":"https://tcgcompanion.fra1.digitaloceanspaces.com/images/sword%26shield/swsh12/213_hires.png","setSlug":"lost-origin","setName":"Lost Origin","setReleaseDate":"2022-09-09T00:00:00.000Z"},{"cardId":"swsh12-246","name":"Pikachu VMAX","number":"TG29","rarity":"Rare Secret","artist":"Aky CG Works","imageUrl":"https://tcgcompanion.fra1.digitaloceanspaces.com/images/sword%26shield/swsh12/TG29.png","imageUrlHiRes":"https://tcgcompanion.fra1.digitaloceanspaces.com/images/sword%26shield/swsh12/TG29_hires.png","setSlug":"lost-origin","setName":"Lost Origin","setReleaseDate":"2022-09-09T00:00:00.000Z"},{"cardId":"swsh10-39","name":"Origin Forme Palkia V","number":"39","rarity":"V","artist":"Aky CG Works","imageUrl":"https://tcgcompanion.fra1.digitaloceanspaces.com/images/sword%26shield/swsh10/39.png","imageUrlHiRes":"https://tcgcompanion.fra1.digitaloceanspaces.com/images/sword%26shield/swsh10/39_hires.png","setSlug":"astral-radiance","setName":"Astral Radiance","setReleaseDate":"2022-05-27T00:00:00.000Z"},{"cardId":"swsh10-40","name":"Origin Forme Palkia VSTAR","number":"40","rarity":"VSTAR","artist":"Aky CG Works","imageUrl":"https://tcgcompanion.fra1.digitaloceanspaces.com/images/sword%26shield/swsh10/40.png","imageUrlHiRes":"https://tcgcompanion.fra1.digitaloceanspaces.com/images/sword%26shield/swsh10/40_hires.png","setSlug":"astral-radiance","setName":"Astral Radiance","setReleaseDate":"2022-05-27T00:00:00.000Z"},{"cardId":"swsh10-134","name":"Wyrdeer V","number":"134","rarity":"V","artist":"Aky CG Works","imageUrl":"https://tcgcompanion.fra1.digitaloceanspaces.com/images/sword%26shield/swsh10/134.png","imageUrlHiRes":"https://tcgcompanion.fra1.digitaloceanspaces.com/images/sword%26shield/swsh10/134_hires.png","setSlug":"astral-radiance","setName":"Astral Radiance","setReleaseDate":"2022-05-27T00:00:00.000Z"},{"cardId":"swsh10-180","name":"Wyrdeer V","number":"180","rarity":"V","artist":"Aky CG Works","imageUrl":"https://tcgcompanion.fra1.digitaloceanspaces.com/images/sword%26shield/swsh10/180.png","imageUrlHiRes":"https://tcgcompanion.fra1.digitaloceanspaces.com/images/sword%26shield/swsh10/180_hires.png","setSlug":"astral-radiance","setName":"Astral Radiance","setReleaseDate":"2022-05-27T00:00:00.000Z"},{"cardId":"swsh10-192","name":"Origin Forme Palkia","number":"192","rarity":"Rare Secret","artist":"Aky CG Works","imageUrl":"https://tcgcompanion.fra1.digitaloceanspaces.com/images/sword%26shield/swsh10/192.png","imageUrlHiRes":"https://tcgcompanion.fra1.digitaloceanspaces.com/images/sword%26shield/swsh10/192_hires.png","setSlug":"astral-radiance","setName":"Astral Radiance","setReleaseDate":"2022-05-27T00:00:00.000Z"},{"cardId":"swsh10-208","name":"Origin Forme Palkia","number":"208","rarity":"Rare Secret","artist":"Aky CG Works","imageUrl":"https://tcgcompanion.fra1.digitaloceanspaces.com/images/sword%26shield/swsh10/208.png","imageUrlHiRes":"https://tcgcompanion.fra1.digitaloceanspaces.com/images/sword%26shield/swsh10/208_hires.png","setSlug":"astral-radiance","setName":"Astral Radiance","setReleaseDate":"2022-05-27T00:00:00.000Z"},{"cardId":"swsh9-128","name":"Drampa V","number":"128","rarity":"V","artist":"Aky CG Works","imageUrl":"https://tcgcompanion.fra1.digitaloceanspaces.com/images/sword%26shield/swsh9/128.png","imageUrlHiRes":"https://tcgcompanion.fra1.digitaloceanspaces.com/images/sword%26shield/swsh9/128_hires.png","setSlug":"brilliant-stars","setName":"Brilliant Stars","setReleaseDate":"2022-02-25T00:00:00.000Z"},{"cardId":"swsh9-183","name":"Galarian Moltres V","number":"183","rarity":"Rare Secret","artist":"Aky CG Works","imageUrl":"https://tcgcompanion.fra1.digitaloceanspaces.com/images/sword%26shield/swsh9/183.png","imageUrlHiRes":"https://tcgcompanion.fra1.digitaloceanspaces.com/images/sword%26shield/swsh9/183_hires.png","setSlug":"brilliant-stars","setName":"Brilliant Stars","setReleaseDate":"2022-02-25T00:00:00.000Z"},{"cardId":"swsh8-26","name":"Appletun V","number":"26","rarity":"V","artist":"Aky CG Works","imageUrl":"https://tcgcompanion.fra1.digitaloceanspaces.com/images/sword%26shield/swsh8/26.png","imageUrlHiRes":"https://tcgcompanion.fra1.digitaloceanspaces.com/images/sword%26shield/swsh8/26_hires.png","setSlug":"fusion-strike","setName":"Fusion Strike","setReleaseDate":"2021-12-11T00:00:00.000Z"},{"cardId":"swsh8-44","name":"Cinderace V","number":"44","rarity":"V","artist":"Aky CG Works","imageUrl":"https://tcgcompanion.fra1.digitaloceanspaces.com/images/sword%26shield/swsh8/44.png","imageUrlHiRes":"https://tcgcompanion.fra1.digitaloceanspaces.com/images/sword%26shield/swsh8/44_hires.png","setSlug":"fusion-strike","setName":"Fusion Strike","setReleaseDate":"2021-12-11T00:00:00.000Z"},{"cardId":"swsh8-146","name":"Lucario V","number":"146","rarity":"V","artist":"Aky CG Works","imageUrl":"https://tcgcompanion.fra1.digitaloceanspaces.com/images/sword%26shield/swsh8/146.png","imageUrlHiRes":"https://tcgcompanion.fra1.digitaloceanspaces.com/images/sword%26shield/swsh8/146_hires.png","setSlug":"fusion-strike","setName":"Fusion Strike","setReleaseDate":"2021-12-11T00:00:00.000Z"},{"cardId":"swsh8-250","name":"Mew V","number":"250","rarity":"Rare Ultra","artist":"Aky CG Works","imageUrl":"https://tcgcompanion.fra1.digitaloceanspaces.com/images/sword%26shield/swsh8/250.png","imageUrlHiRes":"https://tcgcompanion.fra1.digitaloceanspaces.com/images/sword%26shield/swsh8/250_hires.png","setSlug":"fusion-strike","setName":"Fusion Strike","setReleaseDate":"2021-12-11T00:00:00.000Z"},{"cardId":"swsh75-6","name":"Flying Pikachu V","number":"6","rarity":"V","artist":"Aky CG Works","imageUrl":"https://tcgcompanion.fra1.digitaloceanspaces.com/images/sword%26shield/swsh75/6.png","imageUrlHiRes":"https://tcgcompanion.fra1.digitaloceanspaces.com/images/sword%26shield/swsh75/6_hires.png","setSlug":"celebrations","setName":"Celebrations","setReleaseDate":"2021-10-08T00:00:00.000Z"},{"cardId":"swsh75-7","name":"Flying Pikachu VMAX","number":"7","rarity":"VM","artist":"Aky CG Works","imageUrl":"https://tcgcompanion.fra1.digitaloceanspaces.com/images/sword%26shield/swsh75/7.png","imageUrlHiRes":"https://tcgcompanion.fra1.digitaloceanspaces.com/images/sword%26shield/swsh75/7_hires.png","setSlug":"celebrations","setName":"Celebrations","setReleaseDate":"2021-10-08T00:00:00.000Z"},{"cardId":"swsh75-8","name":"Surfing Pikachu V","number":"8","rarity":"V","artist":"Aky CG Works","imageUrl":"https://tcgcompanion.fra1.digitaloceanspaces.com/images/sword%26shield/swsh75/8.png","imageUrlHiRes":"https://tcgcompanion.fra1.digitaloceanspaces.com/images/sword%26shield/swsh75/8_hires.png","setSlug":"celebrations","setName":"Celebrations","setReleaseDate":"2021-10-08T00:00:00.000Z"},{"cardId":"swsh75-9","name":"Suring Pikachu VMAX","number":"9","rarity":"VM","artist":"Aky CG Works","imageUrl":"https://tcgcompanion.fra1.digitaloceanspaces.com/images/sword%26shield/swsh75/9.png","imageUrlHiRes":"https://tcgcompanion.fra1.digitaloceanspaces.com/images/sword%26shield/swsh75/9_hires.png","setSlug":"celebrations","setName":"Celebrations","setReleaseDate":"2021-10-08T00:00:00.000Z"},{"cardId":"swsh7-74","name":"Sylveon V","number":"74","rarity":"V","artist":"Aky CG Works","imageUrl":"https://tcgcompanion.fra1.digitaloceanspaces.com/images/sword%26shield/swsh7/74.png","imageUrlHiRes":"https://tcgcompanion.fra1.digitaloceanspaces.com/images/sword%26shield/swsh7/74_hires.png","setSlug":"evolving-skies","setName":"Evolving Skies","setReleaseDate":"2021-08-27T00:00:00.000Z"},{"cardId":"swsh7-183","name":"Sylveon V","number":"183","rarity":"V","artist":"Aky CG Works","imageUrl":"https://tcgcompanion.fra1.digitaloceanspaces.com/images/sword%26shield/swsh7/183.png","imageUrlHiRes":"https://tcgcompanion.fra1.digitaloceanspaces.com/images/sword%26shield/swsh7/183_hires.png","setSlug":"evolving-skies","setName":"Evolving Skies","setReleaseDate":"2021-08-27T00:00:00.000Z"},{"cardId":"swsh7-190","name":"Garbodor V","number":"190","rarity":"V","artist":"Aky CG Works","imageUrl":"https://tcgcompanion.fra1.digitaloceanspaces.com/images/sword%26shield/swsh7/190.png","imageUrlHiRes":"https://tcgcompanion.fra1.digitaloceanspaces.com/images/sword%26shield/swsh7/190_hires.png","setSlug":"evolving-skies","setName":"Evolving Skies","setReleaseDate":"2021-08-27T00:00:00.000Z"},{"cardId":"swsh7-234","name":"Turffield Stadium","number":"234","rarity":"Rare Secret","artist":"Aky CG Works","imageUrl":"https://tcgcompanion.fra1.digitaloceanspaces.com/images/sword%26shield/swsh7/234.png","imageUrlHiRes":"https://tcgcompanion.fra1.digitaloceanspaces.com/images/sword%26shield/swsh7/234_hires.png","setSlug":"evolving-skies","setName":"Evolving Skies","setReleaseDate":"2021-08-27T00:00:00.000Z"},{"cardId":"swsh6-90","name":"Sandaconda VMAX","number":"90","rarity":"VM","artist":"Aky CG Works","imageUrl":"https://tcgcompanion.fra1.digitaloceanspaces.com/images/sword%26shield/swsh6/90.png","imageUrlHiRes":"https://tcgcompanion.fra1.digitaloceanspaces.com/images/sword%26shield/swsh6/90_hires.png","setSlug":"chilling-reign","setName":"Chilling Reign","setReleaseDate":"2021-06-18T00:00:00.000Z"},{"cardId":"swsh6-97","name":"Galarian Moltres V","number":"97","rarity":"V","artist":"Aky CG Works","imageUrl":"https://tcgcompanion.fra1.digitaloceanspaces.com/images/sword%26shield/swsh6/97.png","imageUrlHiRes":"https://tcgcompanion.fra1.digitaloceanspaces.com/images/sword%26shield/swsh6/97_hires.png","setSlug":"chilling-reign","setName":"Chilling Reign","setReleaseDate":"2021-06-18T00:00:00.000Z"},{"cardId":"swsh6-176","name":"Galarian Moltres V","number":"176","rarity":"V","artist":"Aky CG Works","imageUrl":"https://tcgcompanion.fra1.digitaloceanspaces.com/images/sword%26shield/swsh6/176.png","imageUrlHiRes":"https://tcgcompanion.fra1.digitaloceanspaces.com/images/sword%26shield/swsh6/176_hires.png","setSlug":"chilling-reign","setName":"Chilling Reign","setReleaseDate":"2021-06-18T00:00:00.000Z"},{"cardId":"swsh6-206","name":"Sandaconda VMAX","number":"206","rarity":"Rare Secret","artist":"Aky CG Works","imageUrl":"https://tcgcompanion.fra1.digitaloceanspaces.com/images/sword%26shield/swsh6/206.png","imageUrlHiRes":"https://tcgcompanion.fra1.digitaloceanspaces.com/images/sword%26shield/swsh6/206_hires.png","setSlug":"chilling-reign","setName":"Chilling Reign","setReleaseDate":"2021-06-18T00:00:00.000Z"},{"cardId":"swsh45-54","name":"Cramorant V","number":"54","rarity":"V","artist":"Aky CG Works","imageUrl":"https://tcgcompanion.fra1.digitaloceanspaces.com/images/sword%26shield/swsh45/54.png","imageUrlHiRes":"https://tcgcompanion.fra1.digitaloceanspaces.com/images/sword%26shield/swsh45/54_hires.png","setSlug":"shining-fates","setName":"Shining Fates","setReleaseDate":"2021-02-19T00:00:00.000Z"},{"cardId":"swsh455-107","name":"Charizard VMAX","number":"SV107","rarity":"VM","artist":"Aky CG Works","imageUrl":"https://tcgcompanion.fra1.digitaloceanspaces.com/images/sword%26shield/swsh455/sv107.png","imageUrlHiRes":"https://tcgcompanion.fra1.digitaloceanspaces.com/images/sword%26shield/swsh455/sv107_hires.png","setSlug":"sf-shiny-vault","setName":"SF: Shiny Vault","setReleaseDate":"2021-02-19T00:00:00.000Z"},{"cardId":"swsh455-115","name":"Falinks V","number":"SV115","rarity":"V","artist":"Aky CG Works","imageUrl":"https://tcgcompanion.fra1.digitaloceanspaces.com/images/sword%26shield/swsh455/sv115.png","imageUrlHiRes":"https://tcgcompanion.fra1.digitaloceanspaces.com/images/sword%26shield/swsh455/sv115_hires.png","setSlug":"sf-shiny-vault","setName":"SF: Shiny Vault","setReleaseDate":"2021-02-19T00:00:00.000Z"},{"cardId":"swsh4-44","name":"Pikachu VMAX","number":"44","rarity":"Rare Holo VMAX","artist":"aky CG Works","imageUrl":"https://tcgcompanion.fra1.digitaloceanspaces.com/images/sword%26shield/swsh4/44.png","imageUrlHiRes":"https://tcgcompanion.fra1.digitaloceanspaces.com/images/sword%26shield/swsh4/44_hires.png","setSlug":"vivid-voltage","setName":"Vivid Voltage","setReleaseDate":"2020-11-13T00:00:00.000Z"},{"cardId":"swsh4-102","name":"Zamazenta","number":"102","rarity":"Amazing Rare","artist":"aky CG Works","imageUrl":"https://tcgcompanion.fra1.digitaloceanspaces.com/images/sword%26shield/swsh4/102.png","imageUrlHiRes":"https://tcgcompanion.fra1.digitaloceanspaces.com/images/sword%26shield/swsh4/102_hires.png","setSlug":"vivid-voltage","setName":"Vivid Voltage","setReleaseDate":"2020-11-13T00:00:00.000Z"},{"cardId":"swsh4-126","name":"Aegislash V","number":"126","rarity":"Rare Holo V","artist":"aky CG Works","imageUrl":"https://tcgcompanion.fra1.digitaloceanspaces.com/images/sword%26shield/swsh4/126.png","imageUrlHiRes":"https://tcgcompanion.fra1.digitaloceanspaces.com/images/sword%26shield/swsh4/126_hires.png","setSlug":"vivid-voltage","setName":"Vivid Voltage","setReleaseDate":"2020-11-13T00:00:00.000Z"},{"cardId":"swsh4-127","name":"Aegislash VMAX","number":"127","rarity":"Rare Holo VMAX","artist":"aky CG Works","imageUrl":"https://tcgcompanion.fra1.digitaloceanspaces.com/images/sword%26shield/swsh4/127.png","imageUrlHiRes":"https://tcgcompanion.fra1.digitaloceanspaces.com/images/sword%26shield/swsh4/127_hires.png","setSlug":"vivid-voltage","setName":"Vivid Voltage","setReleaseDate":"2020-11-13T00:00:00.000Z"},{"cardId":"swsh4-177","name":"Aegislash V","number":"177","rarity":"Rare Holo V","artist":"aky CG Works","imageUrl":"https://tcgcompanion.fra1.digitaloceanspaces.com/images/sword%26shield/swsh4/177.png","imageUrlHiRes":"https://tcgcompanion.fra1.digitaloceanspaces.com/images/sword%26shield/swsh4/177_hires.png","setSlug":"vivid-voltage","setName":"Vivid Voltage","setReleaseDate":"2020-11-13T00:00:00.000Z"},{"cardId":"swsh4-188","name":"Pikachu VMAX","number":"188","rarity":"Rare Secret","artist":"aky CG Works","imageUrl":"https://tcgcompanion.fra1.digitaloceanspaces.com/images/sword%26shield/swsh4/188.png","imageUrlHiRes":"https://tcgcompanion.fra1.digitaloceanspaces.com/images/sword%26shield/swsh4/188_hires.png","setSlug":"vivid-voltage","setName":"Vivid Voltage","setReleaseDate":"2020-11-13T00:00:00.000Z"},{"cardId":"swsh4-190","name":"Aegislash VMAX","number":"190","rarity":"Rare Secret","artist":"aky CG Works","imageUrl":"https://tcgcompanion.fra1.digitaloceanspaces.com/images/sword%26shield/swsh4/190.png","imageUrlHiRes":"https://tcgcompanion.fra1.digitaloceanspaces.com/images/sword%26shield/swsh4/190_hires.png","setSlug":"vivid-voltage","setName":"Vivid Voltage","setReleaseDate":"2020-11-13T00:00:00.000Z"},{"cardId":"swsh4-198","name":"Galarian Obstagoon","number":"198","rarity":"Rare Secret","artist":"aky CG Works","imageUrl":"https://tcgcompanion.fra1.digitaloceanspaces.com/images/sword%26shield/swsh4/198.png","imageUrlHiRes":"https://tcgcompanion.fra1.digitaloceanspaces.com/images/sword%26shield/swsh4/198_hires.png","setSlug":"vivid-voltage","setName":"Vivid Voltage","setReleaseDate":"2020-11-13T00:00:00.000Z"},{"cardId":"swsh35-14","name":"Drednaw V","number":"14","rarity":"V","artist":"aky CG Works","imageUrl":"https://tcgcompanion.fra1.digitaloceanspaces.com/images/sword%26shield/swsh35/14.png","imageUrlHiRes":"https://tcgcompanion.fra1.digitaloceanspaces.com/images/sword%26shield/swsh35/14_hires.png","setSlug":"champion-s-path","setName":"Champion's Path","setReleaseDate":"2020-09-24T00:00:00.000Z"},{"cardId":"swsh35-15","name":"Drednaw VMAX","number":"15","rarity":"VM","artist":"aky CG Works","imageUrl":"https://tcgcompanion.fra1.digitaloceanspaces.com/images/sword%26shield/swsh35/15.png","imageUrlHiRes":"https://tcgcompanion.fra1.digitaloceanspaces.com/images/sword%26shield/swsh35/15_hires.png","setSlug":"champion-s-path","setName":"Champion's Path","setReleaseDate":"2020-09-24T00:00:00.000Z"},{"cardId":"swsh35-47","name":"Duraludon V","number":"47","rarity":"V","artist":"aky CG Works","imageUrl":"https://tcgcompanion.fra1.digitaloceanspaces.com/images/sword%26shield/swsh35/47.png","imageUrlHiRes":"https://tcgcompanion.fra1.digitaloceanspaces.com/images/sword%26shield/swsh35/47_hires.png","setSlug":"champion-s-path","setName":"Champion's Path","setReleaseDate":"2020-09-24T00:00:00.000Z"},{"cardId":"swsh35-68","name":"Turffield Stadium","number":"68","rarity":"Uncommon","artist":"aky CG Works","imageUrl":"https://tcgcompanion.fra1.digitaloceanspaces.com/images/sword%26shield/swsh35/68.png","imageUrlHiRes":"https://tcgcompanion.fra1.digitaloceanspaces.com/images/sword%26shield/swsh35/68_hires.png","setSlug":"champion-s-path","setName":"Champion's Path","setReleaseDate":"2020-09-24T00:00:00.000Z"},{"cardId":"swsh35-69","name":"Drednaw V","number":"69","rarity":"V","artist":"aky CG Works","imageUrl":"https://tcgcompanion.fra1.digitaloceanspaces.com/images/sword%26shield/swsh35/69.png","imageUrlHiRes":"https://tcgcompanion.fra1.digitaloceanspaces.com/images/sword%26shield/swsh35/69_hires.png","setSlug":"champion-s-path","setName":"Champion's Path","setReleaseDate":"2020-09-24T00:00:00.000Z"},{"cardId":"swsh35-74","name":"Charizard VMAX","number":"74","rarity":"Rare Secret","artist":"aky CG Works","imageUrl":"https://tcgcompanion.fra1.digitaloceanspaces.com/images/sword%26shield/swsh35/74.png","imageUrlHiRes":"https://tcgcompanion.fra1.digitaloceanspaces.com/images/sword%26shield/swsh35/74_hires.png","setSlug":"champion-s-path","setName":"Champion's Path","setReleaseDate":"2020-09-24T00:00:00.000Z"},{"cardId":"swsh35-75","name":"Drednaw VMAX","number":"75","rarity":"Rare Secret","artist":"aky CG Works","imageUrl":"https://tcgcompanion.fra1.digitaloceanspaces.com/images/sword%26shield/swsh35/75.png","imageUrlHiRes":"https://tcgcompanion.fra1.digitaloceanspaces.com/images/sword%26shield/swsh35/75_hires.png","setSlug":"champion-s-path","setName":"Champion's Path","setReleaseDate":"2020-09-24T00:00:00.000Z"},{"cardId":"swsh3-2","name":"Butterfree VMAX","number":"2","rarity":"VM","artist":"aky CG Works","imageUrl":"https://tcgcompanion.fra1.digitaloceanspaces.com/images/sword%26shield/swsh3/2.png","imageUrlHiRes":"https://tcgcompanion.fra1.digitaloceanspaces.com/images/sword%26shield/swsh3/2_hires.png","setSlug":"darkness-ablaze","setName":"Darkness Ablaze","setReleaseDate":"2020-08-13T00:00:00.000Z"},{"cardId":"swsh3-19","name":"Charizard V","number":"19","rarity":"V","artist":"aky CG Works","imageUrl":"https://tcgcompanion.fra1.digitaloceanspaces.com/images/sword%26shield/swsh3/19.png","imageUrlHiRes":"https://tcgcompanion.fra1.digitaloceanspaces.com/images/sword%26shield/swsh3/19_hires.png","setSlug":"darkness-ablaze","setName":"Darkness Ablaze","setReleaseDate":"2020-08-13T00:00:00.000Z"},{"cardId":"swsh3-20","name":"Charizard VMAX","number":"20","rarity":"VMAX","artist":"Aky CG Works","imageUrl":"https://tcgcompanion.fra1.digitaloceanspaces.com/images/sword%26shield/swsh3/20.png","imageUrlHiRes":"https://tcgcompanion.fra1.digitaloceanspaces.com/images/sword%26shield/swsh3/20_hires.png","setSlug":"darkness-ablaze","setName":"Darkness Ablaze","setReleaseDate":"2020-08-13T00:00:00.000Z"},{"cardId":"swsh3-162","name":"Glimwood Tangle","number":"162","rarity":"Uncommon","artist":"aky CG Works","imageUrl":"https://tcgcompanion.fra1.digitaloceanspaces.com/images/sword%26shield/swsh3/162.png","imageUrlHiRes":"https://tcgcompanion.fra1.digitaloceanspaces.com/images/sword%26shield/swsh3/162_hires.png","setSlug":"darkness-ablaze","setName":"Darkness Ablaze","setReleaseDate":"2020-08-13T00:00:00.000Z"},{"cardId":"swsh3-190","name":"Butterfree VMAX","number":"190","rarity":"Rare Secret","artist":"aky CG Works","imageUrl":"https://tcgcompanion.fra1.digitaloceanspaces.com/images/sword%26shield/swsh3/190.png","imageUrlHiRes":"https://tcgcompanion.fra1.digitaloceanspaces.com/images/sword%26shield/swsh3/190_hires.png","setSlug":"darkness-ablaze","setName":"Darkness Ablaze","setReleaseDate":"2020-08-13T00:00:00.000Z"},{"cardId":"swsh2-67","name":"Boltund V","number":"67","rarity":"V","artist":"aky CG Works","imageUrl":"https://tcgcompanion.fra1.digitaloceanspaces.com/images/sword%26shield/swsh2/67.png","imageUrlHiRes":"https://tcgcompanion.fra1.digitaloceanspaces.com/images/sword%26shield/swsh2/67_hires.png","setSlug":"rebel-clash","setName":"Rebel Clash","setReleaseDate":"2020-04-30T00:00:00.000Z"},{"cardId":"swsh2-92","name":"Dragapult V","number":"92","rarity":"V","artist":"aky CG Works","imageUrl":"https://tcgcompanion.fra1.digitaloceanspaces.com/images/sword%26shield/swsh2/92.png","imageUrlHiRes":"https://tcgcompanion.fra1.digitaloceanspaces.com/images/sword%26shield/swsh2/92_hires.png","setSlug":"rebel-clash","setName":"Rebel Clash","setReleaseDate":"2020-04-30T00:00:00.000Z"},{"cardId":"swsh2-93","name":"Dragapult VMAX","number":"93","rarity":"VM","artist":"aky CG Works","imageUrl":"https://tcgcompanion.fra1.digitaloceanspaces.com/images/sword%26shield/swsh2/93.png","imageUrlHiRes":"https://tcgcompanion.fra1.digitaloceanspaces.com/images/sword%26shield/swsh2/93_hires.png","setSlug":"rebel-clash","setName":"Rebel Clash","setReleaseDate":"2020-04-30T00:00:00.000Z"},{"cardId":"swsh2-108","name":"Sandaconda V","number":"108","rarity":"V","artist":"aky CG Works","imageUrl":"https://tcgcompanion.fra1.digitaloceanspaces.com/images/sword%26shield/swsh2/108.png","imageUrlHiRes":"https://tcgcompanion.fra1.digitaloceanspaces.com/images/sword%26shield/swsh2/108_hires.png","setSlug":"rebel-clash","setName":"Rebel Clash","setReleaseDate":"2020-04-30T00:00:00.000Z"},{"cardId":"swsh2-110","name":"Falinks V","number":"110","rarity":"V","artist":"aky CG Works","imageUrl":"https://tcgcompanion.fra1.digitaloceanspaces.com/images/sword%26shield/swsh2/110.png","imageUrlHiRes":"https://tcgcompanion.fra1.digitaloceanspaces.com/images/sword%26shield/swsh2/110_hires.png","setSlug":"rebel-clash","setName":"Rebel Clash","setReleaseDate":"2020-04-30T00:00:00.000Z"},{"cardId":"swsh2-170","name":"Turffield Stadium","number":"170","rarity":"Uncommon","artist":"aky CG Works","imageUrl":"https://tcgcompanion.fra1.digitaloceanspaces.com/images/sword%26shield/swsh2/170.png","imageUrlHiRes":"https://tcgcompanion.fra1.digitaloceanspaces.com/images/sword%26shield/swsh2/170_hires.png","setSlug":"rebel-clash","setName":"Rebel Clash","setReleaseDate":"2020-04-30T00:00:00.000Z"},{"cardId":"swsh2-181","name":"Boltund V","number":"181","rarity":"Rare Ultra","artist":"aky CG Works","imageUrl":"https://tcgcompanion.fra1.digitaloceanspaces.com/images/sword%26shield/swsh2/181.png","imageUrlHiRes":"https://tcgcompanion.fra1.digitaloceanspaces.com/images/sword%26shield/swsh2/181_hires.png","setSlug":"rebel-clash","setName":"Rebel Clash","setReleaseDate":"2020-04-30T00:00:00.000Z"},{"cardId":"swsh2-183","name":"Dragapult V","number":"183","rarity":"Rare Ultra","artist":"aky CG Works","imageUrl":"https://tcgcompanion.fra1.digitaloceanspaces.com/images/sword%26shield/swsh2/183.png","imageUrlHiRes":"https://tcgcompanion.fra1.digitaloceanspaces.com/images/sword%26shield/swsh2/183_hires.png","setSlug":"rebel-clash","setName":"Rebel Clash","setReleaseDate":"2020-04-30T00:00:00.000Z"},{"cardId":"swsh2-184","name":"Sandaconda V","number":"184","rarity":"Rare Ultra","artist":"aky CG Works","imageUrl":"https://tcgcompanion.fra1.digitaloceanspaces.com/images/sword%26shield/swsh2/184.png","imageUrlHiRes":"https://tcgcompanion.fra1.digitaloceanspaces.com/images/sword%26shield/swsh2/184_hires.png","setSlug":"rebel-clash","setName":"Rebel Clash","setReleaseDate":"2020-04-30T00:00:00.000Z"},{"cardId":"swsh2-185","name":"Falinks V","number":"185","rarity":"Rare Ultra","artist":"aky CG Works","imageUrl":"https://tcgcompanion.fra1.digitaloceanspaces.com/images/sword%26shield/swsh2/185.png","imageUrlHiRes":"https://tcgcompanion.fra1.digitaloceanspaces.com/images/sword%26shield/swsh2/185_hires.png","setSlug":"rebel-clash","setName":"Rebel Clash","setReleaseDate":"2020-04-30T00:00:00.000Z"},{"cardId":"swsh2-197","name":"Dragapult VMAX","number":"197","rarity":"Rare Secret","artist":"aky CG Works","imageUrl":"https://tcgcompanion.fra1.digitaloceanspaces.com/images/sword%26shield/swsh2/197.png","imageUrlHiRes":"https://tcgcompanion.fra1.digitaloceanspaces.com/images/sword%26shield/swsh2/197_hires.png","setSlug":"rebel-clash","setName":"Rebel Clash","setReleaseDate":"2020-04-30T00:00:00.000Z"},{"cardId":"swsh1-139","name":"Zamazenta V","number":"139","rarity":"V","artist":"aky CG Works","imageUrl":"https://tcgcompanion.fra1.digitaloceanspaces.com/images/sword%26shield/swsh1/139.png","imageUrlHiRes":"https://tcgcompanion.fra1.digitaloceanspaces.com/images/sword%26shield/swsh1/139_hires.png","setSlug":"sword-and-shield","setName":"Sword & Shield","setReleaseDate":"2020-02-07T00:00:00.000Z"},{"cardId":"swsh1-142","name":"Snorlax VMAX","number":"142","rarity":"VM","artist":"aky CG Works","imageUrl":"https://tcgcompanion.fra1.digitaloceanspaces.com/images/sword%26shield/swsh1/142.png","imageUrlHiRes":"https://tcgcompanion.fra1.digitaloceanspaces.com/images/sword%26shield/swsh1/142_hires.png","setSlug":"sword-and-shield","setName":"Sword & Shield","setReleaseDate":"2020-02-07T00:00:00.000Z"},{"cardId":"swsh1-155","name":"Cramorant V","number":"155","rarity":"V","artist":"aky CG Works","imageUrl":"https://tcgcompanion.fra1.digitaloceanspaces.com/images/sword%26shield/swsh1/155.png","imageUrlHiRes":"https://tcgcompanion.fra1.digitaloceanspaces.com/images/sword%26shield/swsh1/155_hires.png","setSlug":"sword-and-shield","setName":"Sword & Shield","setReleaseDate":"2020-02-07T00:00:00.000Z"},{"cardId":"swsh1-196","name":"Zamazenta V","number":"196","rarity":"Rare Ultra","artist":"aky CG Works","imageUrl":"https://tcgcompanion.fra1.digitaloceanspaces.com/images/sword%26shield/swsh1/196.png","imageUrlHiRes":"https://tcgcompanion.fra1.digitaloceanspaces.com/images/sword%26shield/swsh1/196_hires.png","setSlug":"sword-and-shield","setName":"Sword & Shield","setReleaseDate":"2020-02-07T00:00:00.000Z"},{"cardId":"swsh1-197","name":"Snorlax V","number":"197","rarity":"Rare Ultra","artist":"aky CG Works","imageUrl":"https://tcgcompanion.fra1.digitaloceanspaces.com/images/sword%26shield/swsh1/197.png","imageUrlHiRes":"https://tcgcompanion.fra1.digitaloceanspaces.com/images/sword%26shield/swsh1/197_hires.png","setSlug":"sword-and-shield","setName":"Sword & Shield","setReleaseDate":"2020-02-07T00:00:00.000Z"},{"cardId":"swsh1-198","name":"Cramorant V","number":"198","rarity":"Rare Ultra","artist":"aky CG Works","imageUrl":"https://tcgcompanion.fra1.digitaloceanspaces.com/images/sword%26shield/swsh1/198.png","imageUrlHiRes":"https://tcgcompanion.fra1.digitaloceanspaces.com/images/sword%26shield/swsh1/198_hires.png","setSlug":"sword-and-shield","setName":"Sword & Shield","setReleaseDate":"2020-02-07T00:00:00.000Z"},{"cardId":"swsh1-206","name":"Snorlax VMAX","number":"206","rarity":"Rare Secret","artist":"aky CG Works","imageUrl":"https://tcgcompanion.fra1.digitaloceanspaces.com/images/sword%26shield/swsh1/206.png","imageUrlHiRes":"https://tcgcompanion.fra1.digitaloceanspaces.com/images/sword%26shield/swsh1/206_hires.png","setSlug":"sword-and-shield","setName":"Sword & Shield","setReleaseDate":"2020-02-07T00:00:00.000Z"},{"cardId":"swsh1-212","name":"Zamazenta V","number":"212","rarity":"Rare Secret","artist":"aky CG Works","imageUrl":"https://tcgcompanion.fra1.digitaloceanspaces.com/images/sword%26shield/swsh1/212.png","imageUrlHiRes":"https://tcgcompanion.fra1.digitaloceanspaces.com/images/sword%26shield/swsh1/212_hires.png","setSlug":"sword-and-shield","setName":"Sword & Shield","setReleaseDate":"2020-02-07T00:00:00.000Z"},{"cardId":"swshp-SWSH004","name":"Meowth V","number":"SWSH004","rarity":"Rare Holo V","artist":"aky CG Works","imageUrl":"https://tcgcompanion.fra1.digitaloceanspaces.com/images/sword%26shield/swshp/SWSH004.png","imageUrlHiRes":"https://tcgcompanion.fra1.digitaloceanspaces.com/images/sword%26shield/swshp/SWSH004_hires.png","setSlug":"swsh-black-star-promos","setName":"SWSH Black Star Promos","setReleaseDate":"2019-11-15T00:00:00.000Z"},{"cardId":"swshp-SWSH005","name":"Meowth VMAX","number":"SWSH005","rarity":"Rare Holo VMAX","artist":"aky CG Works","imageUrl":"https://tcgcompanion.fra1.digitaloceanspaces.com/images/sword%26shield/swshp/SWSH005.png","imageUrlHiRes":"https://tcgcompanion.fra1.digitaloceanspaces.com/images/sword%26shield/swshp/SWSH005_hires.png","setSlug":"swsh-black-star-promos","setName":"SWSH Black Star Promos","setReleaseDate":"2019-11-15T00:00:00.000Z"},{"cardId":"swshp-SWSH019","name":"Zamazenta V","number":"SWSH019","rarity":"Rare Holo V","artist":"aky CG Works","imageUrl":"https://tcgcompanion.fra1.digitaloceanspaces.com/images/sword%26shield/swshp/SWSH019.png","imageUrlHiRes":"https://tcgcompanion.fra1.digitaloceanspaces.com/images/sword%26shield/swshp/SWSH019_hires.png","setSlug":"swsh-black-star-promos","setName":"SWSH Black Star Promos","setReleaseDate":"2019-11-15T00:00:00.000Z"},{"cardId":"swshp-SWSH077","name":"Zamazenta V","number":"SWSH077","rarity":"V","artist":"Aky CG Works","imageUrl":"https://tcgcompanion.fra1.digitaloceanspaces.com/images/sword%26shield/swshp/SWSH077.png","imageUrlHiRes":"https://tcgcompanion.fra1.digitaloceanspaces.com/images/sword%26shield/swshp/SWSH077_hires.png","setSlug":"swsh-black-star-promos","setName":"SWSH Black Star Promos","setReleaseDate":"2019-11-15T00:00:00.000Z"},{"cardId":"swshp-SWSH085","name":"Boltund V","number":"SWSH085","rarity":"V","artist":"Aky CG Works","imageUrl":"https://tcgcompanion.fra1.digitaloceanspaces.com/images/sword%26shield/swshp/SWSH085.png","imageUrlHiRes":"https://tcgcompanion.fra1.digitaloceanspaces.com/images/sword%26shield/swshp/SWSH085_hires.png","setSlug":"swsh-black-star-promos","setName":"SWSH Black Star Promos","setReleaseDate":"2019-11-15T00:00:00.000Z"},{"cardId":"swshp-SWSH086","name":"Cramorant V","number":"SWSH086","rarity":"V","artist":"Aky CG Works","imageUrl":"https://tcgcompanion.fra1.digitaloceanspaces.com/images/sword%26shield/swshp/SWSH086.png","imageUrlHiRes":"https://tcgcompanion.fra1.digitaloceanspaces.com/images/sword%26shield/swshp/SWSH086_hires.png","setSlug":"swsh-black-star-promos","setName":"SWSH Black Star Promos","setReleaseDate":"2019-11-15T00:00:00.000Z"},{"cardId":"swshp-SWSH096","name":"Dragapult V","number":"SWSH096","rarity":"V","artist":"Aky CG Works","imageUrl":"https://tcgcompanion.fra1.digitaloceanspaces.com/images/sword%26shield/swshp/SWSH096.png","imageUrlHiRes":"https://tcgcompanion.fra1.digitaloceanspaces.com/images/sword%26shield/swshp/SWSH096_hires.png","setSlug":"swsh-black-star-promos","setName":"SWSH Black Star Promos","setReleaseDate":"2019-11-15T00:00:00.000Z"},{"cardId":"swshp-SWSH097","name":"Dragapult VMAX","number":"SWSH097","rarity":"VM","artist":"Aky CG Works","imageUrl":"https://tcgcompanion.fra1.digitaloceanspaces.com/images/sword%26shield/swshp/SWSH097.png","imageUrlHiRes":"https://tcgcompanion.fra1.digitaloceanspaces.com/images/sword%26shield/swshp/SWSH097_hires.png","setSlug":"swsh-black-star-promos","setName":"SWSH Black Star Promos","setReleaseDate":"2019-11-15T00:00:00.000Z"},{"cardId":"swshp-SWSH100","name":"Venusaur V","number":"SWSH100","rarity":"Promo","artist":"aky CG Works","imageUrl":"https://tcgcompanion.fra1.digitaloceanspaces.com/images/sword%26shield/swshp/SWSH100.png","imageUrlHiRes":"https://tcgcompanion.fra1.digitaloceanspaces.com/images/sword%26shield/swshp/SWSH100_hires.png","setSlug":"swsh-black-star-promos","setName":"SWSH Black Star Promos","setReleaseDate":"2019-11-15T00:00:00.000Z"},{"cardId":"swshp-SWSH102","name":"Venusaur VMAX","number":"SWSH102","rarity":"Promo","artist":"aky CG Works","imageUrl":"https://tcgcompanion.fra1.digitaloceanspaces.com/images/sword%26shield/swshp/SWSH102.png","imageUrlHiRes":"https://tcgcompanion.fra1.digitaloceanspaces.com/images/sword%26shield/swshp/SWSH102_hires.png","setSlug":"swsh-black-star-promos","setName":"SWSH Black Star Promos","setReleaseDate":"2019-11-15T00:00:00.000Z"},{"cardId":"swhsp-SWSH202","name":"Sylveon V","number":"SWSH202","rarity":"Promo","artist":"Aky CG Works","imageUrl":"https://tcgcompanion.fra1.digitaloceanspaces.com/images/sword%26shield/swshp/SWSH202.png","imageUrlHiRes":"https://tcgcompanion.fra1.digitaloceanspaces.com/images/sword%26shield/swshp/SWSH202_hires.png","setSlug":"swsh-black-star-promos","setName":"SWSH Black Star Promos","setReleaseDate":"2019-11-15T00:00:00.000Z"},{"cardId":"swhsp-SWSH214","name":"Lucario VSTAR","number":"SWSH214","rarity":"Promo","artist":"Aky CG Works","imageUrl":"https://tcgcompanion.fra1.digitaloceanspaces.com/images/sword%26shield/swshp/SWSH214.png","imageUrlHiRes":"https://tcgcompanion.fra1.digitaloceanspaces.com/images/sword%26shield/swshp/SWSH214_hires.png","setSlug":"swsh-black-star-promos","setName":"SWSH Black Star Promos","setReleaseDate":"2019-11-15T00:00:00.000Z"},{"cardId":"swshp-SWSH253","name":"Origin Forme Palkia V","number":"SWSH253","rarity":"Promo","artist":"Aky CG Works","imageUrl":"https://tcgcompanion.fra1.digitaloceanspaces.com/images/sword%26shield/swshp/SWSH253.png","imageUrlHiRes":"https://tcgcompanion.fra1.digitaloceanspaces.com/images/sword%26shield/swshp/SWSH253_hires.png","setSlug":"swsh-black-star-promos","setName":"SWSH Black Star Promos","setReleaseDate":"2019-11-15T00:00:00.000Z"},{"cardId":"swshp-SWSH254","name":"Origin Forme Palkia VSTAR","number":"SWSH254","rarity":"Promo","artist":"Aky CG Works","imageUrl":"https://tcgcompanion.fra1.digitaloceanspaces.com/images/sword%26shield/swshp/SWSH254.png","imageUrlHiRes":"https://tcgcompanion.fra1.digitaloceanspaces.com/images/sword%26shield/swshp/SWSH254_hires.png","setSlug":"swsh-black-star-promos","setName":"SWSH Black Star Promos","setReleaseDate":"2019-11-15T00:00:00.000Z"},{"cardId":"swshp-SWSH265","name":"Zeraora VSTAR","number":"SWSH265","rarity":"Promo","artist":"Aky CG Works","imageUrl":"https://tcgcompanion.fra1.digitaloceanspaces.com/images/sword%26shield/swshp/SWSH265.png","imageUrlHiRes":"https://tcgcompanion.fra1.digitaloceanspaces.com/images/sword%26shield/swshp/SWSH265_hires.png","setSlug":"swsh-black-star-promos","setName":"SWSH Black Star Promos","setReleaseDate":"2019-11-15T00:00:00.000Z"},{"cardId":"swshp-SWSH293","name":"Zamazenta V","number":"SWSH293","rarity":"Promo","artist":"Aky CG Works","imageUrl":"https://tcgcompanion.fra1.digitaloceanspaces.com/images/sword%26shield/swshp/SWSH293.png","imageUrlHiRes":"https://tcgcompanion.fra1.digitaloceanspaces.com/images/sword%26shield/swshp/SWSH293_hires.png","setSlug":"swsh-black-star-promos","setName":"SWSH Black Star Promos","setReleaseDate":"2019-11-15T00:00:00.000Z"},{"cardId":"swshp-SWSH297","name":"Hisuian Zoroark V","number":"SWSH297","rarity":"Promo","artist":"Aky CG Works","imageUrl":"https://tcgcompanion.fra1.digitaloceanspaces.com/images/sword%26shield/swshp/SWSH297.png","imageUrlHiRes":"https://tcgcompanion.fra1.digitaloceanspaces.com/images/sword%26shield/swshp/SWSH297_hires.png","setSlug":"swsh-black-star-promos","setName":"SWSH Black Star Promos","setReleaseDate":"2019-11-15T00:00:00.000Z"},{"cardId":"swshp-SWSH298","name":"Hisuian Zoroark VSTAR","number":"SWSH298","rarity":"Promo","artist":"Aky CG Works","imageUrl":"https://tcgcompanion.fra1.digitaloceanspaces.com/images/sword%26shield/swshp/SWSH298.png","imageUrlHiRes":"https://tcgcompanion.fra1.digitaloceanspaces.com/images/sword%26shield/swshp/SWSH298_hires.png","setSlug":"swsh-black-star-promos","setName":"SWSH Black Star Promos","setReleaseDate":"2019-11-15T00:00:00.000Z"},{"cardId":"sm12-95","name":"Oricorio-GX","number":"95","rarity":"Rare Holo GX","artist":"aky CG Works","imageUrl":"https://tcgcompanion.fra1.digitaloceanspaces.com/images/sun%26moon/sm12/95.png","imageUrlHiRes":"https://tcgcompanion.fra1.digitaloceanspaces.com/images/sun%26moon/sm12/95_hires.png","setSlug":"cosmic-eclipse","setName":"Cosmic Eclipse","setReleaseDate":"2019-11-01T00:00:00.000Z"},{"cardId":"sm12-190","name":"Dragonium Z: Dragon Claw","number":"190","rarity":"Uncommon","artist":"aky CG Works","imageUrl":"https://tcgcompanion.fra1.digitaloceanspaces.com/images/sun%26moon/sm12/190.png","imageUrlHiRes":"https://tcgcompanion.fra1.digitaloceanspaces.com/images/sun%26moon/sm12/190_hires.png","setSlug":"cosmic-eclipse","setName":"Cosmic Eclipse","setReleaseDate":"2019-11-01T00:00:00.000Z"},{"cardId":"sm12-225","name":"Mega Lopunny & Jigglypuff-GX","number":"225","rarity":"Rare Ultra","artist":"aky CG Works","imageUrl":"https://tcgcompanion.fra1.digitaloceanspaces.com/images/sun%26moon/sm12/225.png","imageUrlHiRes":"https://tcgcompanion.fra1.digitaloceanspaces.com/images/sun%26moon/sm12/225_hires.png","setSlug":"cosmic-eclipse","setName":"Cosmic Eclipse","setReleaseDate":"2019-11-01T00:00:00.000Z"},{"cardId":"sm115-9","name":"Charizard-GX","number":"9","rarity":"Rare Holo GX","artist":"aky CG Works","imageUrl":"https://tcgcompanion.fra1.digitaloceanspaces.com/images/sun%26moon/sm115/9.png","imageUrlHiRes":"https://tcgcompanion.fra1.digitaloceanspaces.com/images/sun%26moon/sm115/9_hires.png","setSlug":"hidden-fates","setName":"Hidden Fates","setReleaseDate":"2019-08-23T00:00:00.000Z"},{"cardId":"sm115-31","name":"Mewtwo-GX","number":"31","rarity":"Rare Holo GX","artist":"aky CG Works","imageUrl":"https://tcgcompanion.fra1.digitaloceanspaces.com/images/sun%26moon/sm115/31.png","imageUrlHiRes":"https://tcgcompanion.fra1.digitaloceanspaces.com/images/sun%26moon/sm115/31_hires.png","setSlug":"hidden-fates","setName":"Hidden Fates","setReleaseDate":"2019-08-23T00:00:00.000Z"},{"cardId":"sm11-132","name":"Weavile-GX","number":"132","rarity":"Rare Holo GX","artist":"aky CG Works","imageUrl":"https://tcgcompanion.fra1.digitaloceanspaces.com/images/sun%26moon/sm11/132.png","imageUrlHiRes":"https://tcgcompanion.fra1.digitaloceanspaces.com/images/sun%26moon/sm11/132_hires.png","setSlug":"unified-minds","setName":"Unified Minds","setReleaseDate":"2019-08-02T00:00:00.000Z"},{"cardId":"sm11-195","name":"Flyinium Z: Air Slash","number":"195","rarity":"Uncommon","artist":"aky CG Works","imageUrl":"https://tcgcompanion.fra1.digitaloceanspaces.com/images/sun%26moon/sm11/195.png","imageUrlHiRes":"https://tcgcompanion.fra1.digitaloceanspaces.com/images/sun%26moon/sm11/195_hires.png","setSlug":"unified-minds","setName":"Unified Minds","setReleaseDate":"2019-08-02T00:00:00.000Z"},{"cardId":"sm11-205","name":"Pokémon Research Lab","number":"205","rarity":"Uncommon","artist":"aky CG Works","imageUrl":"https://tcgcompanion.fra1.digitaloceanspaces.com/images/sun%26moon/sm11/205.png","imageUrlHiRes":"https://tcgcompanion.fra1.digitaloceanspaces.com/images/sun%26moon/sm11/205_hires.png","setSlug":"unified-minds","setName":"Unified Minds","setReleaseDate":"2019-08-02T00:00:00.000Z"},{"cardId":"sm11-228","name":"Garchomp & Giratina-GX","number":"228","rarity":"Rare Ultra","artist":"aky CG Works","imageUrl":"https://tcgcompanion.fra1.digitaloceanspaces.com/images/sun%26moon/sm11/228.png","imageUrlHiRes":"https://tcgcompanion.fra1.digitaloceanspaces.com/images/sun%26moon/sm11/228_hires.png","setSlug":"unified-minds","setName":"Unified Minds","setReleaseDate":"2019-08-02T00:00:00.000Z"},{"cardId":"sm10-183","name":"Power Plant","number":"183","rarity":"Uncommon","artist":"aky CG Works","imageUrl":"https://tcgcompanion.fra1.digitaloceanspaces.com/images/sun%26moon/sm10/183.png","imageUrlHiRes":"https://tcgcompanion.fra1.digitaloceanspaces.com/images/sun%26moon/sm10/183_hires.png","setSlug":"unbroken-bonds","setName":"Unbroken Bonds","setReleaseDate":"2019-05-03T00:00:00.000Z"},{"cardId":"sm10-191","name":"Pheromosa & Buzzwole-GX","number":"191","rarity":"Rare Ultra","artist":"aky CG Works","imageUrl":"https://tcgcompanion.fra1.digitaloceanspaces.com/images/sun%26moon/sm10/191.png","imageUrlHiRes":"https://tcgcompanion.fra1.digitaloceanspaces.com/images/sun%26moon/sm10/191_hires.png","setSlug":"unbroken-bonds","setName":"Unbroken Bonds","setReleaseDate":"2019-05-03T00:00:00.000Z"},{"cardId":"sm10-194","name":"Reshiram & Charizard-GX","number":"194","rarity":"Rare Ultra","artist":"aky CG Works","imageUrl":"https://tcgcompanion.fra1.digitaloceanspaces.com/images/sun%26moon/sm10/194.png","imageUrlHiRes":"https://tcgcompanion.fra1.digitaloceanspaces.com/images/sun%26moon/sm10/194_hires.png","setSlug":"unbroken-bonds","setName":"Unbroken Bonds","setReleaseDate":"2019-05-03T00:00:00.000Z"},{"cardId":"sm10-208","name":"Celesteela-GX","number":"208","rarity":"Rare Ultra","artist":"aky CG Works","imageUrl":"https://tcgcompanion.fra1.digitaloceanspaces.com/images/sun%26moon/sm10/208.png","imageUrlHiRes":"https://tcgcompanion.fra1.digitaloceanspaces.com/images/sun%26moon/sm10/208_hires.png","setSlug":"unbroken-bonds","setName":"Unbroken Bonds","setReleaseDate":"2019-05-03T00:00:00.000Z"},{"cardId":"smp-SM188","name":"Kangaskhan GX","number":"SM188","rarity":"","artist":"Aky CG Works","imageUrl":"https://tcgcompanion.fra1.digitaloceanspaces.com/images/sun%26moon/smp/SM188.png","imageUrlHiRes":"https://tcgcompanion.fra1.digitaloceanspaces.com/images/sun%26moon/smp/SM188_hires.png","setSlug":"sm-black-star-promos","setName":"SM Black Star Promos","setReleaseDate":"2017-02-03T00:00:00.000Z"},{"cardId":"smp-SM232","name":"Pikachu GX","number":"SM232","rarity":"","artist":"Aky CG Works","imageUrl":"https://tcgcompanion.fra1.digitaloceanspaces.com/images/sun%26moon/smp/SM232.png","imageUrlHiRes":"https://tcgcompanion.fra1.digitaloceanspaces.com/images/sun%26moon/smp/SM232_hires.png","setSlug":"sm-black-star-promos","setName":"SM Black Star Promos","setReleaseDate":"2017-02-03T00:00:00.000Z"},{"cardId":"smp-SM242","name":"Eevee GX","number":"SM242","rarity":"","artist":"Aky CG Works","imageUrl":"https://tcgcompanion.fra1.digitaloceanspaces.com/images/sun%26moon/smp/SM242.png","imageUrlHiRes":"https://tcgcompanion.fra1.digitaloceanspaces.com/images/sun%26moon/smp/SM242_hires.png","setSlug":"sm-black-star-promos","setName":"SM Black Star Promos","setReleaseDate":"2017-02-03T00:00:00.000Z"},{"cardId":"smp-SM247","name":"Reshiram & Charizard","number":"SM247","rarity":"Promo","artist":"Aky CG Works","imageUrl":"https://tcgcompanion.fra1.digitaloceanspaces.com/images/sun%26moon/smp/SM247.png","imageUrlHiRes":"https://tcgcompanion.fra1.digitaloceanspaces.com/images/sun%26moon/smp/SM247_hires.png","setSlug":"sm-black-star-promos","setName":"SM Black Star Promos","setReleaseDate":"2017-02-03T00:00:00.000Z"}]