[{"cardId":"asc-128","name":"Poochyena","number":"128","rarity":"Common","artist":"Miki Tanaka","imageUrl":"https://tcgcompanion.fra1.digitaloceanspaces.com/images/megaevolution/asc/128.webp","imageUrlHiRes":"https://tcgcompanion.fra1.digitaloceanspaces.com/images/megaevolution/asc/128_hires.webp","setSlug":"ascended-heroes","setName":"Ascended Heroes","setReleaseDate":"2026-01-30T00:00:00.000Z"},{"cardId":"pfl-52","name":"Vibrava","number":"52","rarity":"Common","artist":"Miki Tanaka","imageUrl":"https://tcgcompanion.fra1.digitaloceanspaces.com/images/megaevolution/pfl/52.webp","imageUrlHiRes":"https://tcgcompanion.fra1.digitaloceanspaces.com/images/megaevolution/pfl/52_hires.webp","setSlug":"phantasmal-flames","setName":"Phantasmal Flames","setReleaseDate":"2025-11-14T00:00:00.000Z"},{"cardId":"meg-13","name":"Seedot","number":"13","rarity":"Common","artist":"Miki Tanaka","imageUrl":"https://tcgcompanion.fra1.digitaloceanspaces.com/images/megaevolution/meg/13.webp","imageUrlHiRes":"https://tcgcompanion.fra1.digitaloceanspaces.com/images/megaevolution/meg/13_hires.webp","setSlug":"mega-evolution","setName":"Mega Evolution","setReleaseDate":"2025-09-25T23:00:00.000Z"},{"cardId":"BLK-154","name":"Rufflet","number":"154","rarity":"Rare Secret","artist":"Miki Tanaka","imageUrl":"https://tcgcompanion.fra1.digitaloceanspaces.com/images/scarlet%26violet/BLK/154.webp","imageUrlHiRes":"https://tcgcompanion.fra1.digitaloceanspaces.com/images/scarlet%26violet/BLK/154_hires.webp","setSlug":"black-bolt","setName":"Black Bolt","setReleaseDate":"2025-07-17T22:00:00.000Z"},{"cardId":"dri-54","name":"Clamperl","number":"54","rarity":"Common","artist":"Miki Tanaka","imageUrl":"https://tcgcompanion.fra1.digitaloceanspaces.com/images/scarlet%26violet/dri/54.webp","imageUrlHiRes":"https://tcgcompanion.fra1.digitaloceanspaces.com/images/scarlet%26violet/dri/54_hires.webp","setSlug":"destined-rivals","setName":"Destined Rivals","setReleaseDate":"2025-05-29T23:00:00.000Z"},{"cardId":"jtg-112","name":"Bagon","number":"112","rarity":"Common","artist":"Miki Tanaka","imageUrl":"https://tcgcompanion.fra1.digitaloceanspaces.com/images/scarlet%26violet/jtg/112.png","imageUrlHiRes":"https://tcgcompanion.fra1.digitaloceanspaces.com/images/scarlet%26violet/jtg/112_hires.png","setSlug":"journey-together","setName":"Journey Together","setReleaseDate":"2025-03-28T00:00:00.000Z"},{"cardId":"ssp-64","name":"Stunfisk","number":"64","rarity":"Common","artist":"Miki Tanaka","imageUrl":"https://tcgcompanion.fra1.digitaloceanspaces.com/images/scarlet%26violet/ssp/64.png","imageUrlHiRes":"https://tcgcompanion.fra1.digitaloceanspaces.com/images/scarlet%26violet/ssp/64_hires.png","setSlug":"surging-sparks","setName":"Surging Sparks","setReleaseDate":"2024-11-08T00:00:00.000Z"},{"cardId":"scr-60","name":"Drifloon","number":"60","rarity":"Common","artist":"Miki Tanaka","imageUrl":"https://tcgcompanion.fra1.digitaloceanspaces.com/images/scarlet%26violet/scr/60.png","imageUrlHiRes":"https://tcgcompanion.fra1.digitaloceanspaces.com/images/scarlet%26violet/scr/60_hires.png","setSlug":"stellar-crown","setName":"Stellar Crown","setReleaseDate":"2024-09-13T00:00:00.000Z"},{"cardId":"scr-70","name":"Greavard","number":"70","rarity":"Common","artist":"Miki Tanaka","imageUrl":"https://tcgcompanion.fra1.digitaloceanspaces.com/images/scarlet%26violet/scr/70.png","imageUrlHiRes":"https://tcgcompanion.fra1.digitaloceanspaces.com/images/scarlet%26violet/scr/70_hires.png","setSlug":"stellar-crown","setName":"Stellar Crown","setReleaseDate":"2024-09-13T00:00:00.000Z"},{"cardId":"twm-108","name":"Glimmet","number":"108","rarity":"Common","artist":"Miki Tanaka","imageUrl":"https://tcgcompanion.fra1.digitaloceanspaces.com/images/scarlet%26violet/twm/108.png","imageUrlHiRes":"https://tcgcompanion.fra1.digitaloceanspaces.com/images/scarlet%26violet/twm/108_hires.png","setSlug":"twilight-masquerade","setName":"Twilight Masquerade","setReleaseDate":"2024-05-24T00:00:00.000Z"},{"cardId":"tef-105","name":"Poochyena","number":"105","rarity":"Common","artist":"Miki Tanaka","imageUrl":"https://tcgcompanion.fra1.digitaloceanspaces.com/images/scarlet%26violet/tef/105.png","imageUrlHiRes":"https://tcgcompanion.fra1.digitaloceanspaces.com/images/scarlet%26violet/tef/105_hires.png","setSlug":"temporal-forces","setName":"Temporal Forces","setReleaseDate":"2024-03-22T00:00:00.000Z"},{"cardId":"par-116","name":"Trubbish","number":"116","rarity":"Common","artist":"Miki Tanaka","imageUrl":"https://tcgcompanion.fra1.digitaloceanspaces.com/images/scarlet%26violet/par/116.png","imageUrlHiRes":"https://tcgcompanion.fra1.digitaloceanspaces.com/images/scarlet%26violet/par/116_hires.png","setSlug":"paradox-rift","setName":"Paradox Rift","setReleaseDate":"2023-11-02T00:00:00.000Z"},{"cardId":"par-127","name":"Ferroseed","number":"127","rarity":"Common","artist":"Miki Tanaka","imageUrl":"https://tcgcompanion.fra1.digitaloceanspaces.com/images/scarlet%26violet/par/127.png","imageUrlHiRes":"https://tcgcompanion.fra1.digitaloceanspaces.com/images/scarlet%26violet/par/127_hires.png","setSlug":"paradox-rift","setName":"Paradox Rift","setReleaseDate":"2023-11-02T00:00:00.000Z"},{"cardId":"obf-34","name":"Darumaka","number":"34","rarity":"Common","artist":"Miki Tanaka","imageUrl":"https://tcgcompanion.fra1.digitaloceanspaces.com/images/scarlet%26violet/obf/34.png","imageUrlHiRes":"https://tcgcompanion.fra1.digitaloceanspaces.com/images/scarlet%26violet/obf/34_hires.png","setSlug":"obsidian-flames","setName":"Obsidian Flames","setReleaseDate":"2023-08-11T00:00:00.000Z"},{"cardId":"obf-203","name":"Larvitar","number":"203","rarity":"Rare Secret","artist":"Miki Tanaka","imageUrl":"https://tcgcompanion.fra1.digitaloceanspaces.com/images/scarlet%26violet/obf/203.png","imageUrlHiRes":"https://tcgcompanion.fra1.digitaloceanspaces.com/images/scarlet%26violet/obf/203_hires.png","setSlug":"obsidian-flames","setName":"Obsidian Flames","setReleaseDate":"2023-08-11T00:00:00.000Z"},{"cardId":"pal-23","name":"Bramblin","number":"23","rarity":"Common","artist":"Miki Tanaka","imageUrl":"https://tcgcompanion.fra1.digitaloceanspaces.com/images/scarlet%26violet/pal/23.png","imageUrlHiRes":"https://tcgcompanion.fra1.digitaloceanspaces.com/images/scarlet%26violet/pal/23_hires.png","setSlug":"paldea-evolved","setName":"Paldea Evolved","setReleaseDate":"2023-06-09T00:00:00.000Z"},{"cardId":"pal-221","name":"Paldean Wooper","number":"221","rarity":"Rare Secret","artist":"Miki Tanaka","imageUrl":"https://tcgcompanion.fra1.digitaloceanspaces.com/images/scarlet%26violet/pal/221.png","imageUrlHiRes":"https://tcgcompanion.fra1.digitaloceanspaces.com/images/scarlet%26violet/pal/221_hires.png","setSlug":"paldea-evolved","setName":"Paldea Evolved","setReleaseDate":"2023-06-09T00:00:00.000Z"},{"cardId":"swsh14-35","name":"Luvdisc","number":"35","rarity":"Common","artist":"Miki Tanaka","imageUrl":"https://tcgcompanion.fra1.digitaloceanspaces.com/images/sword%26shield/swsh14/35.png","imageUrlHiRes":"https://tcgcompanion.fra1.digitaloceanspaces.com/images/sword%26shield/swsh14/35_hires.png","setSlug":"crown-zenith","setName":"Crown Zenith","setReleaseDate":"2023-01-20T00:00:00.000Z"},{"cardId":"swsh14-182","name":"Ditto","number":"GG22","rarity":"Rare Secret","artist":"Miki Tanaka","imageUrl":"https://tcgcompanion.fra1.digitaloceanspaces.com/images/sword%26shield/swsh14/GG22.png","imageUrlHiRes":"https://tcgcompanion.fra1.digitaloceanspaces.com/images/sword%26shield/swsh14/GG22_hires.png","setSlug":"crown-zenith","setName":"Crown Zenith","setReleaseDate":"2023-01-20T00:00:00.000Z"},{"cardId":"swsh13-51","name":"Chinchou","number":"51","rarity":"Common","artist":"Miki Tanaka","imageUrl":"https://tcgcompanion.fra1.digitaloceanspaces.com/images/sword%26shield/swsh13/51.png","imageUrlHiRes":"https://tcgcompanion.fra1.digitaloceanspaces.com/images/sword%26shield/swsh13/51_hires.png","setSlug":"silver-tempest","setName":"Silver Tempest","setReleaseDate":"2022-11-11T00:00:00.000Z"},{"cardId":"swsh13-142","name":"Swablu","number":"142","rarity":"Common","artist":"Miki Tanaka","imageUrl":"https://tcgcompanion.fra1.digitaloceanspaces.com/images/sword%26shield/swsh13/142.png","imageUrlHiRes":"https://tcgcompanion.fra1.digitaloceanspaces.com/images/sword%26shield/swsh13/142_hires.png","setSlug":"silver-tempest","setName":"Silver Tempest","setReleaseDate":"2022-11-11T00:00:00.000Z"},{"cardId":"swsh12-1","name":"Oddish","number":"1","rarity":"Common","artist":"Miki Tanaka","imageUrl":"https://tcgcompanion.fra1.digitaloceanspaces.com/images/sword%26shield/swsh12/1.png","imageUrlHiRes":"https://tcgcompanion.fra1.digitaloceanspaces.com/images/sword%26shield/swsh12/1_hires.png","setSlug":"lost-origin","setName":"Lost Origin","setReleaseDate":"2022-09-09T00:00:00.000Z"},{"cardId":"swsh12-30","name":"Poliwag","number":"30","rarity":"Common","artist":"Miki Tanaka","imageUrl":"https://tcgcompanion.fra1.digitaloceanspaces.com/images/sword%26shield/swsh12/30.png","imageUrlHiRes":"https://tcgcompanion.fra1.digitaloceanspaces.com/images/sword%26shield/swsh12/30_hires.png","setSlug":"lost-origin","setName":"Lost Origin","setReleaseDate":"2022-09-09T00:00:00.000Z"},{"cardId":"swsh12-95","name":"Gligar","number":"95","rarity":"Common","artist":"Miki Tanaka","imageUrl":"https://tcgcompanion.fra1.digitaloceanspaces.com/images/sword%26shield/swsh12/95.png","imageUrlHiRes":"https://tcgcompanion.fra1.digitaloceanspaces.com/images/sword%26shield/swsh12/95_hires.png","setSlug":"lost-origin","setName":"Lost Origin","setReleaseDate":"2022-09-09T00:00:00.000Z"},{"cardId":"swsh12-109","name":"Rockruff","number":"109","rarity":"Common","artist":"Miki Tanaka","imageUrl":"https://tcgcompanion.fra1.digitaloceanspaces.com/images/sword%26shield/swsh12/109.png","imageUrlHiRes":"https://tcgcompanion.fra1.digitaloceanspaces.com/images/sword%26shield/swsh12/109_hires.png","setSlug":"lost-origin","setName":"Lost Origin","setReleaseDate":"2022-09-09T00:00:00.000Z"},{"cardId":"swsh12-150","name":"Skwovet","number":"150","rarity":"Common","artist":"Miki Tanaka","imageUrl":"https://tcgcompanion.fra1.digitaloceanspaces.com/images/sword%26shield/swsh12/150.png","imageUrlHiRes":"https://tcgcompanion.fra1.digitaloceanspaces.com/images/sword%26shield/swsh12/150_hires.png","setSlug":"lost-origin","setName":"Lost Origin","setReleaseDate":"2022-09-09T00:00:00.000Z"},{"cardId":"swsh9-9","name":"Burmy","number":"9","rarity":"Common","artist":"Miki Tanaka","imageUrl":"https://tcgcompanion.fra1.digitaloceanspaces.com/images/sword%26shield/swsh9/9.png","imageUrlHiRes":"https://tcgcompanion.fra1.digitaloceanspaces.com/images/sword%26shield/swsh9/9_hires.png","setSlug":"brilliant-stars","setName":"Brilliant Stars","setReleaseDate":"2022-02-25T00:00:00.000Z"},{"cardId":"swsh9-127","name":"Hawlucha","number":"127","rarity":"Common","artist":"Miki Tanaka","imageUrl":"https://tcgcompanion.fra1.digitaloceanspaces.com/images/sword%26shield/swsh9/127.png","imageUrlHiRes":"https://tcgcompanion.fra1.digitaloceanspaces.com/images/sword%26shield/swsh9/127_hires.png","setSlug":"brilliant-stars","setName":"Brilliant Stars","setReleaseDate":"2022-02-25T00:00:00.000Z"},{"cardId":"swsh8-19","name":"Dewpider","number":"19","rarity":"Common","artist":"Miki Tanaka","imageUrl":"https://tcgcompanion.fra1.digitaloceanspaces.com/images/sword%26shield/swsh8/19.png","imageUrlHiRes":"https://tcgcompanion.fra1.digitaloceanspaces.com/images/sword%26shield/swsh8/19_hires.png","setSlug":"fusion-strike","setName":"Fusion Strike","setReleaseDate":"2021-12-11T00:00:00.000Z"},{"cardId":"swsh8-82","name":"Arrokuda","number":"82","rarity":"Common","artist":"Miki Tanaka","imageUrl":"https://tcgcompanion.fra1.digitaloceanspaces.com/images/sword%26shield/swsh8/82.png","imageUrlHiRes":"https://tcgcompanion.fra1.digitaloceanspaces.com/images/sword%26shield/swsh8/82_hires.png","setSlug":"fusion-strike","setName":"Fusion Strike","setReleaseDate":"2021-12-11T00:00:00.000Z"},{"cardId":"swsh8-195","name":"Goomy","number":"195","rarity":"Common","artist":"Miki Tanaka","imageUrl":"https://tcgcompanion.fra1.digitaloceanspaces.com/images/sword%26shield/swsh8/195.png","imageUrlHiRes":"https://tcgcompanion.fra1.digitaloceanspaces.com/images/sword%26shield/swsh8/195_hires.png","setSlug":"fusion-strike","setName":"Fusion Strike","setReleaseDate":"2021-12-11T00:00:00.000Z"},{"cardId":"swsh8-221","name":"Wooloo","number":"221","rarity":"Common","artist":"Miki Tanaka","imageUrl":"https://tcgcompanion.fra1.digitaloceanspaces.com/images/sword%26shield/swsh8/221.png","imageUrlHiRes":"https://tcgcompanion.fra1.digitaloceanspaces.com/images/sword%26shield/swsh8/221_hires.png","setSlug":"fusion-strike","setName":"Fusion Strike","setReleaseDate":"2021-12-11T00:00:00.000Z"},{"cardId":"swsh7-17","name":"Applin","number":"17","rarity":"Common","artist":"Miki Tanaka","imageUrl":"https://tcgcompanion.fra1.digitaloceanspaces.com/images/sword%26shield/swsh7/17.png","imageUrlHiRes":"https://tcgcompanion.fra1.digitaloceanspaces.com/images/sword%26shield/swsh7/17_hires.png","setSlug":"evolving-skies","setName":"Evolving Skies","setReleaseDate":"2021-08-27T00:00:00.000Z"},{"cardId":"swsh7-62","name":"Hypno","number":"62","rarity":"Uncommon","artist":"Miki Tanaka","imageUrl":"https://tcgcompanion.fra1.digitaloceanspaces.com/images/sword%26shield/swsh7/62.png","imageUrlHiRes":"https://tcgcompanion.fra1.digitaloceanspaces.com/images/sword%26shield/swsh7/62_hires.png","setSlug":"evolving-skies","setName":"Evolving Skies","setReleaseDate":"2021-08-27T00:00:00.000Z"},{"cardId":"swsh6-47","name":"Mareep","number":"47","rarity":"Common","artist":"Miki Tanaka","imageUrl":"https://tcgcompanion.fra1.digitaloceanspaces.com/images/sword%26shield/swsh6/47.png","imageUrlHiRes":"https://tcgcompanion.fra1.digitaloceanspaces.com/images/sword%26shield/swsh6/47_hires.png","setSlug":"chilling-reign","setName":"Chilling Reign","setReleaseDate":"2021-06-18T00:00:00.000Z"},{"cardId":"swsh6-96","name":"Galarian Weezing","number":"96","rarity":"Rare","artist":"Miki Tanaka","imageUrl":"https://tcgcompanion.fra1.digitaloceanspaces.com/images/sword%26shield/swsh6/96.png","imageUrlHiRes":"https://tcgcompanion.fra1.digitaloceanspaces.com/images/sword%26shield/swsh6/96_hires.png","setSlug":"chilling-reign","setName":"Chilling Reign","setReleaseDate":"2021-06-18T00:00:00.000Z"},{"cardId":"swsh5-75","name":"Conkeldurr","number":"75","rarity":"Rare","artist":"Miki Tanaka","imageUrl":"https://tcgcompanion.fra1.digitaloceanspaces.com/images/sword%26shield/swsh5/75.png","imageUrlHiRes":"https://tcgcompanion.fra1.digitaloceanspaces.com/images/sword%26shield/swsh5/75_hires.png","setSlug":"battle-styles","setName":"Battle Styles","setReleaseDate":"2021-03-19T00:00:00.000Z"},{"cardId":"swsh5-94","name":"Honchkrow","number":"94","rarity":"Uncommon","artist":"Miki Tanaka","imageUrl":"https://tcgcompanion.fra1.digitaloceanspaces.com/images/sword%26shield/swsh5/94.png","imageUrlHiRes":"https://tcgcompanion.fra1.digitaloceanspaces.com/images/sword%26shield/swsh5/94_hires.png","setSlug":"battle-styles","setName":"Battle Styles","setReleaseDate":"2021-03-19T00:00:00.000Z"},{"cardId":"swsh5-106","name":"Doublade","number":"106","rarity":"Uncommon","artist":"Miki Tanaka","imageUrl":"https://tcgcompanion.fra1.digitaloceanspaces.com/images/sword%26shield/swsh5/106.png","imageUrlHiRes":"https://tcgcompanion.fra1.digitaloceanspaces.com/images/sword%26shield/swsh5/106_hires.png","setSlug":"battle-styles","setName":"Battle Styles","setReleaseDate":"2021-03-19T00:00:00.000Z"},{"cardId":"swsh4-67","name":"Shuppet","number":"67","rarity":"Common","artist":"Miki Tanaka","imageUrl":"https://tcgcompanion.fra1.digitaloceanspaces.com/images/sword%26shield/swsh4/67.png","imageUrlHiRes":"https://tcgcompanion.fra1.digitaloceanspaces.com/images/sword%26shield/swsh4/67_hires.png","setSlug":"vivid-voltage","setName":"Vivid Voltage","setReleaseDate":"2020-11-13T00:00:00.000Z"},{"cardId":"swsh4-124","name":"Ferrothorn","number":"124","rarity":"Uncommon","artist":"Miki Tanaka","imageUrl":"https://tcgcompanion.fra1.digitaloceanspaces.com/images/sword%26shield/swsh4/124.png","imageUrlHiRes":"https://tcgcompanion.fra1.digitaloceanspaces.com/images/sword%26shield/swsh4/124_hires.png","setSlug":"vivid-voltage","setName":"Vivid Voltage","setReleaseDate":"2020-11-13T00:00:00.000Z"},{"cardId":"swsh35-3","name":"Kakuna","number":"3","rarity":"Common","artist":"Miki Tanaka","imageUrl":"https://tcgcompanion.fra1.digitaloceanspaces.com/images/sword%26shield/swsh35/3.png","imageUrlHiRes":"https://tcgcompanion.fra1.digitaloceanspaces.com/images/sword%26shield/swsh35/3_hires.png","setSlug":"champion-s-path","setName":"Champion's Path","setReleaseDate":"2020-09-24T00:00:00.000Z"},{"cardId":"swsh3-4","name":"Parasect","number":"4","rarity":"Uncommon","artist":"Miki Tanaka","imageUrl":"https://tcgcompanion.fra1.digitaloceanspaces.com/images/sword%26shield/swsh3/4.png","imageUrlHiRes":"https://tcgcompanion.fra1.digitaloceanspaces.com/images/sword%26shield/swsh3/4_hires.png","setSlug":"darkness-ablaze","setName":"Darkness Ablaze","setReleaseDate":"2020-08-13T00:00:00.000Z"},{"cardId":"swsh3-72","name":"Lunatone","number":"72","rarity":"Uncommon","artist":"Miki Tanaka","imageUrl":"https://tcgcompanion.fra1.digitaloceanspaces.com/images/sword%26shield/swsh3/72.png","imageUrlHiRes":"https://tcgcompanion.fra1.digitaloceanspaces.com/images/sword%26shield/swsh3/72_hires.png","setSlug":"darkness-ablaze","setName":"Darkness Ablaze","setReleaseDate":"2020-08-13T00:00:00.000Z"},{"cardId":"swsh3-92","name":"Solrock","number":"92","rarity":"Uncommon","artist":"Miki Tanaka","imageUrl":"https://tcgcompanion.fra1.digitaloceanspaces.com/images/sword%26shield/swsh3/92.png","imageUrlHiRes":"https://tcgcompanion.fra1.digitaloceanspaces.com/images/sword%26shield/swsh3/92_hires.png","setSlug":"darkness-ablaze","setName":"Darkness Ablaze","setReleaseDate":"2020-08-13T00:00:00.000Z"},{"cardId":"swsh2-8","name":"Lombre","number":"8","rarity":"Uncommon","artist":"Miki Tanaka","imageUrl":"https://tcgcompanion.fra1.digitaloceanspaces.com/images/sword%26shield/swsh2/8.png","imageUrlHiRes":"https://tcgcompanion.fra1.digitaloceanspaces.com/images/sword%26shield/swsh2/8_hires.png","setSlug":"rebel-clash","setName":"Rebel Clash","setReleaseDate":"2020-04-30T00:00:00.000Z"},{"cardId":"swsh2-96","name":"Nosepass","number":"96","rarity":"Common","artist":"Miki Tanaka","imageUrl":"https://tcgcompanion.fra1.digitaloceanspaces.com/images/sword%26shield/swsh2/96.png","imageUrlHiRes":"https://tcgcompanion.fra1.digitaloceanspaces.com/images/sword%26shield/swsh2/96_hires.png","setSlug":"rebel-clash","setName":"Rebel Clash","setReleaseDate":"2020-04-30T00:00:00.000Z"},{"cardId":"swsh1-8","name":"Durant","number":"8","rarity":"Rare","artist":"Miki Tanaka","imageUrl":"https://tcgcompanion.fra1.digitaloceanspaces.com/images/sword%26shield/swsh1/8.png","imageUrlHiRes":"https://tcgcompanion.fra1.digitaloceanspaces.com/images/sword%26shield/swsh1/8_hires.png","setSlug":"sword-and-shield","setName":"Sword & Shield","setReleaseDate":"2020-02-07T00:00:00.000Z"},{"cardId":"swsh1-102","name":"Baltoy","number":"102","rarity":"Common","artist":"Miki Tanaka","imageUrl":"https://tcgcompanion.fra1.digitaloceanspaces.com/images/sword%26shield/swsh1/102.png","imageUrlHiRes":"https://tcgcompanion.fra1.digitaloceanspaces.com/images/sword%26shield/swsh1/102_hires.png","setSlug":"sword-and-shield","setName":"Sword & Shield","setReleaseDate":"2020-02-07T00:00:00.000Z"},{"cardId":"sm12-27","name":"Magcargo","number":"27","rarity":"Rare","artist":"Miki Tanaka","imageUrl":"https://tcgcompanion.fra1.digitaloceanspaces.com/images/sun%26moon/sm12/27.png","imageUrlHiRes":"https://tcgcompanion.fra1.digitaloceanspaces.com/images/sun%26moon/sm12/27_hires.png","setSlug":"cosmic-eclipse","setName":"Cosmic Eclipse","setReleaseDate":"2019-11-01T00:00:00.000Z"},{"cardId":"sm12-121","name":"Crabrawler","number":"121","rarity":"Common","artist":"Miki Tanaka","imageUrl":"https://tcgcompanion.fra1.digitaloceanspaces.com/images/sun%26moon/sm12/121.png","imageUrlHiRes":"https://tcgcompanion.fra1.digitaloceanspaces.com/images/sun%26moon/sm12/121_hires.png","setSlug":"cosmic-eclipse","setName":"Cosmic Eclipse","setReleaseDate":"2019-11-01T00:00:00.000Z"},{"cardId":"sm12-169","name":"Aipom","number":"169","rarity":"Common","artist":"Miki Tanaka","imageUrl":"https://tcgcompanion.fra1.digitaloceanspaces.com/images/sun%26moon/sm12/169.png","imageUrlHiRes":"https://tcgcompanion.fra1.digitaloceanspaces.com/images/sun%26moon/sm12/169_hires.png","setSlug":"cosmic-eclipse","setName":"Cosmic Eclipse","setReleaseDate":"2019-11-01T00:00:00.000Z"},{"cardId":"mc19-8","name":"Mankey","number":"8","rarity":"Promo","artist":"Miki Tanaka","imageUrl":"https://tcgcompanion.fra1.digitaloceanspaces.com/images/sun%26moon/mc19/8.png","imageUrlHiRes":"https://tcgcompanion.fra1.digitaloceanspaces.com/images/sun%26moon/mc19/8_hires.png","setSlug":"mcdonald-s-collection-2019","setName":"McDonald's Collection 2019","setReleaseDate":"2019-10-15T00:00:00.000Z"},{"cardId":"sm11-185","name":"Komala","number":"185","rarity":"Uncommon","artist":"Miki Tanaka","imageUrl":"https://tcgcompanion.fra1.digitaloceanspaces.com/images/sun%26moon/sm11/185.png","imageUrlHiRes":"https://tcgcompanion.fra1.digitaloceanspaces.com/images/sun%26moon/sm11/185_hires.png","setSlug":"unified-minds","setName":"Unified Minds","setReleaseDate":"2019-08-02T00:00:00.000Z"},{"cardId":"sm11-218","name":"Slowpoke & Psyduck-GX","number":"218","rarity":"Rare Ultra","artist":"Miki Tanaka","imageUrl":"https://tcgcompanion.fra1.digitaloceanspaces.com/images/sun%26moon/sm11/218.png","imageUrlHiRes":"https://tcgcompanion.fra1.digitaloceanspaces.com/images/sun%26moon/sm11/218_hires.png","setSlug":"unified-minds","setName":"Unified Minds","setReleaseDate":"2019-08-02T00:00:00.000Z"},{"cardId":"sm10-69","name":"Haunter","number":"69","rarity":"Uncommon","artist":"Miki Tanaka","imageUrl":"https://tcgcompanion.fra1.digitaloceanspaces.com/images/sun%26moon/sm10/69.png","imageUrlHiRes":"https://tcgcompanion.fra1.digitaloceanspaces.com/images/sun%26moon/sm10/69_hires.png","setSlug":"unbroken-bonds","setName":"Unbroken Bonds","setReleaseDate":"2019-05-03T00:00:00.000Z"},{"cardId":"sm10-71","name":"Drowzee","number":"71","rarity":"Common","artist":"Miki Tanaka","imageUrl":"https://tcgcompanion.fra1.digitaloceanspaces.com/images/sun%26moon/sm10/71.png","imageUrlHiRes":"https://tcgcompanion.fra1.digitaloceanspaces.com/images/sun%26moon/sm10/71_hires.png","setSlug":"unbroken-bonds","setName":"Unbroken Bonds","setReleaseDate":"2019-05-03T00:00:00.000Z"},{"cardId":"sm10-77","name":"Misdreavus","number":"77","rarity":"Common","artist":"Miki Tanaka","imageUrl":"https://tcgcompanion.fra1.digitaloceanspaces.com/images/sun%26moon/sm10/77.png","imageUrlHiRes":"https://tcgcompanion.fra1.digitaloceanspaces.com/images/sun%26moon/sm10/77_hires.png","setSlug":"unbroken-bonds","setName":"Unbroken Bonds","setReleaseDate":"2019-05-03T00:00:00.000Z"},{"cardId":"sm8-41","name":"Quilava","number":"41","rarity":"Uncommon","artist":"Miki Tanaka","imageUrl":"https://tcgcompanion.fra1.digitaloceanspaces.com/images/sun%26moon/sm8/41.png","imageUrlHiRes":"https://tcgcompanion.fra1.digitaloceanspaces.com/images/sun%26moon/sm8/41_hires.png","setSlug":"lost-thunder","setName":"Lost Thunder","setReleaseDate":"2018-11-02T00:00:00.000Z"},{"cardId":"sm8-81","name":"Blitzle","number":"81","rarity":"Common","artist":"Miki Tanaka","imageUrl":"https://tcgcompanion.fra1.digitaloceanspaces.com/images/sun%26moon/sm8/81.png","imageUrlHiRes":"https://tcgcompanion.fra1.digitaloceanspaces.com/images/sun%26moon/sm8/81_hires.png","setSlug":"lost-thunder","setName":"Lost Thunder","setReleaseDate":"2018-11-02T00:00:00.000Z"},{"cardId":"sm8-96","name":"Sableye","number":"96","rarity":"Uncommon","artist":"Miki Tanaka","imageUrl":"https://tcgcompanion.fra1.digitaloceanspaces.com/images/sun%26moon/sm8/96.png","imageUrlHiRes":"https://tcgcompanion.fra1.digitaloceanspaces.com/images/sun%26moon/sm8/96_hires.png","setSlug":"lost-thunder","setName":"Lost Thunder","setReleaseDate":"2018-11-02T00:00:00.000Z"},{"cardId":"sm8-163","name":"Pikipek","number":"163","rarity":"Common","artist":"Miki Tanaka","imageUrl":"https://tcgcompanion.fra1.digitaloceanspaces.com/images/sun%26moon/sm8/163.png","imageUrlHiRes":"https://tcgcompanion.fra1.digitaloceanspaces.com/images/sun%26moon/sm8/163_hires.png","setSlug":"lost-thunder","setName":"Lost Thunder","setReleaseDate":"2018-11-02T00:00:00.000Z"},{"cardId":"sm7-2","name":"Weepinbell","number":"2","rarity":"Uncommon","artist":"Miki Tanaka","imageUrl":"https://tcgcompanion.fra1.digitaloceanspaces.com/images/sun%26moon/sm7/2.png","imageUrlHiRes":"https://tcgcompanion.fra1.digitaloceanspaces.com/images/sun%26moon/sm7/2_hires.png","setSlug":"celestial-storm","setName":"Celestial Storm","setReleaseDate":"2018-08-03T00:00:00.000Z"},{"cardId":"sm7-3","name":"Victreebel","number":"3","rarity":"Rare Holo","artist":"Miki Tanaka","imageUrl":"https://tcgcompanion.fra1.digitaloceanspaces.com/images/sun%26moon/sm7/3.png","imageUrlHiRes":"https://tcgcompanion.fra1.digitaloceanspaces.com/images/sun%26moon/sm7/3_hires.png","setSlug":"celestial-storm","setName":"Celestial Storm","setReleaseDate":"2018-08-03T00:00:00.000Z"},{"cardId":"sm6-7","name":"Spewpa","number":"7","rarity":"Uncommon","artist":"Miki Tanaka","imageUrl":"https://tcgcompanion.fra1.digitaloceanspaces.com/images/sun%26moon/sm6/7.png","imageUrlHiRes":"https://tcgcompanion.fra1.digitaloceanspaces.com/images/sun%26moon/sm6/7_hires.png","setSlug":"forbidden-light","setName":"Forbidden Light","setReleaseDate":"2018-05-04T00:00:00.000Z"},{"cardId":"sm6-29","name":"Bergmite","number":"29","rarity":"Common","artist":"Miki Tanaka","imageUrl":"https://tcgcompanion.fra1.digitaloceanspaces.com/images/sun%26moon/sm6/29.png","imageUrlHiRes":"https://tcgcompanion.fra1.digitaloceanspaces.com/images/sun%26moon/sm6/29_hires.png","setSlug":"forbidden-light","setName":"Forbidden Light","setReleaseDate":"2018-05-04T00:00:00.000Z"},{"cardId":"sm6-37","name":"Helioptile","number":"37","rarity":"Common","artist":"Miki Tanaka","imageUrl":"https://tcgcompanion.fra1.digitaloceanspaces.com/images/sun%26moon/sm6/37.png","imageUrlHiRes":"https://tcgcompanion.fra1.digitaloceanspaces.com/images/sun%26moon/sm6/37_hires.png","setSlug":"forbidden-light","setName":"Forbidden Light","setReleaseDate":"2018-05-04T00:00:00.000Z"},{"cardId":"sm4-44","name":"Pumpkaboo","number":"44","rarity":"Common","artist":"Miki Tanaka","imageUrl":"https://tcgcompanion.fra1.digitaloceanspaces.com/images/sun%26moon/sm4/44.png","imageUrlHiRes":"https://tcgcompanion.fra1.digitaloceanspaces.com/images/sun%26moon/sm4/44_hires.png","setSlug":"crimson-invasion","setName":"Crimson Invasion","setReleaseDate":"2017-11-03T00:00:00.000Z"},{"cardId":"sm4-50","name":"Mankey","number":"50","rarity":"Common","artist":"Miki Tanaka","imageUrl":"https://tcgcompanion.fra1.digitaloceanspaces.com/images/sun%26moon/sm4/50.png","imageUrlHiRes":"https://tcgcompanion.fra1.digitaloceanspaces.com/images/sun%26moon/sm4/50_hires.png","setSlug":"crimson-invasion","setName":"Crimson Invasion","setReleaseDate":"2017-11-03T00:00:00.000Z"},{"cardId":"sm3-22","name":"Pansear","number":"22","rarity":"Common","artist":"Miki Tanaka","imageUrl":"https://tcgcompanion.fra1.digitaloceanspaces.com/images/sun%26moon/sm3/22.png","imageUrlHiRes":"https://tcgcompanion.fra1.digitaloceanspaces.com/images/sun%26moon/sm3/22_hires.png","setSlug":"burning-shadows","setName":"Burning Shadows","setReleaseDate":"2017-08-05T00:00:00.000Z"},{"cardId":"sm3-59","name":"Espurr","number":"59","rarity":"Common","artist":"Miki Tanaka","imageUrl":"https://tcgcompanion.fra1.digitaloceanspaces.com/images/sun%26moon/sm3/59.png","imageUrlHiRes":"https://tcgcompanion.fra1.digitaloceanspaces.com/images/sun%26moon/sm3/59_hires.png","setSlug":"burning-shadows","setName":"Burning Shadows","setReleaseDate":"2017-08-05T00:00:00.000Z"},{"cardId":"sm2-29","name":"Wailmer","number":"29","rarity":"Common","artist":"Miki Tanaka","imageUrl":"https://tcgcompanion.fra1.digitaloceanspaces.com/images/sun%26moon/sm2/29.png","imageUrlHiRes":"https://tcgcompanion.fra1.digitaloceanspaces.com/images/sun%26moon/sm2/29_hires.png","setSlug":"guardians-rising","setName":"Guardians Rising","setReleaseDate":"2017-05-05T00:00:00.000Z"},{"cardId":"sm2-89","name":"Clefable","number":"89","rarity":"Uncommon","artist":"Miki Tanaka","imageUrl":"https://tcgcompanion.fra1.digitaloceanspaces.com/images/sun%26moon/sm2/89.png","imageUrlHiRes":"https://tcgcompanion.fra1.digitaloceanspaces.com/images/sun%26moon/sm2/89_hires.png","setSlug":"guardians-rising","setName":"Guardians Rising","setReleaseDate":"2017-05-05T00:00:00.000Z"},{"cardId":"sm1-68","name":"Hariyama","number":"68","rarity":"Rare","artist":"Miki Tanaka","imageUrl":"https://tcgcompanion.fra1.digitaloceanspaces.com/images/sun%26moon/sm1/68.png","imageUrlHiRes":"https://tcgcompanion.fra1.digitaloceanspaces.com/images/sun%26moon/sm1/68_hires.png","setSlug":"sun-and-moon","setName":"Sun & Moon","setReleaseDate":"2017-02-03T00:00:00.000Z"},{"cardId":"xy11-47","name":"Drifblim","number":"47","rarity":"Uncommon","artist":"Miki Tanaka","imageUrl":"https://tcgcompanion.fra1.digitaloceanspaces.com/images/xy/xy11/47.png","imageUrlHiRes":"https://tcgcompanion.fra1.digitaloceanspaces.com/images/xy/xy11/47_hires.png","setSlug":"steam-siege","setName":"Steam Siege","setReleaseDate":"2016-08-03T00:00:00.000Z"},{"cardId":"xy11-71","name":"Klink","number":"71","rarity":"Common","artist":"Miki Tanaka","imageUrl":"https://tcgcompanion.fra1.digitaloceanspaces.com/images/xy/xy11/71.png","imageUrlHiRes":"https://tcgcompanion.fra1.digitaloceanspaces.com/images/xy/xy11/71_hires.png","setSlug":"steam-siege","setName":"Steam Siege","setReleaseDate":"2016-08-03T00:00:00.000Z"},{"cardId":"g1-22","name":"Magikarp","number":"22","rarity":"Common","artist":"Miki Tanaka","imageUrl":"https://tcgcompanion.fra1.digitaloceanspaces.com/images/xy/g1/22.png","imageUrlHiRes":"https://tcgcompanion.fra1.digitaloceanspaces.com/images/xy/g1/22_hires.png","setSlug":"generations","setName":"Generations","setReleaseDate":"2016-02-22T00:00:00.000Z"},{"cardId":"g1-32","name":"Slowpoke","number":"32","rarity":"Common","artist":"Miki Tanaka","imageUrl":"https://tcgcompanion.fra1.digitaloceanspaces.com/images/xy/g1/32.png","imageUrlHiRes":"https://tcgcompanion.fra1.digitaloceanspaces.com/images/xy/g1/32_hires.png","setSlug":"generations","setName":"Generations","setReleaseDate":"2016-02-22T00:00:00.000Z"},{"cardId":"g1-rc2","name":"Shroomish","number":"RC2","rarity":"Common","artist":"Miki Tanaka","imageUrl":"https://tcgcompanion.fra1.digitaloceanspaces.com/images/xy/g1/RC2.png","imageUrlHiRes":"https://tcgcompanion.fra1.digitaloceanspaces.com/images/xy/g1/RC2_hires.png","setSlug":"generations","setName":"Generations","setReleaseDate":"2016-02-22T00:00:00.000Z"},{"cardId":"xy9-33","name":"Tympole","number":"33","rarity":"Common","artist":"Miki Tanaka","imageUrl":"https://tcgcompanion.fra1.digitaloceanspaces.com/images/xy/xy9/33.png","imageUrlHiRes":"https://tcgcompanion.fra1.digitaloceanspaces.com/images/xy/xy9/33_hires.png","setSlug":"breakpoint","setName":"BREAKpoint","setReleaseDate":"2016-02-03T00:00:00.000Z"},{"cardId":"xy8-10","name":"Quilladin","number":"10","rarity":"Uncommon","artist":"Miki Tanaka","imageUrl":"https://tcgcompanion.fra1.digitaloceanspaces.com/images/xy/xy8/10.png","imageUrlHiRes":"https://tcgcompanion.fra1.digitaloceanspaces.com/images/xy/xy8/10_hires.png","setSlug":"breakthrough","setName":"BREAKthrough","setReleaseDate":"2015-11-04T00:00:00.000Z"},{"cardId":"xy8-119","name":"Hoothoot","number":"119","rarity":"Common","artist":"Miki Tanaka","imageUrl":"https://tcgcompanion.fra1.digitaloceanspaces.com/images/xy/xy8/119.png","imageUrlHiRes":"https://tcgcompanion.fra1.digitaloceanspaces.com/images/xy/xy8/119_hires.png","setSlug":"breakthrough","setName":"BREAKthrough","setReleaseDate":"2015-11-04T00:00:00.000Z"},{"cardId":"xy7-24","name":"Regice","number":"24","rarity":"Rare","artist":"Miki Tanaka","imageUrl":"https://tcgcompanion.fra1.digitaloceanspaces.com/images/xy/xy7/24.png","imageUrlHiRes":"https://tcgcompanion.fra1.digitaloceanspaces.com/images/xy/xy7/24_hires.png","setSlug":"ancient-origins","setName":"Ancient Origins","setReleaseDate":"2015-08-12T00:00:00.000Z"},{"cardId":"xy6-49","name":"Dratini","number":"49","rarity":"Common","artist":"Miki Tanaka","imageUrl":"https://tcgcompanion.fra1.digitaloceanspaces.com/images/xy/xy6/49.png","imageUrlHiRes":"https://tcgcompanion.fra1.digitaloceanspaces.com/images/xy/xy6/49_hires.png","setSlug":"roaring-skies","setName":"Roaring Skies","setReleaseDate":"2015-05-06T00:00:00.000Z"},{"cardId":"xy5-22","name":"Slugma","number":"22","rarity":"Common","artist":"Miki Tanaka","imageUrl":"https://tcgcompanion.fra1.digitaloceanspaces.com/images/xy/xy5/22.png","imageUrlHiRes":"https://tcgcompanion.fra1.digitaloceanspaces.com/images/xy/xy5/22_hires.png","setSlug":"primal-clash","setName":"Primal Clash","setReleaseDate":"2015-02-04T00:00:00.000Z"},{"cardId":"xy5-51","name":"Gorebyss","number":"51","rarity":"Uncommon","artist":"Miki Tanaka","imageUrl":"https://tcgcompanion.fra1.digitaloceanspaces.com/images/xy/xy5/51.png","imageUrlHiRes":"https://tcgcompanion.fra1.digitaloceanspaces.com/images/xy/xy5/51_hires.png","setSlug":"primal-clash","setName":"Primal Clash","setReleaseDate":"2015-02-04T00:00:00.000Z"},{"cardId":"bw11-34","name":"Prinplup","number":"34","rarity":"Uncommon","artist":"Miki Tanaka","imageUrl":"https://tcgcompanion.fra1.digitaloceanspaces.com/images/black%26white/bw11/34.png","imageUrlHiRes":"https://tcgcompanion.fra1.digitaloceanspaces.com/images/black%26white/bw11/34_hires.png","setSlug":"legendary-treasures","setName":"Legendary Treasures","setReleaseDate":"2013-11-06T00:00:00.000Z"},{"cardId":"bw11-108","name":"Tornadus","number":"108","rarity":"Rare Holo","artist":"Miki Tanaka","imageUrl":"https://tcgcompanion.fra1.digitaloceanspaces.com/images/black%26white/bw11/108.png","imageUrlHiRes":"https://tcgcompanion.fra1.digitaloceanspaces.com/images/black%26white/bw11/108_hires.png","setSlug":"legendary-treasures","setName":"Legendary Treasures","setReleaseDate":"2013-11-06T00:00:00.000Z"},{"cardId":"bw7-44","name":"Frillish","number":"44","rarity":"Common","artist":"Miki Tanaka","imageUrl":"https://tcgcompanion.fra1.digitaloceanspaces.com/images/black%26white/bw7/44.png","imageUrlHiRes":"https://tcgcompanion.fra1.digitaloceanspaces.com/images/black%26white/bw7/44_hires.png","setSlug":"boundaries-crossed","setName":"Boundaries Crossed","setReleaseDate":"2012-11-07T00:00:00.000Z"},{"cardId":"bw7-70","name":"Woobat","number":"70","rarity":"Common","artist":"Miki Tanaka","imageUrl":"https://tcgcompanion.fra1.digitaloceanspaces.com/images/black%26white/bw7/70.png","imageUrlHiRes":"https://tcgcompanion.fra1.digitaloceanspaces.com/images/black%26white/bw7/70_hires.png","setSlug":"boundaries-crossed","setName":"Boundaries Crossed","setReleaseDate":"2012-11-07T00:00:00.000Z"},{"cardId":"bw6-35","name":"Palpitoad","number":"35","rarity":"Uncommon","artist":"Miki Tanaka","imageUrl":"https://tcgcompanion.fra1.digitaloceanspaces.com/images/black%26white/bw6/35.png","imageUrlHiRes":"https://tcgcompanion.fra1.digitaloceanspaces.com/images/black%26white/bw6/35_hires.png","setSlug":"dragons-exalted","setName":"Dragons Exalted","setReleaseDate":"2012-08-15T00:00:00.000Z"},{"cardId":"bw6-37","name":"Alomomola","number":"37","rarity":"Rare","artist":"Miki Tanaka","imageUrl":"https://tcgcompanion.fra1.digitaloceanspaces.com/images/black%26white/bw6/37.png","imageUrlHiRes":"https://tcgcompanion.fra1.digitaloceanspaces.com/images/black%26white/bw6/37_hires.png","setSlug":"dragons-exalted","setName":"Dragons Exalted","setReleaseDate":"2012-08-15T00:00:00.000Z"},{"cardId":"bw5-42","name":"Joltik","number":"42","rarity":"Common","artist":"Miki Tanaka","imageUrl":"https://tcgcompanion.fra1.digitaloceanspaces.com/images/black%26white/bw5/42.png","imageUrlHiRes":"https://tcgcompanion.fra1.digitaloceanspaces.com/images/black%26white/bw5/42_hires.png","setSlug":"dark-explorers","setName":"Dark Explorers","setReleaseDate":"2012-05-09T00:00:00.000Z"},{"cardId":"hgss1-18","name":"Exeggutor","number":"18","rarity":"Rare","artist":"Miki Tanaka","imageUrl":"https://tcgcompanion.fra1.digitaloceanspaces.com/images/heartgold%26soulsilver/hgss1/18.png","imageUrlHiRes":"https://tcgcompanion.fra1.digitaloceanspaces.com/images/heartgold%26soulsilver/hgss1/18_hires.png","setSlug":"heartgold-and-soulsilver","setName":"HeartGold & SoulSilver","setReleaseDate":"2010-02-10T00:00:00.000Z"},{"cardId":"hgss1-47","name":"Miltank","number":"47","rarity":"Uncommon","artist":"Miki Tanaka","imageUrl":"https://tcgcompanion.fra1.digitaloceanspaces.com/images/heartgold%26soulsilver/hgss1/47.png","imageUrlHiRes":"https://tcgcompanion.fra1.digitaloceanspaces.com/images/heartgold%26soulsilver/hgss1/47_hires.png","setSlug":"heartgold-and-soulsilver","setName":"HeartGold & SoulSilver","setReleaseDate":"2010-02-10T00:00:00.000Z"},{"cardId":"hgss1-63","name":"Exeggcute","number":"63","rarity":"Common","artist":"Miki Tanaka","imageUrl":"https://tcgcompanion.fra1.digitaloceanspaces.com/images/heartgold%26soulsilver/hgss1/63.png","imageUrlHiRes":"https://tcgcompanion.fra1.digitaloceanspaces.com/images/heartgold%26soulsilver/hgss1/63_hires.png","setSlug":"heartgold-and-soulsilver","setName":"HeartGold & SoulSilver","setReleaseDate":"2010-02-10T00:00:00.000Z"},{"cardId":"hgss1-64","name":"Girafarig","number":"64","rarity":"Common","artist":"Miki Tanaka","imageUrl":"https://tcgcompanion.fra1.digitaloceanspaces.com/images/heartgold%26soulsilver/hgss1/64.png","imageUrlHiRes":"https://tcgcompanion.fra1.digitaloceanspaces.com/images/heartgold%26soulsilver/hgss1/64_hires.png","setSlug":"heartgold-and-soulsilver","setName":"HeartGold & SoulSilver","setReleaseDate":"2010-02-10T00:00:00.000Z"},{"cardId":"pl4-24","name":"Pelipper","number":"24","rarity":"Rare","artist":"Miki Tanaka","imageUrl":"https://tcgcompanion.fra1.digitaloceanspaces.com/images/platinum/pl4/24.png","imageUrlHiRes":"https://tcgcompanion.fra1.digitaloceanspaces.com/images/platinum/pl4/24_hires.png","setSlug":"arceus","setName":"Arceus","setReleaseDate":"2009-11-04T00:00:00.000Z"},{"cardId":"pl4-51","name":"Wormadam Trash Cloak","number":"51","rarity":"Uncommon","artist":"Miki Tanaka","imageUrl":"https://tcgcompanion.fra1.digitaloceanspaces.com/images/platinum/pl4/51.png","imageUrlHiRes":"https://tcgcompanion.fra1.digitaloceanspaces.com/images/platinum/pl4/51_hires.png","setSlug":"arceus","setName":"Arceus","setReleaseDate":"2009-11-04T00:00:00.000Z"},{"cardId":"pl4-73","name":"Rattata","number":"73","rarity":"Common","artist":"Miki Tanaka","imageUrl":"https://tcgcompanion.fra1.digitaloceanspaces.com/images/platinum/pl4/73.png","imageUrlHiRes":"https://tcgcompanion.fra1.digitaloceanspaces.com/images/platinum/pl4/73_hires.png","setSlug":"arceus","setName":"Arceus","setReleaseDate":"2009-11-04T00:00:00.000Z"},{"cardId":"pl3-46","name":"Spinda","number":"46","rarity":"Rare","artist":"Miki Tanaka","imageUrl":"https://tcgcompanion.fra1.digitaloceanspaces.com/images/platinum/pl3/46.png","imageUrlHiRes":"https://tcgcompanion.fra1.digitaloceanspaces.com/images/platinum/pl3/46_hires.png","setSlug":"supreme-victors","setName":"Supreme Victors","setReleaseDate":"2009-08-19T00:00:00.000Z"},{"cardId":"pl3-115","name":"Mime Jr.","number":"115","rarity":"Common","artist":"Miki Tanaka","imageUrl":"https://tcgcompanion.fra1.digitaloceanspaces.com/images/platinum/pl3/115.png","imageUrlHiRes":"https://tcgcompanion.fra1.digitaloceanspaces.com/images/platinum/pl3/115_hires.png","setSlug":"supreme-victors","setName":"Supreme Victors","setReleaseDate":"2009-08-19T00:00:00.000Z"},{"cardId":"pl3-130","name":"Surskit","number":"130","rarity":"Common","artist":"Miki Tanaka","imageUrl":"https://tcgcompanion.fra1.digitaloceanspaces.com/images/platinum/pl3/130.png","imageUrlHiRes":"https://tcgcompanion.fra1.digitaloceanspaces.com/images/platinum/pl3/130_hires.png","setSlug":"supreme-victors","setName":"Supreme Victors","setReleaseDate":"2009-08-19T00:00:00.000Z"},{"cardId":"pl2-71","name":"Nidoran♀","number":"71","rarity":"Common","artist":"Miki Tanaka","imageUrl":"https://tcgcompanion.fra1.digitaloceanspaces.com/images/platinum/pl2/71.png","imageUrlHiRes":"https://tcgcompanion.fra1.digitaloceanspaces.com/images/platinum/pl2/71_hires.png","setSlug":"rising-rivals","setName":"Rising Rivals","setReleaseDate":"2009-05-16T00:00:00.000Z"},{"cardId":"pl2-78","name":"Seedot","number":"78","rarity":"Common","artist":"Miki Tanaka","imageUrl":"https://tcgcompanion.fra1.digitaloceanspaces.com/images/platinum/pl2/78.png","imageUrlHiRes":"https://tcgcompanion.fra1.digitaloceanspaces.com/images/platinum/pl2/78_hires.png","setSlug":"rising-rivals","setName":"Rising Rivals","setReleaseDate":"2009-05-16T00:00:00.000Z"},{"cardId":"pl2-80","name":"Shellos West Sea","number":"80","rarity":"Common","artist":"Miki Tanaka","imageUrl":"https://tcgcompanion.fra1.digitaloceanspaces.com/images/platinum/pl2/80.png","imageUrlHiRes":"https://tcgcompanion.fra1.digitaloceanspaces.com/images/platinum/pl2/80_hires.png","setSlug":"rising-rivals","setName":"Rising Rivals","setReleaseDate":"2009-05-16T00:00:00.000Z"},{"cardId":"pl1-74","name":"Electrike","number":"74","rarity":"Common","artist":"Miki Tanaka","imageUrl":"https://tcgcompanion.fra1.digitaloceanspaces.com/images/platinum/pl1/74.png","imageUrlHiRes":"https://tcgcompanion.fra1.digitaloceanspaces.com/images/platinum/pl1/74_hires.png","setSlug":"platinum","setName":"Platinum","setReleaseDate":"2009-02-11T00:00:00.000Z"},{"cardId":"pl1-89","name":"Ralts","number":"89","rarity":"Common","artist":"Miki Tanaka","imageUrl":"https://tcgcompanion.fra1.digitaloceanspaces.com/images/platinum/pl1/89.png","imageUrlHiRes":"https://tcgcompanion.fra1.digitaloceanspaces.com/images/platinum/pl1/89_hires.png","setSlug":"platinum","setName":"Platinum","setReleaseDate":"2009-02-11T00:00:00.000Z"},{"cardId":"pl1-90","name":"Remoraid","number":"90","rarity":"Common","artist":"Miki Tanaka","imageUrl":"https://tcgcompanion.fra1.digitaloceanspaces.com/images/platinum/pl1/90.png","imageUrlHiRes":"https://tcgcompanion.fra1.digitaloceanspaces.com/images/platinum/pl1/90_hires.png","setSlug":"platinum","setName":"Platinum","setReleaseDate":"2009-02-11T00:00:00.000Z"},{"cardId":"dp7-55","name":"Bronzor","number":"55","rarity":"Common","artist":"Miki Tanaka","imageUrl":"https://tcgcompanion.fra1.digitaloceanspaces.com/images/diamond%26pearl/dp7/55.png","imageUrlHiRes":"https://tcgcompanion.fra1.digitaloceanspaces.com/images/diamond%26pearl/dp7/55_hires.png","setSlug":"stormfront","setName":"Stormfront","setReleaseDate":"2008-11-01T00:00:00.000Z"},{"cardId":"dp7-57","name":"Combee","number":"57","rarity":"Common","artist":"Miki Tanaka","imageUrl":"https://tcgcompanion.fra1.digitaloceanspaces.com/images/diamond%26pearl/dp7/57.png","imageUrlHiRes":"https://tcgcompanion.fra1.digitaloceanspaces.com/images/diamond%26pearl/dp7/57_hires.png","setSlug":"stormfront","setName":"Stormfront","setReleaseDate":"2008-11-01T00:00:00.000Z"},{"cardId":"dp7-81","name":"Voltorb","number":"81","rarity":"Common","artist":"Miki Tanaka","imageUrl":"https://tcgcompanion.fra1.digitaloceanspaces.com/images/diamond%26pearl/dp7/81.png","imageUrlHiRes":"https://tcgcompanion.fra1.digitaloceanspaces.com/images/diamond%26pearl/dp7/81_hires.png","setSlug":"stormfront","setName":"Stormfront","setReleaseDate":"2008-11-01T00:00:00.000Z"},{"cardId":"ex15-41","name":"Togepi δ","number":"41","rarity":"Uncommon","artist":"Miki Tanaka","imageUrl":"https://tcgcompanion.fra1.digitaloceanspaces.com/images/ex/ex15/41.png","imageUrlHiRes":"https://tcgcompanion.fra1.digitaloceanspaces.com/images/ex/ex15/41_hires.png","setSlug":"dragon-frontiers","setName":"Dragon Frontiers","setReleaseDate":"2006-11-01T00:00:00.000Z"},{"cardId":"ex15-64","name":"Smoochum δ","number":"64","rarity":"Common","artist":"Miki Tanaka","imageUrl":"https://tcgcompanion.fra1.digitaloceanspaces.com/images/ex/ex15/64.png","imageUrlHiRes":"https://tcgcompanion.fra1.digitaloceanspaces.com/images/ex/ex15/64_hires.png","setSlug":"dragon-frontiers","setName":"Dragon Frontiers","setReleaseDate":"2006-11-01T00:00:00.000Z"},{"cardId":"ex15-65","name":"Swablu δ","number":"65","rarity":"Common","artist":"Miki Tanaka","imageUrl":"https://tcgcompanion.fra1.digitaloceanspaces.com/images/ex/ex15/65.png","imageUrlHiRes":"https://tcgcompanion.fra1.digitaloceanspaces.com/images/ex/ex15/65_hires.png","setSlug":"dragon-frontiers","setName":"Dragon Frontiers","setReleaseDate":"2006-11-01T00:00:00.000Z"},{"cardId":"ex15-66","name":"Taillow δ","number":"66","rarity":"Common","artist":"Miki Tanaka","imageUrl":"https://tcgcompanion.fra1.digitaloceanspaces.com/images/ex/ex15/66.png","imageUrlHiRes":"https://tcgcompanion.fra1.digitaloceanspaces.com/images/ex/ex15/66_hires.png","setSlug":"dragon-frontiers","setName":"Dragon Frontiers","setReleaseDate":"2006-11-01T00:00:00.000Z"},{"cardId":"ex14-21","name":"Igglybuff","number":"21","rarity":"Rare","artist":"Miki Tanaka","imageUrl":"https://tcgcompanion.fra1.digitaloceanspaces.com/images/ex/ex14/21.png","imageUrlHiRes":"https://tcgcompanion.fra1.digitaloceanspaces.com/images/ex/ex14/21_hires.png","setSlug":"crystal-guardians","setName":"Crystal Guardians","setReleaseDate":"2006-08-30T00:00:00.000Z"},{"cardId":"ex14-41","name":"Skitty","number":"41","rarity":"Uncommon","artist":"Miki Tanaka","imageUrl":"https://tcgcompanion.fra1.digitaloceanspaces.com/images/ex/ex14/41.png","imageUrlHiRes":"https://tcgcompanion.fra1.digitaloceanspaces.com/images/ex/ex14/41_hires.png","setSlug":"crystal-guardians","setName":"Crystal Guardians","setReleaseDate":"2006-08-30T00:00:00.000Z"},{"cardId":"ex14-59","name":"Numel","number":"59","rarity":"Common","artist":"Miki Tanaka","imageUrl":"https://tcgcompanion.fra1.digitaloceanspaces.com/images/ex/ex14/59.png","imageUrlHiRes":"https://tcgcompanion.fra1.digitaloceanspaces.com/images/ex/ex14/59_hires.png","setSlug":"crystal-guardians","setName":"Crystal Guardians","setReleaseDate":"2006-08-30T00:00:00.000Z"},{"cardId":"ex12-48","name":"Aron","number":"48","rarity":"Common","artist":"Miki Tanaka","imageUrl":"https://tcgcompanion.fra1.digitaloceanspaces.com/images/ex/ex12/48.png","imageUrlHiRes":"https://tcgcompanion.fra1.digitaloceanspaces.com/images/ex/ex12/48_hires.png","setSlug":"legend-maker","setName":"Legend Maker","setReleaseDate":"2006-02-01T00:00:00.000Z"},{"cardId":"ex12-53","name":"Geodude","number":"53","rarity":"Common","artist":"Miki Tanaka","imageUrl":"https://tcgcompanion.fra1.digitaloceanspaces.com/images/ex/ex12/53.png","imageUrlHiRes":"https://tcgcompanion.fra1.digitaloceanspaces.com/images/ex/ex12/53_hires.png","setSlug":"legend-maker","setName":"Legend Maker","setReleaseDate":"2006-02-01T00:00:00.000Z"},{"cardId":"ex12-65","name":"Spheal","number":"65","rarity":"Common","artist":"Miki Tanaka","imageUrl":"https://tcgcompanion.fra1.digitaloceanspaces.com/images/ex/ex12/65.png","imageUrlHiRes":"https://tcgcompanion.fra1.digitaloceanspaces.com/images/ex/ex12/65_hires.png","setSlug":"legend-maker","setName":"Legend Maker","setReleaseDate":"2006-02-01T00:00:00.000Z"},{"cardId":"ex11-26","name":"Rain Castform","number":"26","rarity":"Rare","artist":"Miki Tanaka","imageUrl":"https://tcgcompanion.fra1.digitaloceanspaces.com/images/ex/ex11/26.png","imageUrlHiRes":"https://tcgcompanion.fra1.digitaloceanspaces.com/images/ex/ex11/26_hires.png","setSlug":"delta-species","setName":"Delta Species","setReleaseDate":"2005-10-31T00:00:00.000Z"},{"cardId":"ex11-29","name":"Snow-cloud Castform","number":"29","rarity":"Rare","artist":"Miki Tanaka","imageUrl":"https://tcgcompanion.fra1.digitaloceanspaces.com/images/ex/ex11/29.png","imageUrlHiRes":"https://tcgcompanion.fra1.digitaloceanspaces.com/images/ex/ex11/29_hires.png","setSlug":"delta-species","setName":"Delta Species","setReleaseDate":"2005-10-31T00:00:00.000Z"},{"cardId":"ex11-31","name":"Sunny Castform","number":"31","rarity":"Rare","artist":"Miki Tanaka","imageUrl":"https://tcgcompanion.fra1.digitaloceanspaces.com/images/ex/ex11/31.png","imageUrlHiRes":"https://tcgcompanion.fra1.digitaloceanspaces.com/images/ex/ex11/31_hires.png","setSlug":"delta-species","setName":"Delta Species","setReleaseDate":"2005-10-31T00:00:00.000Z"},{"cardId":"ex11-34","name":"Castform","number":"34","rarity":"Uncommon","artist":"Miki Tanaka","imageUrl":"https://tcgcompanion.fra1.digitaloceanspaces.com/images/ex/ex11/34.png","imageUrlHiRes":"https://tcgcompanion.fra1.digitaloceanspaces.com/images/ex/ex11/34_hires.png","setSlug":"delta-species","setName":"Delta Species","setReleaseDate":"2005-10-31T00:00:00.000Z"},{"cardId":"ex10-47","name":"Shuckle","number":"47","rarity":"Uncommon","artist":"Miki Tanaka","imageUrl":"https://tcgcompanion.fra1.digitaloceanspaces.com/images/ex/ex10/47.png","imageUrlHiRes":"https://tcgcompanion.fra1.digitaloceanspaces.com/images/ex/ex10/47_hires.png","setSlug":"unseen-forces","setName":"Unseen Forces","setReleaseDate":"2005-08-22T00:00:00.000Z"},{"cardId":"ex10-55","name":"Eevee","number":"55","rarity":"Common","artist":"Miki Tanaka","imageUrl":"https://tcgcompanion.fra1.digitaloceanspaces.com/images/ex/ex10/55.png","imageUrlHiRes":"https://tcgcompanion.fra1.digitaloceanspaces.com/images/ex/ex10/55_hires.png","setSlug":"unseen-forces","setName":"Unseen Forces","setReleaseDate":"2005-08-22T00:00:00.000Z"},{"cardId":"ex10-68","name":"Poliwhirl","number":"68","rarity":"Common","artist":"Miki Tanaka","imageUrl":"https://tcgcompanion.fra1.digitaloceanspaces.com/images/ex/ex10/68.png","imageUrlHiRes":"https://tcgcompanion.fra1.digitaloceanspaces.com/images/ex/ex10/68_hires.png","setSlug":"unseen-forces","setName":"Unseen Forces","setReleaseDate":"2005-08-22T00:00:00.000Z"},{"cardId":"ex8-27","name":"Tropius","number":"27","rarity":"Rare","artist":"Miki Tanaka","imageUrl":"https://tcgcompanion.fra1.digitaloceanspaces.com/images/ex/ex8/27.png","imageUrlHiRes":"https://tcgcompanion.fra1.digitaloceanspaces.com/images/ex/ex8/27_hires.png","setSlug":"deoxys","setName":"Deoxys","setReleaseDate":"2005-02-01T00:00:00.000Z"},{"cardId":"ex8-28","name":"Whiscash","number":"28","rarity":"Rare","artist":"Miki Tanaka","imageUrl":"https://tcgcompanion.fra1.digitaloceanspaces.com/images/ex/ex8/28.png","imageUrlHiRes":"https://tcgcompanion.fra1.digitaloceanspaces.com/images/ex/ex8/28_hires.png","setSlug":"deoxys","setName":"Deoxys","setReleaseDate":"2005-02-01T00:00:00.000Z"},{"cardId":"ex8-54","name":"Barboach","number":"54","rarity":"Common","artist":"Miki Tanaka","imageUrl":"https://tcgcompanion.fra1.digitaloceanspaces.com/images/ex/ex8/54.png","imageUrlHiRes":"https://tcgcompanion.fra1.digitaloceanspaces.com/images/ex/ex8/54_hires.png","setSlug":"deoxys","setName":"Deoxys","setReleaseDate":"2005-02-01T00:00:00.000Z"},{"cardId":"ex7-26","name":"Quagsire","number":"26","rarity":"Rare","artist":"Miki Tanaka","imageUrl":"https://tcgcompanion.fra1.digitaloceanspaces.com/images/ex/ex7/26.png","imageUrlHiRes":"https://tcgcompanion.fra1.digitaloceanspaces.com/images/ex/ex7/26_hires.png","setSlug":"team-rocket-returns","setName":"Team Rocket Returns","setReleaseDate":"2004-11-01T00:00:00.000Z"},{"cardId":"ex7-45","name":"Mantine","number":"45","rarity":"Uncommon","artist":"Miki Tanaka","imageUrl":"https://tcgcompanion.fra1.digitaloceanspaces.com/images/ex/ex7/45.png","imageUrlHiRes":"https://tcgcompanion.fra1.digitaloceanspaces.com/images/ex/ex7/45_hires.png","setSlug":"team-rocket-returns","setName":"Team Rocket Returns","setReleaseDate":"2004-11-01T00:00:00.000Z"},{"cardId":"ex7-70","name":"Psyduck","number":"70","rarity":"Common","artist":"Miki Tanaka","imageUrl":"https://tcgcompanion.fra1.digitaloceanspaces.com/images/ex/ex7/70.png","imageUrlHiRes":"https://tcgcompanion.fra1.digitaloceanspaces.com/images/ex/ex7/70_hires.png","setSlug":"team-rocket-returns","setName":"Team Rocket Returns","setReleaseDate":"2004-11-01T00:00:00.000Z"},{"cardId":"ex7-82","name":"Zubat","number":"82","rarity":"Common","artist":"Miki Tanaka","imageUrl":"https://tcgcompanion.fra1.digitaloceanspaces.com/images/ex/ex7/82.png","imageUrlHiRes":"https://tcgcompanion.fra1.digitaloceanspaces.com/images/ex/ex7/82_hires.png","setSlug":"team-rocket-returns","setName":"Team Rocket Returns","setReleaseDate":"2004-11-01T00:00:00.000Z"},{"cardId":"ex6-19","name":"Chansey","number":"19","rarity":"Rare","artist":"Miki Tanaka","imageUrl":"https://tcgcompanion.fra1.digitaloceanspaces.com/images/ex/ex6/19.png","imageUrlHiRes":"https://tcgcompanion.fra1.digitaloceanspaces.com/images/ex/ex6/19_hires.png","setSlug":"firered-and-leafgreen","setName":"FireRed & LeafGreen","setReleaseDate":"2004-08-30T00:00:00.000Z"},{"cardId":"ex6-28","name":"Primeape","number":"28","rarity":"Rare","artist":"Miki Tanaka","imageUrl":"https://tcgcompanion.fra1.digitaloceanspaces.com/images/ex/ex6/28.png","imageUrlHiRes":"https://tcgcompanion.fra1.digitaloceanspaces.com/images/ex/ex6/28_hires.png","setSlug":"firered-and-leafgreen","setName":"FireRed & LeafGreen","setReleaseDate":"2004-08-30T00:00:00.000Z"},{"cardId":"ex6-38","name":"Mankey","number":"38","rarity":"Uncommon","artist":"Miki Tanaka","imageUrl":"https://tcgcompanion.fra1.digitaloceanspaces.com/images/ex/ex6/38.png","imageUrlHiRes":"https://tcgcompanion.fra1.digitaloceanspaces.com/images/ex/ex6/38_hires.png","setSlug":"firered-and-leafgreen","setName":"FireRed & LeafGreen","setReleaseDate":"2004-08-30T00:00:00.000Z"},{"cardId":"ex5-17","name":"Chimecho","number":"17","rarity":"Rare","artist":"Miki Tanaka","imageUrl":"https://tcgcompanion.fra1.digitaloceanspaces.com/images/ex/ex5/17.png","imageUrlHiRes":"https://tcgcompanion.fra1.digitaloceanspaces.com/images/ex/ex5/17_hires.png","setSlug":"hidden-legends","setName":"Hidden Legends","setReleaseDate":"2004-06-01T00:00:00.000Z"},{"cardId":"ex5-33","name":"Dodrio","number":"33","rarity":"Uncommon","artist":"Miki Tanaka","imageUrl":"https://tcgcompanion.fra1.digitaloceanspaces.com/images/ex/ex5/33.png","imageUrlHiRes":"https://tcgcompanion.fra1.digitaloceanspaces.com/images/ex/ex5/33_hires.png","setSlug":"hidden-legends","setName":"Hidden Legends","setReleaseDate":"2004-06-01T00:00:00.000Z"},{"cardId":"ex5-40","name":"Luvdisc","number":"40","rarity":"Uncommon","artist":"Miki Tanaka","imageUrl":"https://tcgcompanion.fra1.digitaloceanspaces.com/images/ex/ex5/40.png","imageUrlHiRes":"https://tcgcompanion.fra1.digitaloceanspaces.com/images/ex/ex5/40_hires.png","setSlug":"hidden-legends","setName":"Hidden Legends","setReleaseDate":"2004-06-01T00:00:00.000Z"},{"cardId":"ex5-60","name":"Doduo","number":"60","rarity":"Common","artist":"Miki Tanaka","imageUrl":"https://tcgcompanion.fra1.digitaloceanspaces.com/images/ex/ex5/60.png","imageUrlHiRes":"https://tcgcompanion.fra1.digitaloceanspaces.com/images/ex/ex5/60_hires.png","setSlug":"hidden-legends","setName":"Hidden Legends","setReleaseDate":"2004-06-01T00:00:00.000Z"},{"cardId":"ex3-27","name":"Flaaffy","number":"27","rarity":"Uncommon","artist":"Miki Tanaka","imageUrl":"https://tcgcompanion.fra1.digitaloceanspaces.com/images/ex/ex3/27.png","imageUrlHiRes":"https://tcgcompanion.fra1.digitaloceanspaces.com/images/ex/ex3/27_hires.png","setSlug":"dragon","setName":"Dragon","setReleaseDate":"2003-11-24T00:00:00.000Z"},{"cardId":"ex3-64","name":"Mareep","number":"64","rarity":"Common","artist":"Miki Tanaka","imageUrl":"https://tcgcompanion.fra1.digitaloceanspaces.com/images/ex/ex3/64.png","imageUrlHiRes":"https://tcgcompanion.fra1.digitaloceanspaces.com/images/ex/ex3/64_hires.png","setSlug":"dragon","setName":"Dragon","setReleaseDate":"2003-11-24T00:00:00.000Z"},{"cardId":"ex3-73","name":"Spoink","number":"73","rarity":"Common","artist":"Miki Tanaka","imageUrl":"https://tcgcompanion.fra1.digitaloceanspaces.com/images/ex/ex3/73.png","imageUrlHiRes":"https://tcgcompanion.fra1.digitaloceanspaces.com/images/ex/ex3/73_hires.png","setSlug":"dragon","setName":"Dragon","setReleaseDate":"2003-11-24T00:00:00.000Z"},{"cardId":"ecard3-48","name":"Cleffa","number":"48","rarity":"Common","artist":"Miki Tanaka","imageUrl":"https://tcgcompanion.fra1.digitaloceanspaces.com/images/e-card/ecard3/48.png","imageUrlHiRes":"https://tcgcompanion.fra1.digitaloceanspaces.com/images/e-card/ecard3/48_hires.png","setSlug":"skyridge","setName":"Skyridge","setReleaseDate":"2003-05-12T00:00:00.000Z"},{"cardId":"ecard3-74","name":"Machop","number":"74","rarity":"Common","artist":"Miki Tanaka","imageUrl":"https://tcgcompanion.fra1.digitaloceanspaces.com/images/e-card/ecard3/74.png","imageUrlHiRes":"https://tcgcompanion.fra1.digitaloceanspaces.com/images/e-card/ecard3/74_hires.png","setSlug":"skyridge","setName":"Skyridge","setReleaseDate":"2003-05-12T00:00:00.000Z"},{"cardId":"ecard3-80","name":"Natu","number":"80","rarity":"Common","artist":"Miki Tanaka","imageUrl":"https://tcgcompanion.fra1.digitaloceanspaces.com/images/e-card/ecard3/80.png","imageUrlHiRes":"https://tcgcompanion.fra1.digitaloceanspaces.com/images/e-card/ecard3/80_hires.png","setSlug":"skyridge","setName":"Skyridge","setReleaseDate":"2003-05-12T00:00:00.000Z"},{"cardId":"ecard3-87","name":"Poliwag","number":"87","rarity":"Common","artist":"Miki Tanaka","imageUrl":"https://tcgcompanion.fra1.digitaloceanspaces.com/images/e-card/ecard3/87.png","imageUrlHiRes":"https://tcgcompanion.fra1.digitaloceanspaces.com/images/e-card/ecard3/87_hires.png","setSlug":"skyridge","setName":"Skyridge","setReleaseDate":"2003-05-12T00:00:00.000Z"},{"cardId":"ecard3-93","name":"Sandslash","number":"93","rarity":"Common","artist":"Miki Tanaka","imageUrl":"https://tcgcompanion.fra1.digitaloceanspaces.com/images/e-card/ecard3/93.png","imageUrlHiRes":"https://tcgcompanion.fra1.digitaloceanspaces.com/images/e-card/ecard3/93_hires.png","setSlug":"skyridge","setName":"Skyridge","setReleaseDate":"2003-05-12T00:00:00.000Z"},{"cardId":"ecard3-105","name":"Sunflora","number":"105","rarity":"Common","artist":"Miki Tanaka","imageUrl":"https://tcgcompanion.fra1.digitaloceanspaces.com/images/e-card/ecard3/105.png","imageUrlHiRes":"https://tcgcompanion.fra1.digitaloceanspaces.com/images/e-card/ecard3/105_hires.png","setSlug":"skyridge","setName":"Skyridge","setReleaseDate":"2003-05-12T00:00:00.000Z"},{"cardId":"ecard3-116","name":"Yanma","number":"116","rarity":"Common","artist":"Miki Tanaka","imageUrl":"https://tcgcompanion.fra1.digitaloceanspaces.com/images/e-card/ecard3/116.png","imageUrlHiRes":"https://tcgcompanion.fra1.digitaloceanspaces.com/images/e-card/ecard3/116_hires.png","setSlug":"skyridge","setName":"Skyridge","setReleaseDate":"2003-05-12T00:00:00.000Z"},{"cardId":"ecard2-42","name":"Victreebel","number":"42","rarity":"Rare","artist":"Miki Tanaka","imageUrl":"https://tcgcompanion.fra1.digitaloceanspaces.com/images/e-card/ecard2/42.png","imageUrlHiRes":"https://tcgcompanion.fra1.digitaloceanspaces.com/images/e-card/ecard2/42_hires.png","setSlug":"aquapolis","setName":"Aquapolis","setReleaseDate":"2003-01-15T00:00:00.000Z"},{"cardId":"ecard2-65","name":"Weepinbell","number":"65","rarity":"Uncommon","artist":"Miki Tanaka","imageUrl":"https://tcgcompanion.fra1.digitaloceanspaces.com/images/e-card/ecard2/65.png","imageUrlHiRes":"https://tcgcompanion.fra1.digitaloceanspaces.com/images/e-card/ecard2/65_hires.png","setSlug":"aquapolis","setName":"Aquapolis","setReleaseDate":"2003-01-15T00:00:00.000Z"},{"cardId":"ecard2-78","name":"Goldeen","number":"78","rarity":"Common","artist":"Miki Tanaka","imageUrl":"https://tcgcompanion.fra1.digitaloceanspaces.com/images/e-card/ecard2/78.png","imageUrlHiRes":"https://tcgcompanion.fra1.digitaloceanspaces.com/images/e-card/ecard2/78_hires.png","setSlug":"aquapolis","setName":"Aquapolis","setReleaseDate":"2003-01-15T00:00:00.000Z"},{"cardId":"ecard2-99","name":"Paras","number":"99","rarity":"Common","artist":"Miki Tanaka","imageUrl":"https://tcgcompanion.fra1.digitaloceanspaces.com/images/e-card/ecard2/99.png","imageUrlHiRes":"https://tcgcompanion.fra1.digitaloceanspaces.com/images/e-card/ecard2/99_hires.png","setSlug":"aquapolis","setName":"Aquapolis","setReleaseDate":"2003-01-15T00:00:00.000Z"},{"cardId":"ecard2-109","name":"Smeargle","number":"109","rarity":"Common","artist":"Miki Tanaka","imageUrl":"https://tcgcompanion.fra1.digitaloceanspaces.com/images/e-card/ecard2/109.png","imageUrlHiRes":"https://tcgcompanion.fra1.digitaloceanspaces.com/images/e-card/ecard2/109_hires.png","setSlug":"aquapolis","setName":"Aquapolis","setReleaseDate":"2003-01-15T00:00:00.000Z"},{"cardId":"ecard2-111","name":"Spinarak","number":"111","rarity":"Common","artist":"Miki Tanaka","imageUrl":"https://tcgcompanion.fra1.digitaloceanspaces.com/images/e-card/ecard2/111.png","imageUrlHiRes":"https://tcgcompanion.fra1.digitaloceanspaces.com/images/e-card/ecard2/111_hires.png","setSlug":"aquapolis","setName":"Aquapolis","setReleaseDate":"2003-01-15T00:00:00.000Z"},{"cardId":"ecard2-114","name":"Togepi","number":"114","rarity":"Common","artist":"Miki Tanaka","imageUrl":"https://tcgcompanion.fra1.digitaloceanspaces.com/images/e-card/ecard2/114.png","imageUrlHiRes":"https://tcgcompanion.fra1.digitaloceanspaces.com/images/e-card/ecard2/114_hires.png","setSlug":"aquapolis","setName":"Aquapolis","setReleaseDate":"2003-01-15T00:00:00.000Z"},{"cardId":"ecard2-180","name":"Victreebel","number":"H30","rarity":"Rare","artist":"Miki Tanaka","imageUrl":"https://tcgcompanion.fra1.digitaloceanspaces.com/images/e-card/ecard2/H30.png","imageUrlHiRes":"https://tcgcompanion.fra1.digitaloceanspaces.com/images/e-card/ecard2/H30_hires.png","setSlug":"aquapolis","setName":"Aquapolis","setReleaseDate":"2003-01-15T00:00:00.000Z"},{"cardId":"ecard1-31","name":"Vileplume","number":"31","rarity":"Rare Holo","artist":"Miki Tanaka","imageUrl":"https://tcgcompanion.fra1.digitaloceanspaces.com/images/e-card/ecard1/31.png","imageUrlHiRes":"https://tcgcompanion.fra1.digitaloceanspaces.com/images/e-card/ecard1/31_hires.png","setSlug":"expedition-base-set","setName":"Expedition Base Set","setReleaseDate":"2002-09-15T00:00:00.000Z"},{"cardId":"ecard1-69","name":"Vileplume","number":"69","rarity":"Rare","artist":"Miki Tanaka","imageUrl":"https://tcgcompanion.fra1.digitaloceanspaces.com/images/e-card/ecard1/69.png","imageUrlHiRes":"https://tcgcompanion.fra1.digitaloceanspaces.com/images/e-card/ecard1/69_hires.png","setSlug":"expedition-base-set","setName":"Expedition Base Set","setReleaseDate":"2002-09-15T00:00:00.000Z"},{"cardId":"ecard1-82","name":"Ivysaur","number":"82","rarity":"Uncommon","artist":"Miki Tanaka","imageUrl":"https://tcgcompanion.fra1.digitaloceanspaces.com/images/e-card/ecard1/82.png","imageUrlHiRes":"https://tcgcompanion.fra1.digitaloceanspaces.com/images/e-card/ecard1/82_hires.png","setSlug":"expedition-base-set","setName":"Expedition Base Set","setReleaseDate":"2002-09-15T00:00:00.000Z"},{"cardId":"ecard1-86","name":"Magmar","number":"86","rarity":"Uncommon","artist":"Miki Tanaka","imageUrl":"https://tcgcompanion.fra1.digitaloceanspaces.com/images/e-card/ecard1/86.png","imageUrlHiRes":"https://tcgcompanion.fra1.digitaloceanspaces.com/images/e-card/ecard1/86_hires.png","setSlug":"expedition-base-set","setName":"Expedition Base Set","setReleaseDate":"2002-09-15T00:00:00.000Z"},{"cardId":"ecard1-96","name":"Caterpie","number":"96","rarity":"Common","artist":"Miki Tanaka","imageUrl":"https://tcgcompanion.fra1.digitaloceanspaces.com/images/e-card/ecard1/96.png","imageUrlHiRes":"https://tcgcompanion.fra1.digitaloceanspaces.com/images/e-card/ecard1/96_hires.png","setSlug":"expedition-base-set","setName":"Expedition Base Set","setReleaseDate":"2002-09-15T00:00:00.000Z"},{"cardId":"ecard1-99","name":"Chikorita","number":"99","rarity":"Common","artist":"Miki Tanaka","imageUrl":"https://tcgcompanion.fra1.digitaloceanspaces.com/images/e-card/ecard1/99.png","imageUrlHiRes":"https://tcgcompanion.fra1.digitaloceanspaces.com/images/e-card/ecard1/99_hires.png","setSlug":"expedition-base-set","setName":"Expedition Base Set","setReleaseDate":"2002-09-15T00:00:00.000Z"},{"cardId":"ecard1-102","name":"Corsola","number":"102","rarity":"Common","artist":"Miki Tanaka","imageUrl":"https://tcgcompanion.fra1.digitaloceanspaces.com/images/e-card/ecard1/102.png","imageUrlHiRes":"https://tcgcompanion.fra1.digitaloceanspaces.com/images/e-card/ecard1/102_hires.png","setSlug":"expedition-base-set","setName":"Expedition Base Set","setReleaseDate":"2002-09-15T00:00:00.000Z"},{"cardId":"base6-93","name":"Slowpoke","number":"93","rarity":"Common","artist":"Miki Tanaka","imageUrl":"https://tcgcompanion.fra1.digitaloceanspaces.com/images/base/base6/93.png","imageUrlHiRes":"https://tcgcompanion.fra1.digitaloceanspaces.com/images/base/base6/93_hires.png","setSlug":"legendary-collection","setName":"Legendary Collection","setReleaseDate":"2002-05-24T00:00:00.000Z"},{"cardId":"neo4-23","name":"Light Lanturn","number":"23","rarity":"Rare","artist":"Miki Tanaka","imageUrl":"https://tcgcompanion.fra1.digitaloceanspaces.com/images/neo/neo4/23.png","imageUrlHiRes":"https://tcgcompanion.fra1.digitaloceanspaces.com/images/neo/neo4/23_hires.png","setSlug":"neo-destiny","setName":"Neo Destiny","setReleaseDate":"2002-02-28T00:00:00.000Z"},{"cardId":"neo4-25","name":"Light Machamp","number":"25","rarity":"Rare","artist":"Miki Tanaka","imageUrl":"https://tcgcompanion.fra1.digitaloceanspaces.com/images/neo/neo4/25.png","imageUrlHiRes":"https://tcgcompanion.fra1.digitaloceanspaces.com/images/neo/neo4/25_hires.png","setSlug":"neo-destiny","setName":"Neo Destiny","setReleaseDate":"2002-02-28T00:00:00.000Z"},{"cardId":"neo4-40","name":"Dark Wigglytuff","number":"40","rarity":"Uncommon","artist":"Miki Tanaka","imageUrl":"https://tcgcompanion.fra1.digitaloceanspaces.com/images/neo/neo4/40.png","imageUrlHiRes":"https://tcgcompanion.fra1.digitaloceanspaces.com/images/neo/neo4/40_hires.png","setSlug":"neo-destiny","setName":"Neo Destiny","setReleaseDate":"2002-02-28T00:00:00.000Z"},{"cardId":"neo4-49","name":"Light Machoke","number":"49","rarity":"Uncommon","artist":"Miki Tanaka","imageUrl":"https://tcgcompanion.fra1.digitaloceanspaces.com/images/neo/neo4/49.png","imageUrlHiRes":"https://tcgcompanion.fra1.digitaloceanspaces.com/images/neo/neo4/49_hires.png","setSlug":"neo-destiny","setName":"Neo Destiny","setReleaseDate":"2002-02-28T00:00:00.000Z"},{"cardId":"neo4-76","name":"Phanpy","number":"76","rarity":"Common","artist":"Miki Tanaka","imageUrl":"https://tcgcompanion.fra1.digitaloceanspaces.com/images/neo/neo4/76.png","imageUrlHiRes":"https://tcgcompanion.fra1.digitaloceanspaces.com/images/neo/neo4/76_hires.png","setSlug":"neo-destiny","setName":"Neo Destiny","setReleaseDate":"2002-02-28T00:00:00.000Z"},{"cardId":"neo4-85","name":"Totodile","number":"85","rarity":"Common","artist":"Miki Tanaka","imageUrl":"https://tcgcompanion.fra1.digitaloceanspaces.com/images/neo/neo4/85.png","imageUrlHiRes":"https://tcgcompanion.fra1.digitaloceanspaces.com/images/neo/neo4/85_hires.png","setSlug":"neo-destiny","setName":"Neo Destiny","setReleaseDate":"2002-02-28T00:00:00.000Z"},{"cardId":"neo3-37","name":"Seaking","number":"37","rarity":"Uncommon","artist":"Miki Tanaka","imageUrl":"https://tcgcompanion.fra1.digitaloceanspaces.com/images/neo/neo3/37.png","imageUrlHiRes":"https://tcgcompanion.fra1.digitaloceanspaces.com/images/neo/neo3/37_hires.png","setSlug":"neo-revelation","setName":"Neo Revelation","setReleaseDate":"2001-09-21T00:00:00.000Z"},{"cardId":"neo3-43","name":"Farfetch'd","number":"43","rarity":"Common","artist":"Miki Tanaka","imageUrl":"https://tcgcompanion.fra1.digitaloceanspaces.com/images/neo/neo3/43.png","imageUrlHiRes":"https://tcgcompanion.fra1.digitaloceanspaces.com/images/neo/neo3/43_hires.png","setSlug":"neo-revelation","setName":"Neo Revelation","setReleaseDate":"2001-09-21T00:00:00.000Z"},{"cardId":"neo3-50","name":"Remoraid","number":"50","rarity":"Common","artist":"Miki Tanaka","imageUrl":"https://tcgcompanion.fra1.digitaloceanspaces.com/images/neo/neo3/50.png","imageUrlHiRes":"https://tcgcompanion.fra1.digitaloceanspaces.com/images/neo/neo3/50_hires.png","setSlug":"neo-revelation","setName":"Neo Revelation","setReleaseDate":"2001-09-21T00:00:00.000Z"},{"cardId":"neo3-57","name":"Swinub","number":"57","rarity":"Common","artist":"Miki Tanaka","imageUrl":"https://tcgcompanion.fra1.digitaloceanspaces.com/images/neo/neo3/57.png","imageUrlHiRes":"https://tcgcompanion.fra1.digitaloceanspaces.com/images/neo/neo3/57_hires.png","setSlug":"neo-revelation","setName":"Neo Revelation","setReleaseDate":"2001-09-21T00:00:00.000Z"},{"cardId":"neo2-40","name":"Igglybuff","number":"40","rarity":"Uncommon","artist":"Miki Tanaka","imageUrl":"https://tcgcompanion.fra1.digitaloceanspaces.com/images/neo/neo2/40.png","imageUrlHiRes":"https://tcgcompanion.fra1.digitaloceanspaces.com/images/neo/neo2/40_hires.png","setSlug":"neo-discovery","setName":"Neo Discovery","setReleaseDate":"2001-06-01T00:00:00.000Z"},{"cardId":"neo2-65","name":"Teddiursa","number":"65","rarity":"Common","artist":"Miki Tanaka","imageUrl":"https://tcgcompanion.fra1.digitaloceanspaces.com/images/neo/neo2/65.png","imageUrlHiRes":"https://tcgcompanion.fra1.digitaloceanspaces.com/images/neo/neo2/65_hires.png","setSlug":"neo-discovery","setName":"Neo Discovery","setReleaseDate":"2001-06-01T00:00:00.000Z"},{"cardId":"neo2-66","name":"Tyrogue","number":"66","rarity":"Common","artist":"Miki Tanaka","imageUrl":"https://tcgcompanion.fra1.digitaloceanspaces.com/images/neo/neo2/66.png","imageUrlHiRes":"https://tcgcompanion.fra1.digitaloceanspaces.com/images/neo/neo2/66_hires.png","setSlug":"neo-discovery","setName":"Neo Discovery","setReleaseDate":"2001-06-01T00:00:00.000Z"},{"cardId":"neo2-70","name":"Weedle","number":"70","rarity":"Common","artist":"Miki Tanaka","imageUrl":"https://tcgcompanion.fra1.digitaloceanspaces.com/images/neo/neo2/70.png","imageUrlHiRes":"https://tcgcompanion.fra1.digitaloceanspaces.com/images/neo/neo2/70_hires.png","setSlug":"neo-discovery","setName":"Neo Discovery","setReleaseDate":"2001-06-01T00:00:00.000Z"},{"cardId":"neo1-22","name":"Elekid","number":"22","rarity":"Rare","artist":"Miki Tanaka","imageUrl":"https://tcgcompanion.fra1.digitaloceanspaces.com/images/neo/neo1/22.png","imageUrlHiRes":"https://tcgcompanion.fra1.digitaloceanspaces.com/images/neo/neo1/22_hires.png","setSlug":"neo-genesis","setName":"Neo Genesis","setReleaseDate":"2000-12-16T00:00:00.000Z"},{"cardId":"neo1-62","name":"Horsea","number":"62","rarity":"Common","artist":"Miki Tanaka","imageUrl":"https://tcgcompanion.fra1.digitaloceanspaces.com/images/neo/neo1/62.png","imageUrlHiRes":"https://tcgcompanion.fra1.digitaloceanspaces.com/images/neo/neo1/62_hires.png","setSlug":"neo-genesis","setName":"Neo Genesis","setReleaseDate":"2000-12-16T00:00:00.000Z"},{"cardId":"neo1-82","name":"Wooper","number":"82","rarity":"Common","artist":"Miki Tanaka","imageUrl":"https://tcgcompanion.fra1.digitaloceanspaces.com/images/neo/neo1/82.png","imageUrlHiRes":"https://tcgcompanion.fra1.digitaloceanspaces.com/images/neo/neo1/82_hires.png","setSlug":"neo-genesis","setName":"Neo Genesis","setReleaseDate":"2000-12-16T00:00:00.000Z"},{"cardId":"base5-11","name":"Dark Magneton","number":"11","rarity":"Rare Holo","artist":"Miki Tanaka","imageUrl":"https://tcgcompanion.fra1.digitaloceanspaces.com/images/base/base5/11.png","imageUrlHiRes":"https://tcgcompanion.fra1.digitaloceanspaces.com/images/base/base5/11_hires.png","setSlug":"team-rocket","setName":"Team Rocket","setReleaseDate":"2000-04-24T00:00:00.000Z"},{"cardId":"base5-28","name":"Dark Magneton","number":"28","rarity":"Rare","artist":"Miki Tanaka","imageUrl":"https://tcgcompanion.fra1.digitaloceanspaces.com/images/base/base5/28.png","imageUrlHiRes":"https://tcgcompanion.fra1.digitaloceanspaces.com/images/base/base5/28_hires.png","setSlug":"team-rocket","setName":"Team Rocket","setReleaseDate":"2000-04-24T00:00:00.000Z"},{"cardId":"base5-60","name":"Magnemite","number":"60","rarity":"Common","artist":"Miki Tanaka","imageUrl":"https://tcgcompanion.fra1.digitaloceanspaces.com/images/base/base5/60.png","imageUrlHiRes":"https://tcgcompanion.fra1.digitaloceanspaces.com/images/base/base5/60_hires.png","setSlug":"team-rocket","setName":"Team Rocket","setReleaseDate":"2000-04-24T00:00:00.000Z"},{"cardId":"base3-55","name":"Slowpoke","number":"55","rarity":"Common","artist":"Miki Tanaka","imageUrl":"https://tcgcompanion.fra1.digitaloceanspaces.com/images/base/base3/55.png","imageUrlHiRes":"https://tcgcompanion.fra1.digitaloceanspaces.com/images/base/base3/55_hires.png","setSlug":"fossil","setName":"Fossil","setReleaseDate":"1999-10-09T00:00:00.000Z"},{"cardId":"basep-46","name":"Electabuzz","number":"46","rarity":"","artist":"Miki Tanaka","imageUrl":"https://tcgcompanion.fra1.digitaloceanspaces.com/images/base/basep/46.png","imageUrlHiRes":"https://tcgcompanion.fra1.digitaloceanspaces.com/images/base/basep/46_hires.png","setSlug":"wizards-black-star-promos","setName":"Wizards Black Star Promos","setReleaseDate":"1999-06-30T00:00:00.000Z"}]