[{"cardId":"asc-20","name":"Charmander","number":"20","rarity":"Common","artist":"Orca","imageUrl":"https://tcgcompanion.fra1.digitaloceanspaces.com/images/megaevolution/asc/20.webp","imageUrlHiRes":"https://tcgcompanion.fra1.digitaloceanspaces.com/images/megaevolution/asc/20_hires.webp","setSlug":"ascended-heroes","setName":"Ascended Heroes","setReleaseDate":"2026-01-30T00:00:00.000Z"},{"cardId":"pfl-31","name":"Boltund","number":"31","rarity":"Common","artist":"Orca","imageUrl":"https://tcgcompanion.fra1.digitaloceanspaces.com/images/megaevolution/pfl/31.webp","imageUrlHiRes":"https://tcgcompanion.fra1.digitaloceanspaces.com/images/megaevolution/pfl/31_hires.webp","setSlug":"phantasmal-flames","setName":"Phantasmal Flames","setReleaseDate":"2025-11-14T00:00:00.000Z"},{"cardId":"pfl-104","name":"Togedemaru","number":"104","rarity":"Rare Secret","artist":"Orca","imageUrl":"https://tcgcompanion.fra1.digitaloceanspaces.com/images/megaevolution/pfl/104.webp","imageUrlHiRes":"https://tcgcompanion.fra1.digitaloceanspaces.com/images/megaevolution/pfl/104_hires.webp","setSlug":"phantasmal-flames","setName":"Phantasmal Flames","setReleaseDate":"2025-11-14T00:00:00.000Z"},{"cardId":"meg-54","name":"Abra","number":"54","rarity":"Common","artist":"Orca","imageUrl":"https://tcgcompanion.fra1.digitaloceanspaces.com/images/megaevolution/meg/54.webp","imageUrlHiRes":"https://tcgcompanion.fra1.digitaloceanspaces.com/images/megaevolution/meg/54_hires.webp","setSlug":"mega-evolution","setName":"Mega Evolution","setReleaseDate":"2025-09-25T23:00:00.000Z"},{"cardId":"WHT-96","name":"Tepig","number":"96","rarity":"Rare Secret","artist":"Orca","imageUrl":"https://tcgcompanion.fra1.digitaloceanspaces.com/images/scarlet%26violet/WHT/96.webp","imageUrlHiRes":"https://tcgcompanion.fra1.digitaloceanspaces.com/images/scarlet%26violet/WHT/96_hires.webp","setSlug":"white-flare","setName":"White Flare","setReleaseDate":"2025-07-17T22:00:00.000Z"},{"cardId":"dri-194","name":"Misty's Lapras","number":"194","rarity":"Rare Secret","artist":"Orca","imageUrl":"https://tcgcompanion.fra1.digitaloceanspaces.com/images/scarlet%26violet/dri/194.webp","imageUrlHiRes":"https://tcgcompanion.fra1.digitaloceanspaces.com/images/scarlet%26violet/dri/194_hires.webp","setSlug":"destined-rivals","setName":"Destined Rivals","setReleaseDate":"2025-05-29T23:00:00.000Z"},{"cardId":"ssp-74","name":"Azumarill","number":"74","rarity":"Uncommon","artist":"Orca","imageUrl":"https://tcgcompanion.fra1.digitaloceanspaces.com/images/scarlet%26violet/ssp/74.png","imageUrlHiRes":"https://tcgcompanion.fra1.digitaloceanspaces.com/images/scarlet%26violet/ssp/74_hires.png","setSlug":"surging-sparks","setName":"Surging Sparks","setReleaseDate":"2024-11-08T00:00:00.000Z"},{"cardId":"scr-143","name":"Bulbasaur","number":"143","rarity":"Rare Secret","artist":"Orca","imageUrl":"https://tcgcompanion.fra1.digitaloceanspaces.com/images/scarlet%26violet/scr/143.png","imageUrlHiRes":"https://tcgcompanion.fra1.digitaloceanspaces.com/images/scarlet%26violet/scr/143_hires.png","setSlug":"stellar-crown","setName":"Stellar Crown","setReleaseDate":"2024-09-13T00:00:00.000Z"},{"cardId":"sfa-44","name":"Axew","number":"44","rarity":"Common","artist":"Orca","imageUrl":"https://tcgcompanion.fra1.digitaloceanspaces.com/images/scarlet%26violet/sfa/44.png","imageUrlHiRes":"https://tcgcompanion.fra1.digitaloceanspaces.com/images/scarlet%26violet/sfa/44_hires.png","setSlug":"shrouded-fable","setName":"Shrouded Fable","setReleaseDate":"2024-08-02T00:00:00.000Z"},{"cardId":"twm-9","name":"Volbeat","number":"9","rarity":"Common","artist":"Orca","imageUrl":"https://tcgcompanion.fra1.digitaloceanspaces.com/images/scarlet%26violet/twm/9.png","imageUrlHiRes":"https://tcgcompanion.fra1.digitaloceanspaces.com/images/scarlet%26violet/twm/9_hires.png","setSlug":"twilight-masquerade","setName":"Twilight Masquerade","setReleaseDate":"2024-05-24T00:00:00.000Z"},{"cardId":"twm-10","name":"Illumise","number":"10","rarity":"Common","artist":"Orca","imageUrl":"https://tcgcompanion.fra1.digitaloceanspaces.com/images/scarlet%26violet/twm/10.png","imageUrlHiRes":"https://tcgcompanion.fra1.digitaloceanspaces.com/images/scarlet%26violet/twm/10_hires.png","setSlug":"twilight-masquerade","setName":"Twilight Masquerade","setReleaseDate":"2024-05-24T00:00:00.000Z"},{"cardId":"tef-45","name":"Snom","number":"45","rarity":"Common","artist":"Orca","imageUrl":"https://tcgcompanion.fra1.digitaloceanspaces.com/images/scarlet%26violet/tef/45.png","imageUrlHiRes":"https://tcgcompanion.fra1.digitaloceanspaces.com/images/scarlet%26violet/tef/45_hires.png","setSlug":"temporal-forces","setName":"Temporal Forces","setReleaseDate":"2024-03-22T00:00:00.000Z"},{"cardId":"tef-180","name":"Lickitung","number":"180","rarity":"Rare Secret","artist":"Orca","imageUrl":"https://tcgcompanion.fra1.digitaloceanspaces.com/images/scarlet%26violet/tef/180.png","imageUrlHiRes":"https://tcgcompanion.fra1.digitaloceanspaces.com/images/scarlet%26violet/tef/180_hires.png","setSlug":"temporal-forces","setName":"Temporal Forces","setReleaseDate":"2024-03-22T00:00:00.000Z"},{"cardId":"svp-107","name":"Mareep","number":"107","rarity":"Promo","artist":"Orca","imageUrl":"https://tcgcompanion.fra1.digitaloceanspaces.com/images/scarlet%26violet/svp/107.png","imageUrlHiRes":"https://tcgcompanion.fra1.digitaloceanspaces.com/images/scarlet%26violet/svp/107_hires.png","setSlug":"sv-black-star-promos","setName":"SV Black Star Promos","setReleaseDate":"2023-03-30T00:00:00.000Z"}]