[{"cardId":"xy12-1","name":"Venusaur-EX","number":"1","rarity":"Rare Holo EX","artist":"Eske Yoshinob","imageUrl":"https://tcgcompanion.fra1.digitaloceanspaces.com/images/xy/xy12/1.png","imageUrlHiRes":"https://tcgcompanion.fra1.digitaloceanspaces.com/images/xy/xy12/1_hires.png"},{"cardId":"xy12-2","name":"M Venusaur-EX","number":"2","rarity":"Rare Holo EX","artist":"5ban Graphics","imageUrl":"https://tcgcompanion.fra1.digitaloceanspaces.com/images/xy/xy12/2.png","imageUrlHiRes":"https://tcgcompanion.fra1.digitaloceanspaces.com/images/xy/xy12/2_hires.png"},{"cardId":"xy12-3","name":"Caterpie","number":"3","rarity":"Common","artist":"Ken Sugimori","imageUrl":"https://tcgcompanion.fra1.digitaloceanspaces.com/images/xy/xy12/3.png","imageUrlHiRes":"https://tcgcompanion.fra1.digitaloceanspaces.com/images/xy/xy12/3_hires.png"},{"cardId":"xy12-4","name":"Metapod","number":"4","rarity":"Uncommon","artist":"Ken Sugimori","imageUrl":"https://tcgcompanion.fra1.digitaloceanspaces.com/images/xy/xy12/4.png","imageUrlHiRes":"https://tcgcompanion.fra1.digitaloceanspaces.com/images/xy/xy12/4_hires.png"},{"cardId":"xy12-5","name":"Weedle","number":"5","rarity":"Common","artist":"Mitsuhiro Arita","imageUrl":"https://tcgcompanion.fra1.digitaloceanspaces.com/images/xy/xy12/5.png","imageUrlHiRes":"https://tcgcompanion.fra1.digitaloceanspaces.com/images/xy/xy12/5_hires.png"},{"cardId":"xy12-6","name":"Kakuna","number":"6","rarity":"Uncommon","artist":"Keiji Kinebuchi","imageUrl":"https://tcgcompanion.fra1.digitaloceanspaces.com/images/xy/xy12/6.png","imageUrlHiRes":"https://tcgcompanion.fra1.digitaloceanspaces.com/images/xy/xy12/6_hires.png"},{"cardId":"xy12-7","name":"Beedrill","number":"7","rarity":"Rare","artist":"Ken Sugimori","imageUrl":"https://tcgcompanion.fra1.digitaloceanspaces.com/images/xy/xy12/7.png","imageUrlHiRes":"https://tcgcompanion.fra1.digitaloceanspaces.com/images/xy/xy12/7_hires.png"},{"cardId":"xy12-8","name":"Tangela","number":"8","rarity":"Common","artist":"Mitsuhiro Arita","imageUrl":"https://tcgcompanion.fra1.digitaloceanspaces.com/images/xy/xy12/8.png","imageUrlHiRes":"https://tcgcompanion.fra1.digitaloceanspaces.com/images/xy/xy12/8_hires.png"},{"cardId":"xy12-9","name":"Charmander","number":"9","rarity":"Common","artist":"Mitsuhiro Arita","imageUrl":"https://tcgcompanion.fra1.digitaloceanspaces.com/images/xy/xy12/9.png","imageUrlHiRes":"https://tcgcompanion.fra1.digitaloceanspaces.com/images/xy/xy12/9_hires.png"},{"cardId":"xy12-10","name":"Charmeleon","number":"10","rarity":"Uncommon","artist":"Mitsuhiro Arita","imageUrl":"https://tcgcompanion.fra1.digitaloceanspaces.com/images/xy/xy12/10.png","imageUrlHiRes":"https://tcgcompanion.fra1.digitaloceanspaces.com/images/xy/xy12/10_hires.png"},{"cardId":"xy12-11","name":"Charizard","number":"11","rarity":"Rare Holo","artist":"Mitsuhiro Arita","imageUrl":"https://tcgcompanion.fra1.digitaloceanspaces.com/images/xy/xy12/11.png","imageUrlHiRes":"https://tcgcompanion.fra1.digitaloceanspaces.com/images/xy/xy12/11_hires.png"},{"cardId":"xy12-12","name":"Charizard-EX","number":"12","rarity":"Rare Holo EX","artist":"PLANETA","imageUrl":"https://tcgcompanion.fra1.digitaloceanspaces.com/images/xy/xy12/12.png","imageUrlHiRes":"https://tcgcompanion.fra1.digitaloceanspaces.com/images/xy/xy12/12_hires.png"},{"cardId":"xy12-13","name":"M Charizard-EX","number":"13","rarity":"Rare Holo EX","artist":"5ban Graphics","imageUrl":"https://tcgcompanion.fra1.digitaloceanspaces.com/images/xy/xy12/13.png","imageUrlHiRes":"https://tcgcompanion.fra1.digitaloceanspaces.com/images/xy/xy12/13_hires.png"},{"cardId":"xy12-14","name":"Vulpix","number":"14","rarity":"Common","artist":"Ken Sugimori","imageUrl":"https://tcgcompanion.fra1.digitaloceanspaces.com/images/xy/xy12/14.png","imageUrlHiRes":"https://tcgcompanion.fra1.digitaloceanspaces.com/images/xy/xy12/14_hires.png"},{"cardId":"xy12-15","name":"Ninetales","number":"15","rarity":"Rare Holo","artist":"Ken Sugimori","imageUrl":"https://tcgcompanion.fra1.digitaloceanspaces.com/images/xy/xy12/15.png","imageUrlHiRes":"https://tcgcompanion.fra1.digitaloceanspaces.com/images/xy/xy12/15_hires.png"},{"cardId":"xy12-16","name":"Ninetales BREAK","number":"16","rarity":"Rare BREAK","artist":"5ban Graphics","imageUrl":"https://tcgcompanion.fra1.digitaloceanspaces.com/images/xy/xy12/16.png","imageUrlHiRes":"https://tcgcompanion.fra1.digitaloceanspaces.com/images/xy/xy12/16_hires.png"},{"cardId":"xy12-17","name":"Growlithe","number":"17","rarity":"Common","artist":"Ken Sugimori","imageUrl":"https://tcgcompanion.fra1.digitaloceanspaces.com/images/xy/xy12/17.png","imageUrlHiRes":"https://tcgcompanion.fra1.digitaloceanspaces.com/images/xy/xy12/17_hires.png"},{"cardId":"xy12-18","name":"Arcanine","number":"18","rarity":"Rare","artist":"Ken Sugimori","imageUrl":"https://tcgcompanion.fra1.digitaloceanspaces.com/images/xy/xy12/18.png","imageUrlHiRes":"https://tcgcompanion.fra1.digitaloceanspaces.com/images/xy/xy12/18_hires.png"},{"cardId":"xy12-19","name":"Ponyta","number":"19","rarity":"Common","artist":"Ken Sugimori","imageUrl":"https://tcgcompanion.fra1.digitaloceanspaces.com/images/xy/xy12/19.png","imageUrlHiRes":"https://tcgcompanion.fra1.digitaloceanspaces.com/images/xy/xy12/19_hires.png"},{"cardId":"xy12-20","name":"Magmar","number":"20","rarity":"Uncommon","artist":"Ken Sugimori","imageUrl":"https://tcgcompanion.fra1.digitaloceanspaces.com/images/xy/xy12/20.png","imageUrlHiRes":"https://tcgcompanion.fra1.digitaloceanspaces.com/images/xy/xy12/20_hires.png"},{"cardId":"xy12-21","name":"Blastoise-EX","number":"21","rarity":"Rare Holo EX","artist":"Eske Yoshinob","imageUrl":"https://tcgcompanion.fra1.digitaloceanspaces.com/images/xy/xy12/21.png","imageUrlHiRes":"https://tcgcompanion.fra1.digitaloceanspaces.com/images/xy/xy12/21_hires.png"},{"cardId":"xy12-22","name":"M Blastoise-EX","number":"22","rarity":"Rare Holo EX","artist":"5ban Graphics","imageUrl":"https://tcgcompanion.fra1.digitaloceanspaces.com/images/xy/xy12/22.png","imageUrlHiRes":"https://tcgcompanion.fra1.digitaloceanspaces.com/images/xy/xy12/22_hires.png"},{"cardId":"xy12-23","name":"Poliwag","number":"23","rarity":"Common","artist":"Ken Sugimori","imageUrl":"https://tcgcompanion.fra1.digitaloceanspaces.com/images/xy/xy12/23.png","imageUrlHiRes":"https://tcgcompanion.fra1.digitaloceanspaces.com/images/xy/xy12/23_hires.png"},{"cardId":"xy12-24","name":"Poliwhirl","number":"24","rarity":"Uncommon","artist":"Ken Sugimori","imageUrl":"https://tcgcompanion.fra1.digitaloceanspaces.com/images/xy/xy12/24.png","imageUrlHiRes":"https://tcgcompanion.fra1.digitaloceanspaces.com/images/xy/xy12/24_hires.png"},{"cardId":"xy12-25","name":"Poliwrath","number":"25","rarity":"Rare Holo","artist":"Ken Sugimori","imageUrl":"https://tcgcompanion.fra1.digitaloceanspaces.com/images/xy/xy12/25.png","imageUrlHiRes":"https://tcgcompanion.fra1.digitaloceanspaces.com/images/xy/xy12/25_hires.png"},{"cardId":"xy12-26","name":"Slowbro-EX","number":"26","rarity":"Rare Holo EX","artist":"Ayaka Yoshida","imageUrl":"https://tcgcompanion.fra1.digitaloceanspaces.com/images/xy/xy12/26.png","imageUrlHiRes":"https://tcgcompanion.fra1.digitaloceanspaces.com/images/xy/xy12/26_hires.png"},{"cardId":"xy12-27","name":"M Slowbro-EX","number":"27","rarity":"Rare Holo EX","artist":"5ban Graphics","imageUrl":"https://tcgcompanion.fra1.digitaloceanspaces.com/images/xy/xy12/27.png","imageUrlHiRes":"https://tcgcompanion.fra1.digitaloceanspaces.com/images/xy/xy12/27_hires.png"},{"cardId":"xy12-28","name":"Seel","number":"28","rarity":"Common","artist":"Ken Sugimori","imageUrl":"https://tcgcompanion.fra1.digitaloceanspaces.com/images/xy/xy12/28.png","imageUrlHiRes":"https://tcgcompanion.fra1.digitaloceanspaces.com/images/xy/xy12/28_hires.png"},{"cardId":"xy12-29","name":"Dewgong","number":"29","rarity":"Rare","artist":"Mitsuhiro Arita","imageUrl":"https://tcgcompanion.fra1.digitaloceanspaces.com/images/xy/xy12/29.png","imageUrlHiRes":"https://tcgcompanion.fra1.digitaloceanspaces.com/images/xy/xy12/29_hires.png"},{"cardId":"xy12-30","name":"Staryu","number":"30","rarity":"Common","artist":"Keiji Kinebuchi","imageUrl":"https://tcgcompanion.fra1.digitaloceanspaces.com/images/xy/xy12/30.png","imageUrlHiRes":"https://tcgcompanion.fra1.digitaloceanspaces.com/images/xy/xy12/30_hires.png"},{"cardId":"xy12-31","name":"Starmie","number":"31","rarity":"Rare","artist":"Keiji Kinebuchi","imageUrl":"https://tcgcompanion.fra1.digitaloceanspaces.com/images/xy/xy12/31.png","imageUrlHiRes":"https://tcgcompanion.fra1.digitaloceanspaces.com/images/xy/xy12/31_hires.png"},{"cardId":"xy12-32","name":"Starmie BREAK","number":"32","rarity":"Rare BREAK","artist":"5ban Graphics","imageUrl":"https://tcgcompanion.fra1.digitaloceanspaces.com/images/xy/xy12/32.png","imageUrlHiRes":"https://tcgcompanion.fra1.digitaloceanspaces.com/images/xy/xy12/32_hires.png"},{"cardId":"xy12-33","name":"Magikarp","number":"33","rarity":"Common","artist":"Mitsuhiro Arita","imageUrl":"https://tcgcompanion.fra1.digitaloceanspaces.com/images/xy/xy12/33.png","imageUrlHiRes":"https://tcgcompanion.fra1.digitaloceanspaces.com/images/xy/xy12/33_hires.png"},{"cardId":"xy12-34","name":"Gyarados","number":"34","rarity":"Rare Holo","artist":"Mitsuhiro Arita","imageUrl":"https://tcgcompanion.fra1.digitaloceanspaces.com/images/xy/xy12/34.png","imageUrlHiRes":"https://tcgcompanion.fra1.digitaloceanspaces.com/images/xy/xy12/34_hires.png"},{"cardId":"xy12-35","name":"Pikachu","number":"35","rarity":"Common","artist":"Mitsuhiro Arita","imageUrl":"https://tcgcompanion.fra1.digitaloceanspaces.com/images/xy/xy12/35.png","imageUrlHiRes":"https://tcgcompanion.fra1.digitaloceanspaces.com/images/xy/xy12/35_hires.png"},{"cardId":"xy12-36","name":"Raichu","number":"36","rarity":"Rare Holo","artist":"Ken Sugimori","imageUrl":"https://tcgcompanion.fra1.digitaloceanspaces.com/images/xy/xy12/36.png","imageUrlHiRes":"https://tcgcompanion.fra1.digitaloceanspaces.com/images/xy/xy12/36_hires.png"},{"cardId":"xy12-37","name":"Magnemite","number":"37","rarity":"Common","artist":"Keiji Kinebuchi","imageUrl":"https://tcgcompanion.fra1.digitaloceanspaces.com/images/xy/xy12/37.png","imageUrlHiRes":"https://tcgcompanion.fra1.digitaloceanspaces.com/images/xy/xy12/37_hires.png"},{"cardId":"xy12-38","name":"Magneton","number":"38","rarity":"Rare Holo","artist":"Keiji Kinebuchi","imageUrl":"https://tcgcompanion.fra1.digitaloceanspaces.com/images/xy/xy12/38.png","imageUrlHiRes":"https://tcgcompanion.fra1.digitaloceanspaces.com/images/xy/xy12/38_hires.png"},{"cardId":"xy12-39","name":"Voltorb","number":"39","rarity":"Common","artist":"Keiji Kinebuchi","imageUrl":"https://tcgcompanion.fra1.digitaloceanspaces.com/images/xy/xy12/39.png","imageUrlHiRes":"https://tcgcompanion.fra1.digitaloceanspaces.com/images/xy/xy12/39_hires.png"},{"cardId":"xy12-40","name":"Electrode","number":"40","rarity":"Rare","artist":"Keiji Kinebuchi","imageUrl":"https://tcgcompanion.fra1.digitaloceanspaces.com/images/xy/xy12/40.png","imageUrlHiRes":"https://tcgcompanion.fra1.digitaloceanspaces.com/images/xy/xy12/40_hires.png"},{"cardId":"xy12-41","name":"Electabuzz","number":"41","rarity":"Common","artist":"Ken Sugimori","imageUrl":"https://tcgcompanion.fra1.digitaloceanspaces.com/images/xy/xy12/41.png","imageUrlHiRes":"https://tcgcompanion.fra1.digitaloceanspaces.com/images/xy/xy12/41_hires.png"},{"cardId":"xy12-42","name":"Zapdos","number":"42","rarity":"Rare Holo","artist":"Ken Sugimori","imageUrl":"https://tcgcompanion.fra1.digitaloceanspaces.com/images/xy/xy12/42.png","imageUrlHiRes":"https://tcgcompanion.fra1.digitaloceanspaces.com/images/xy/xy12/42_hires.png"},{"cardId":"xy12-43","name":"Nidoran♂","number":"43","rarity":"Common","artist":"Ken Sugimori","imageUrl":"https://tcgcompanion.fra1.digitaloceanspaces.com/images/xy/xy12/43.png","imageUrlHiRes":"https://tcgcompanion.fra1.digitaloceanspaces.com/images/xy/xy12/43_hires.png"},{"cardId":"xy12-44","name":"Nidorino","number":"44","rarity":"Uncommon","artist":"Mitsuhiro Arita","imageUrl":"https://tcgcompanion.fra1.digitaloceanspaces.com/images/xy/xy12/44.png","imageUrlHiRes":"https://tcgcompanion.fra1.digitaloceanspaces.com/images/xy/xy12/44_hires.png"},{"cardId":"xy12-45","name":"Nidoking","number":"45","rarity":"Rare Holo","artist":"Ken Sugimori","imageUrl":"https://tcgcompanion.fra1.digitaloceanspaces.com/images/xy/xy12/45.png","imageUrlHiRes":"https://tcgcompanion.fra1.digitaloceanspaces.com/images/xy/xy12/45_hires.png"},{"cardId":"xy12-46","name":"Nidoking BREAK","number":"46","rarity":"Rare BREAK","artist":"5ban Graphics","imageUrl":"https://tcgcompanion.fra1.digitaloceanspaces.com/images/xy/xy12/46.png","imageUrlHiRes":"https://tcgcompanion.fra1.digitaloceanspaces.com/images/xy/xy12/46_hires.png"},{"cardId":"xy12-47","name":"Gastly","number":"47","rarity":"Common","artist":"Keiji Kinebuchi","imageUrl":"https://tcgcompanion.fra1.digitaloceanspaces.com/images/xy/xy12/47.png","imageUrlHiRes":"https://tcgcompanion.fra1.digitaloceanspaces.com/images/xy/xy12/47_hires.png"},{"cardId":"xy12-48","name":"Haunter","number":"48","rarity":"Uncommon","artist":"Keiji Kinebuchi","imageUrl":"https://tcgcompanion.fra1.digitaloceanspaces.com/images/xy/xy12/48.png","imageUrlHiRes":"https://tcgcompanion.fra1.digitaloceanspaces.com/images/xy/xy12/48_hires.png"},{"cardId":"xy12-49","name":"Drowzee","number":"49","rarity":"Common","artist":"Ken Sugimori","imageUrl":"https://tcgcompanion.fra1.digitaloceanspaces.com/images/xy/xy12/49.png","imageUrlHiRes":"https://tcgcompanion.fra1.digitaloceanspaces.com/images/xy/xy12/49_hires.png"},{"cardId":"xy12-50","name":"Koffing","number":"50","rarity":"Uncommon","artist":"Mitsuhiro Arita","imageUrl":"https://tcgcompanion.fra1.digitaloceanspaces.com/images/xy/xy12/50.png","imageUrlHiRes":"https://tcgcompanion.fra1.digitaloceanspaces.com/images/xy/xy12/50_hires.png"},{"cardId":"xy12-51","name":"Mewtwo","number":"51","rarity":"Rare","artist":"Ken Sugimori","imageUrl":"https://tcgcompanion.fra1.digitaloceanspaces.com/images/xy/xy12/51.png","imageUrlHiRes":"https://tcgcompanion.fra1.digitaloceanspaces.com/images/xy/xy12/51_hires.png"},{"cardId":"xy12-52","name":"Mewtwo-EX","number":"52","rarity":"Rare Holo EX","artist":"Eske Yoshinob","imageUrl":"https://tcgcompanion.fra1.digitaloceanspaces.com/images/xy/xy12/52.png","imageUrlHiRes":"https://tcgcompanion.fra1.digitaloceanspaces.com/images/xy/xy12/52_hires.png"},{"cardId":"xy12-53","name":"Mew","number":"53","rarity":"Rare Holo","artist":"Ken Sugimori","imageUrl":"https://tcgcompanion.fra1.digitaloceanspaces.com/images/xy/xy12/53.png","imageUrlHiRes":"https://tcgcompanion.fra1.digitaloceanspaces.com/images/xy/xy12/53_hires.png"},{"cardId":"xy12-54","name":"Sandshrew","number":"54","rarity":"Common","artist":"Ken Sugimori","imageUrl":"https://tcgcompanion.fra1.digitaloceanspaces.com/images/xy/xy12/54.png","imageUrlHiRes":"https://tcgcompanion.fra1.digitaloceanspaces.com/images/xy/xy12/54_hires.png"},{"cardId":"xy12-55","name":"Diglett","number":"55","rarity":"Common","artist":"Keiji Kinebuchi","imageUrl":"https://tcgcompanion.fra1.digitaloceanspaces.com/images/xy/xy12/55.png","imageUrlHiRes":"https://tcgcompanion.fra1.digitaloceanspaces.com/images/xy/xy12/55_hires.png"},{"cardId":"xy12-56","name":"Dugtrio","number":"56","rarity":"Rare","artist":"Keiji Kinebuchi","imageUrl":"https://tcgcompanion.fra1.digitaloceanspaces.com/images/xy/xy12/56.png","imageUrlHiRes":"https://tcgcompanion.fra1.digitaloceanspaces.com/images/xy/xy12/56_hires.png"},{"cardId":"xy12-57","name":"Machop","number":"57","rarity":"Common","artist":"Mitsuhiro Arita","imageUrl":"https://tcgcompanion.fra1.digitaloceanspaces.com/images/xy/xy12/57.png","imageUrlHiRes":"https://tcgcompanion.fra1.digitaloceanspaces.com/images/xy/xy12/57_hires.png"},{"cardId":"xy12-58","name":"Machoke","number":"58","rarity":"Uncommon","artist":"Ken Sugimori","imageUrl":"https://tcgcompanion.fra1.digitaloceanspaces.com/images/xy/xy12/58.png","imageUrlHiRes":"https://tcgcompanion.fra1.digitaloceanspaces.com/images/xy/xy12/58_hires.png"},{"cardId":"xy12-59","name":"Machamp","number":"59","rarity":"Rare Holo","artist":"Ken Sugimori","imageUrl":"https://tcgcompanion.fra1.digitaloceanspaces.com/images/xy/xy12/59.png","imageUrlHiRes":"https://tcgcompanion.fra1.digitaloceanspaces.com/images/xy/xy12/59_hires.png"},{"cardId":"xy12-60","name":"Machamp BREAK","number":"60","rarity":"Rare BREAK","artist":"5ban Graphics","imageUrl":"https://tcgcompanion.fra1.digitaloceanspaces.com/images/xy/xy12/60.png","imageUrlHiRes":"https://tcgcompanion.fra1.digitaloceanspaces.com/images/xy/xy12/60_hires.png"},{"cardId":"xy12-61","name":"Onix","number":"61","rarity":"Common","artist":"Ken Sugimori","imageUrl":"https://tcgcompanion.fra1.digitaloceanspaces.com/images/xy/xy12/61.png","imageUrlHiRes":"https://tcgcompanion.fra1.digitaloceanspaces.com/images/xy/xy12/61_hires.png"},{"cardId":"xy12-62","name":"Hitmonchan","number":"62","rarity":"Rare Holo","artist":"Ken Sugimori","imageUrl":"https://tcgcompanion.fra1.digitaloceanspaces.com/images/xy/xy12/62.png","imageUrlHiRes":"https://tcgcompanion.fra1.digitaloceanspaces.com/images/xy/xy12/62_hires.png"},{"cardId":"xy12-63","name":"Clefairy","number":"63","rarity":"Rare Holo","artist":"Ken Sugimori","imageUrl":"https://tcgcompanion.fra1.digitaloceanspaces.com/images/xy/xy12/63.png","imageUrlHiRes":"https://tcgcompanion.fra1.digitaloceanspaces.com/images/xy/xy12/63_hires.png"},{"cardId":"xy12-64","name":"Pidgeot-EX","number":"64","rarity":"Rare Holo EX","artist":"Eske Yoshinob","imageUrl":"https://tcgcompanion.fra1.digitaloceanspaces.com/images/xy/xy12/64.png","imageUrlHiRes":"https://tcgcompanion.fra1.digitaloceanspaces.com/images/xy/xy12/64_hires.png"},{"cardId":"xy12-65","name":"M Pidgeot-EX","number":"65","rarity":"Rare Holo EX","artist":"5ban Graphics","imageUrl":"https://tcgcompanion.fra1.digitaloceanspaces.com/images/xy/xy12/65.png","imageUrlHiRes":"https://tcgcompanion.fra1.digitaloceanspaces.com/images/xy/xy12/65_hires.png"},{"cardId":"xy12-66","name":"Rattata","number":"66","rarity":"Common","artist":"Mitsuhiro Arita","imageUrl":"https://tcgcompanion.fra1.digitaloceanspaces.com/images/xy/xy12/66.png","imageUrlHiRes":"https://tcgcompanion.fra1.digitaloceanspaces.com/images/xy/xy12/66_hires.png"},{"cardId":"xy12-67","name":"Raticate","number":"67","rarity":"Rare","artist":"Ken Sugimori","imageUrl":"https://tcgcompanion.fra1.digitaloceanspaces.com/images/xy/xy12/67.png","imageUrlHiRes":"https://tcgcompanion.fra1.digitaloceanspaces.com/images/xy/xy12/67_hires.png"},{"cardId":"xy12-68","name":"Farfetch'd","number":"68","rarity":"Rare","artist":"Ken Sugimori","imageUrl":"https://tcgcompanion.fra1.digitaloceanspaces.com/images/xy/xy12/68.png","imageUrlHiRes":"https://tcgcompanion.fra1.digitaloceanspaces.com/images/xy/xy12/68_hires.png"},{"cardId":"xy12-69","name":"Doduo","number":"69","rarity":"Common","artist":"Mitsuhiro Arita","imageUrl":"https://tcgcompanion.fra1.digitaloceanspaces.com/images/xy/xy12/69.png","imageUrlHiRes":"https://tcgcompanion.fra1.digitaloceanspaces.com/images/xy/xy12/69_hires.png"},{"cardId":"xy12-70","name":"Chansey","number":"70","rarity":"Rare Holo","artist":"Ken Sugimori","imageUrl":"https://tcgcompanion.fra1.digitaloceanspaces.com/images/xy/xy12/70.png","imageUrlHiRes":"https://tcgcompanion.fra1.digitaloceanspaces.com/images/xy/xy12/70_hires.png"},{"cardId":"xy12-71","name":"Porygon","number":"71","rarity":"Uncommon","artist":"Tomoaki Imakuni","imageUrl":"https://tcgcompanion.fra1.digitaloceanspaces.com/images/xy/xy12/71.png","imageUrlHiRes":"https://tcgcompanion.fra1.digitaloceanspaces.com/images/xy/xy12/71_hires.png"},{"cardId":"xy12-72","name":"Dragonite-EX","number":"72","rarity":"Rare Holo EX","artist":"Ayaka Yoshida","imageUrl":"https://tcgcompanion.fra1.digitaloceanspaces.com/images/xy/xy12/72.png","imageUrlHiRes":"https://tcgcompanion.fra1.digitaloceanspaces.com/images/xy/xy12/72_hires.png"},{"cardId":"xy12-73","name":"Blastoise Spirit Link","number":"73","rarity":"Uncommon","artist":"5ban Graphics","imageUrl":"https://tcgcompanion.fra1.digitaloceanspaces.com/images/xy/xy12/73.png","imageUrlHiRes":"https://tcgcompanion.fra1.digitaloceanspaces.com/images/xy/xy12/73_hires.png"},{"cardId":"xy12-74","name":"Brock's Grit","number":"74","rarity":"Uncommon","artist":"Ken Sugimori","imageUrl":"https://tcgcompanion.fra1.digitaloceanspaces.com/images/xy/xy12/74.png","imageUrlHiRes":"https://tcgcompanion.fra1.digitaloceanspaces.com/images/xy/xy12/74_hires.png"},{"cardId":"xy12-75","name":"Charizard Spirit Link","number":"75","rarity":"Uncommon","artist":"5ban Graphics","imageUrl":"https://tcgcompanion.fra1.digitaloceanspaces.com/images/xy/xy12/75.png","imageUrlHiRes":"https://tcgcompanion.fra1.digitaloceanspaces.com/images/xy/xy12/75_hires.png"},{"cardId":"xy12-76","name":"Devolution Spray","number":"76","rarity":"Uncommon","artist":"Keiji Kinebuchi","imageUrl":"https://tcgcompanion.fra1.digitaloceanspaces.com/images/xy/xy12/76.png","imageUrlHiRes":"https://tcgcompanion.fra1.digitaloceanspaces.com/images/xy/xy12/76_hires.png"},{"cardId":"xy12-77","name":"Energy Retrieval","number":"77","rarity":"Uncommon","artist":"Keiji Kinebuchi","imageUrl":"https://tcgcompanion.fra1.digitaloceanspaces.com/images/xy/xy12/77.png","imageUrlHiRes":"https://tcgcompanion.fra1.digitaloceanspaces.com/images/xy/xy12/77_hires.png"},{"cardId":"xy12-78","name":"Full Heal","number":"78","rarity":"Uncommon","artist":"Keiji Kinebuchi","imageUrl":"https://tcgcompanion.fra1.digitaloceanspaces.com/images/xy/xy12/78.png","imageUrlHiRes":"https://tcgcompanion.fra1.digitaloceanspaces.com/images/xy/xy12/78_hires.png"},{"cardId":"xy12-79","name":"Maintenance","number":"79","rarity":"Uncommon","artist":"Keiji Kinebuchi","imageUrl":"https://tcgcompanion.fra1.digitaloceanspaces.com/images/xy/xy12/79.png","imageUrlHiRes":"https://tcgcompanion.fra1.digitaloceanspaces.com/images/xy/xy12/79_hires.png"},{"cardId":"xy12-80","name":"Misty's Determination","number":"80","rarity":"Uncommon","artist":"Ken Sugimori","imageUrl":"https://tcgcompanion.fra1.digitaloceanspaces.com/images/xy/xy12/80.png","imageUrlHiRes":"https://tcgcompanion.fra1.digitaloceanspaces.com/images/xy/xy12/80_hires.png"},{"cardId":"xy12-81","name":"Pidgeot Spirit Link","number":"81","rarity":"Uncommon","artist":"5ban Graphics","imageUrl":"https://tcgcompanion.fra1.digitaloceanspaces.com/images/xy/xy12/81.png","imageUrlHiRes":"https://tcgcompanion.fra1.digitaloceanspaces.com/images/xy/xy12/81_hires.png"},{"cardId":"xy12-82","name":"Pokédex","number":"82","rarity":"Uncommon","artist":"Keiji Kinebuchi","imageUrl":"https://tcgcompanion.fra1.digitaloceanspaces.com/images/xy/xy12/82.png","imageUrlHiRes":"https://tcgcompanion.fra1.digitaloceanspaces.com/images/xy/xy12/82_hires.png"},{"cardId":"xy12-83","name":"Potion","number":"83","rarity":"Uncommon","artist":"Keiji Kinebuchi","imageUrl":"https://tcgcompanion.fra1.digitaloceanspaces.com/images/xy/xy12/83.png","imageUrlHiRes":"https://tcgcompanion.fra1.digitaloceanspaces.com/images/xy/xy12/83_hires.png"},{"cardId":"xy12-84","name":"Professor Oak's Hint","number":"84","rarity":"Uncommon","artist":"Ken Sugimori","imageUrl":"https://tcgcompanion.fra1.digitaloceanspaces.com/images/xy/xy12/84.png","imageUrlHiRes":"https://tcgcompanion.fra1.digitaloceanspaces.com/images/xy/xy12/84_hires.png"},{"cardId":"xy12-85","name":"Revive","number":"85","rarity":"Uncommon","artist":"Keiji Kinebuchi","imageUrl":"https://tcgcompanion.fra1.digitaloceanspaces.com/images/xy/xy12/85.png","imageUrlHiRes":"https://tcgcompanion.fra1.digitaloceanspaces.com/images/xy/xy12/85_hires.png"},{"cardId":"xy12-86","name":"Slowbro Spirit Link","number":"86","rarity":"Uncommon","artist":"5ban Graphics","imageUrl":"https://tcgcompanion.fra1.digitaloceanspaces.com/images/xy/xy12/86.png","imageUrlHiRes":"https://tcgcompanion.fra1.digitaloceanspaces.com/images/xy/xy12/86_hires.png"},{"cardId":"xy12-87","name":"Super Potion","number":"87","rarity":"Uncommon","artist":"Keiji Kinebuchi","imageUrl":"https://tcgcompanion.fra1.digitaloceanspaces.com/images/xy/xy12/87.png","imageUrlHiRes":"https://tcgcompanion.fra1.digitaloceanspaces.com/images/xy/xy12/87_hires.png"},{"cardId":"xy12-88","name":"Switch","number":"88","rarity":"Uncommon","artist":"Keiji Kinebuchi","imageUrl":"https://tcgcompanion.fra1.digitaloceanspaces.com/images/xy/xy12/88.png","imageUrlHiRes":"https://tcgcompanion.fra1.digitaloceanspaces.com/images/xy/xy12/88_hires.png"},{"cardId":"xy12-89","name":"Venusaur Spirit Link","number":"89","rarity":"Uncommon","artist":"5ban Graphics","imageUrl":"https://tcgcompanion.fra1.digitaloceanspaces.com/images/xy/xy12/89.png","imageUrlHiRes":"https://tcgcompanion.fra1.digitaloceanspaces.com/images/xy/xy12/89_hires.png"},{"cardId":"xy12-90","name":"Double Colorless Energy","number":"90","rarity":"Uncommon","artist":"Keiji Kinebuchi","imageUrl":"https://tcgcompanion.fra1.digitaloceanspaces.com/images/xy/xy12/90.png","imageUrlHiRes":"https://tcgcompanion.fra1.digitaloceanspaces.com/images/xy/xy12/90_hires.png"},{"cardId":"xy12-91","name":"Grass Energy","number":"91","rarity":"Common","artist":"","imageUrl":"https://tcgcompanion.fra1.digitaloceanspaces.com/images/xy/xy12/91.png","imageUrlHiRes":"https://tcgcompanion.fra1.digitaloceanspaces.com/images/xy/xy12/91_hires.png"},{"cardId":"xy12-92","name":"Fire Energy","number":"92","rarity":"Common","artist":"","imageUrl":"https://tcgcompanion.fra1.digitaloceanspaces.com/images/xy/xy12/92.png","imageUrlHiRes":"https://tcgcompanion.fra1.digitaloceanspaces.com/images/xy/xy12/92_hires.png"},{"cardId":"xy12-93","name":"Water Energy","number":"93","rarity":"Common","artist":"","imageUrl":"https://tcgcompanion.fra1.digitaloceanspaces.com/images/xy/xy12/93.png","imageUrlHiRes":"https://tcgcompanion.fra1.digitaloceanspaces.com/images/xy/xy12/93_hires.png"},{"cardId":"xy12-94","name":"Lightning Energy","number":"94","rarity":"Common","artist":"","imageUrl":"https://tcgcompanion.fra1.digitaloceanspaces.com/images/xy/xy12/94.png","imageUrlHiRes":"https://tcgcompanion.fra1.digitaloceanspaces.com/images/xy/xy12/94_hires.png"},{"cardId":"xy12-95","name":"Psychic Energy","number":"95","rarity":"Common","artist":"","imageUrl":"https://tcgcompanion.fra1.digitaloceanspaces.com/images/xy/xy12/95.png","imageUrlHiRes":"https://tcgcompanion.fra1.digitaloceanspaces.com/images/xy/xy12/95_hires.png"},{"cardId":"xy12-96","name":"Fighting Energy","number":"96","rarity":"Common","artist":"","imageUrl":"https://tcgcompanion.fra1.digitaloceanspaces.com/images/xy/xy12/96.png","imageUrlHiRes":"https://tcgcompanion.fra1.digitaloceanspaces.com/images/xy/xy12/96_hires.png"},{"cardId":"xy12-97","name":"Darkness Energy","number":"97","rarity":"Common","artist":"","imageUrl":"https://tcgcompanion.fra1.digitaloceanspaces.com/images/xy/xy12/97.png","imageUrlHiRes":"https://tcgcompanion.fra1.digitaloceanspaces.com/images/xy/xy12/97_hires.png"},{"cardId":"xy12-98","name":"Metal Energy","number":"98","rarity":"Common","artist":"","imageUrl":"https://tcgcompanion.fra1.digitaloceanspaces.com/images/xy/xy12/98.png","imageUrlHiRes":"https://tcgcompanion.fra1.digitaloceanspaces.com/images/xy/xy12/98_hires.png"},{"cardId":"xy12-99","name":"Fairy Energy","number":"99","rarity":"Common","artist":"","imageUrl":"https://tcgcompanion.fra1.digitaloceanspaces.com/images/xy/xy12/99.png","imageUrlHiRes":"https://tcgcompanion.fra1.digitaloceanspaces.com/images/xy/xy12/99_hires.png"},{"cardId":"xy12-100","name":"M Venusaur-EX","number":"100","rarity":"Rare Ultra","artist":"5ban Graphics","imageUrl":"https://tcgcompanion.fra1.digitaloceanspaces.com/images/xy/xy12/100.png","imageUrlHiRes":"https://tcgcompanion.fra1.digitaloceanspaces.com/images/xy/xy12/100_hires.png"},{"cardId":"xy12-101","name":"M Charizard-EX","number":"101","rarity":"Rare Ultra","artist":"5ban Graphics","imageUrl":"https://tcgcompanion.fra1.digitaloceanspaces.com/images/xy/xy12/101.png","imageUrlHiRes":"https://tcgcompanion.fra1.digitaloceanspaces.com/images/xy/xy12/101_hires.png"},{"cardId":"xy12-102","name":"M Blastoise-EX","number":"102","rarity":"Rare Ultra","artist":"5ban Graphics","imageUrl":"https://tcgcompanion.fra1.digitaloceanspaces.com/images/xy/xy12/102.png","imageUrlHiRes":"https://tcgcompanion.fra1.digitaloceanspaces.com/images/xy/xy12/102_hires.png"},{"cardId":"xy12-103","name":"Mewtwo-EX","number":"103","rarity":"Rare Ultra","artist":"Ryo Ueda","imageUrl":"https://tcgcompanion.fra1.digitaloceanspaces.com/images/xy/xy12/103.png","imageUrlHiRes":"https://tcgcompanion.fra1.digitaloceanspaces.com/images/xy/xy12/103_hires.png"},{"cardId":"xy12-104","name":"Pidgeot-EX","number":"104","rarity":"Rare Ultra","artist":"Ryo Ueda","imageUrl":"https://tcgcompanion.fra1.digitaloceanspaces.com/images/xy/xy12/104.png","imageUrlHiRes":"https://tcgcompanion.fra1.digitaloceanspaces.com/images/xy/xy12/104_hires.png"},{"cardId":"xy12-105","name":"M Pidgeot-EX","number":"105","rarity":"Rare Ultra","artist":"5ban Graphics","imageUrl":"https://tcgcompanion.fra1.digitaloceanspaces.com/images/xy/xy12/105.png","imageUrlHiRes":"https://tcgcompanion.fra1.digitaloceanspaces.com/images/xy/xy12/105_hires.png"},{"cardId":"xy12-106","name":"Dragonite-EX","number":"106","rarity":"Rare Ultra","artist":"Ryo Ueda","imageUrl":"https://tcgcompanion.fra1.digitaloceanspaces.com/images/xy/xy12/106.png","imageUrlHiRes":"https://tcgcompanion.fra1.digitaloceanspaces.com/images/xy/xy12/106_hires.png"},{"cardId":"xy12-107","name":"Brock's Grit","number":"107","rarity":"Rare Ultra","artist":"Hitoshi Ariga","imageUrl":"https://tcgcompanion.fra1.digitaloceanspaces.com/images/xy/xy12/107.png","imageUrlHiRes":"https://tcgcompanion.fra1.digitaloceanspaces.com/images/xy/xy12/107_hires.png"},{"cardId":"xy12-108","name":"Misty's Determination","number":"108","rarity":"Rare Ultra","artist":"Megumi Mizutani","imageUrl":"https://tcgcompanion.fra1.digitaloceanspaces.com/images/xy/xy12/108.png","imageUrlHiRes":"https://tcgcompanion.fra1.digitaloceanspaces.com/images/xy/xy12/108_hires.png"},{"cardId":"xy12-109","name":"ナッシー[Exeggutor]","number":"109","rarity":"Rare Secret","artist":"Dr.Ooyama","imageUrl":"https://tcgcompanion.fra1.digitaloceanspaces.com/images/xy/xy12/109.png","imageUrlHiRes":"https://tcgcompanion.fra1.digitaloceanspaces.com/images/xy/xy12/109_hires.png"},{"cardId":"xy12-110","name":"Flying Pikachu","number":"110","rarity":"Rare Secret","artist":"Toshinao Aoki","imageUrl":"https://tcgcompanion.fra1.digitaloceanspaces.com/images/xy/xy12/110.png","imageUrlHiRes":"https://tcgcompanion.fra1.digitaloceanspaces.com/images/xy/xy12/110_hires.png"},{"cardId":"xy12-111","name":"Surfing Pikachu","number":"111","rarity":"Rare Secret","artist":"Toshinao Aoki","imageUrl":"https://tcgcompanion.fra1.digitaloceanspaces.com/images/xy/xy12/111.png","imageUrlHiRes":"https://tcgcompanion.fra1.digitaloceanspaces.com/images/xy/xy12/111_hires.png"},{"cardId":"xy12-112","name":"Imakuni?'s Doduo","number":"112","rarity":"Rare Secret","artist":"Imakuni?","imageUrl":"https://tcgcompanion.fra1.digitaloceanspaces.com/images/xy/xy12/112.png","imageUrlHiRes":"https://tcgcompanion.fra1.digitaloceanspaces.com/images/xy/xy12/112_hires.png"},{"cardId":"xy12-113","name":"Here Comes Team Rocket!","number":"113","rarity":"Rare Secret","artist":"Ken Sugimori","imageUrl":"https://tcgcompanion.fra1.digitaloceanspaces.com/images/xy/xy12/113.png","imageUrlHiRes":"https://tcgcompanion.fra1.digitaloceanspaces.com/images/xy/xy12/113_hires.png"}]